Workbook
Name _day1: '4_4_請求書'!$AZ$5
Name _day1: '4_4_納品書'!$AZ$10
Name _day1: #REF!
Name _day1: #REF!
Name _day1: #REF!
Name _day1: #REF!
Name _day2: '4_4_請求書'!$AZ$10
Name _day2: '4_4_納品書'!#REF!
Name _day2: #REF!
Name _day2: #REF!
Name _day2: #REF!
Name _day2: #REF!
Name excluded: '4_4_請求書'!#REF!
Name excluded: '4_4_納品書'!$BE$3
Name excluded: #REF!
Name excluded: #REF!
Name excluded: #REF!
Name excluded: #REF!
Name exclusive: #REF!
Name exclusive: #REF!
Name exclusive: #REF!
Name exclusive: #REF!
Name exclusive: #REF!
Name exclusive: #REF!
Name exclusive: #REF!
Name exclusive: #REF!
Name exclusive: #REF!
Name exclusive: #REF!
Name exclusive: #REF!
Name exclusive: #REF!
Name exclusive: #REF!
Name exclusive: #REF!
Name exclusive: #REF!
Name exclusive: #REF!
Name exclusive: #REF!
Name exclusive: #REF!
Name exclusive: #REF!
Name exclusive: #REF!
Name exclusive: #REF!
Name exclusive: #REF!
Name exclusive: '4_5_領収書'!$BD$5
Name exclusive: #REF!
Name exclusive: #REF!
Name exclusive: #REF!
Name exclusive: #REF!
Name exclusive: #REF!
Name exclusive: #REF!
Name exclusive: #REF!
Name exclusive: #REF!
Name exclusive: #REF!
Name exclusive: #REF!
Name exclusive: #REF!
Name exclusive: #REF!
Name exclusive: #REF!
Name exclusive: #REF!
Name exclusive: #REF!
Name exemption: '4_4_請求書'!#REF!
Name exemption: '4_4_納品書'!$BF$3
Name hutan: #REF!
Name hutan: #REF!

Sheet 管理
B1: 請求書発行者 | C1: 9 | E1: 請求日 | F1: =[1]請求書管理!$F1 -> 46097 | H1: 納品日 | I1: =[1]請求書管理!$I1 -> 46097 | K1: 領収日 | L1: =[1]請求書管理!$L1 -> 46105 | N1: お支払期限 | O1: =[1]請求書管理!$O1 -> 46105
B2: 購入者 | C2: 103 | E2: 件名： | F2: =[1]請求書管理!$F2 -> 2026年3月16日分のお取引に関するご請求書
A3: =[1]請求書管理!$A3 -> № | B3: =[1]請求書管理!$B3 -> 社名 | C3: =[1]請求書管理!$C3 -> 郵便番号 | D3: =[1]請求書管理!$D3 -> 住所1 | E3: =[1]請求書管理!$E3 -> 住所2 | F3: =[1]請求書管理!$F3 -> TEL | G3: =[1]請求書管理!$G3 -> FAX | H3: =[1]請求書管理!$H3 -> WEB | I3: =[1]請求書管理!$I3 -> 担当者 | J3: =[1]請求書管理!$J3 -> mail | K3: =[1]請求書管理!$K3 -> 登録番号 | L3: =[1]請求書管理!$L3 -> 振込先 | M3: =[1]請求書管理!$M3 -> 口座名義 | N3: =[1]請求書管理!$N3 -> お客様コード | O3: =[1]請求書管理!$O3 -> sandisk有無 | P3: =[1]請求書管理!$P3 -> sandiskURL | Q3: 請求書№ | R3: 納品書№ | S3: 領収書№
A4: =[1]請求書管理!$A4 -> 1 | B4: =[1]請求書管理!$B4 -> ダイワボウ情報システム株式会社 | C4: =[1]請求書管理!$C4 -> 530-0005 | D4: =[1]請求書管理!$D4 -> 大阪府大阪市北区中之島3丁目2番4号 | E4: =[1]請求書管理!$E4 -> 中之島フェスティバルタワー・ウエスト 10F | F4: =[1]請求書管理!$F4 -> 06-4707-8000 | G4: =[1]請求書管理!$G4 -> 06-4707-8052 | H4: =[1]請求書管理!$H4 -> https://www.pc-daiwabo.co.jp | I4: =[1]請求書管理!$I4 -> 担当事業所：東京第1支店 韋駄天事業部 | J4: =[1]請求書管理!$J4 -> mail：idaten-c@pc-daiwabo.co.jp | K4: =[1]請求書管理!$K4 -> T6120001083217 | L4: =[1]請求書管理!$L4 -> 三菱ＵＦＪ銀行 船場支店 普通 7077113 | M4: =[1]請求書管理!$M4 -> ダイワボウジョウホウシステム（カ | N4: =[1]請求書管理!$N4 -> 5824-111 | O4: =[1]請求書管理!$O4 -> ◎ | P4: =[1]請求書管理!$P4 -> https://www.pc-daiwabo.co.jp/business/maker_list_s.html | Q4: =[1]請求書管理!$Q4 -> INV-260316-101 | R4: =[1]請求書管理!$R4 -> DEL-260316-101 | S4: =[1]請求書管理!$S4 -> REC-260324-101
A5: =[1]請求書管理!$A5 -> 2 | B5: =[1]請求書管理!$B5 -> 東映無線株式会社 | C5: =[1]請求書管理!$C5 -> 101-0021 | D5: =[1]請求書管理!$D5 -> 東京都千代田区外神田1丁目10番11号 | E5: =[1]請求書管理!$E5 -> 東京ラジオデパート内 | F5: =[1]請求書管理!$F5 -> 03-3253-5660 | G5: =[1]請求書管理!$G5 -> 03-3253-5661 | H5: =[1]請求書管理!$H5 -> http://www.toeimusen.co.jp | I5: =[1]請求書管理!$I5 -> 営業部 浜田英夫 | J5: =[1]請求書管理!$J5 -> E-MAIL：th＠toeimusen.co.jp | K5: =[1]請求書管理!$K5 -> T1010001023790 | L5: =[1]請求書管理!$L5 -> 三菱ＵＦＪ銀行 神田駅前支店 当座 2025636 | M5: =[1]請求書管理!$M5 -> トウエイムセン（カ | N5: =[1]請求書管理!$N5 -> 7391-112 | O5: =[1]請求書管理!$O5 -> × | P5: =[1]請求書管理!$P5 -> 0 | Q5: =[1]請求書管理!$Q5 -> INV-260316-102 | R5: =[1]請求書管理!$R5 -> DEL-260316-102 | S5: =[1]請求書管理!$S5 -> REC-260324-102
A6: =[1]請求書管理!$A6 -> 3 | B6: =[1]請求書管理!$B6 -> 浜田電機株式会社 | C6: =[1]請求書管理!$C6 -> 103-0023 | D6: =[1]請求書管理!$D6 -> 東京都中央区日本橋本町3丁目9番4号 | E6: =[1]請求書管理!$E6 -> 0 | F6: =[1]請求書管理!$F6 -> 03-5651-7351 | G6: =[1]請求書管理!$G6 -> 03-5651-7353 | H6: =[1]請求書管理!$H6 -> https://www.hamada-dk.com | I6: =[1]請求書管理!$I6 -> 浜田 健太郎 | J6: =[1]請求書管理!$J6 -> E-MAIL：ke-hamda@hamada-dk.co.jp | K6: =[1]請求書管理!$K6 -> T6010001026302 | L6: =[1]請求書管理!$L6 -> みずほ銀行 神田支店 普通7014121 | M6: =[1]請求書管理!$M6 -> ハマダデンキ（カ | N6: =[1]請求書管理!$N6 -> 1648-113 | O6: =[1]請求書管理!$O6 -> × | P6: =[1]請求書管理!$P6 -> 0 | Q6: =[1]請求書管理!$Q6 -> INV-260316-103 | R6: =[1]請求書管理!$R6 -> DEL-260316-103 | S6: =[1]請求書管理!$S6 -> REC-260324-103
A7: =[1]請求書管理!$A7 -> 4 | B7: =[1]請求書管理!$B7 -> ウエスタンデジタル合同会社 | C7: =[1]請求書管理!$C7 -> 108-0075 | D7: =[1]請求書管理!$D7 -> 東京都港区港南1丁目6番31号 | E7: =[1]請求書管理!$E7 -> 品川東急ビル3階 | F7: =[1]請求書管理!$F7 -> 0120-893-009 | G7: =[1]請求書管理!$G7 -> 0 | H7: =[1]請求書管理!$H7 -> https://shop.sandisk.com | I7: =[1]請求書管理!$I7 -> 0 | J7: =[1]請求書管理!$J7 -> E-MAIL：westerndigital_jp@custhelp.com | K7: =[1]請求書管理!$K7 -> T2010401090562 | L7: =[1]請求書管理!$L7 -> みずほ銀行 品川支店 普通7759780 | M7: =[1]請求書管理!$M7 -> ウエスタンデジタル（ド | N7: =[1]請求書管理!$N7 -> 9057-114 | O7: =[1]請求書管理!$O7 -> ◎ | P7: =[1]請求書管理!$P7 -> 0 | Q7: =[1]請求書管理!$Q7 -> INV-260316-104 | R7: =[1]請求書管理!$R7 -> DEL-260316-104 | S7: =[1]請求書管理!$S7 -> REC-260324-104
A8: =[1]請求書管理!$A8 -> 5 | B8: =[1]請求書管理!$B8 -> 株式会社アーキサイト | C8: =[1]請求書管理!$C8 -> 110-0006 | D8: =[1]請求書管理!$D8 -> 東京都台東区秋葉原5番9号 | E8: =[1]請求書管理!$E8 -> 明治安田生命秋葉原ビル | F8: =[1]請求書管理!$F8 -> 03-6859-0281 | G8: =[1]請求書管理!$G8 -> 03-6859-0282 | H8: =[1]請求書管理!$H8 -> https://archisite.co.jp | I8: =[1]請求書管理!$I8 -> 大谷 謙 | J8: =[1]請求書管理!$J8 -> e-mail：koya@archisite.co.jp | K8: =[1]請求書管理!$K8 -> T3010001075632 | L8: =[1]請求書管理!$L8 -> みずほ 銀行本郷 支店 (普) 口座 2681066 | M8: =[1]請求書管理!$M8 -> カ）アーキサイト | N8: =[1]請求書管理!$N8 -> 2483-115 | O8: =[1]請求書管理!$O8 -> × | P8: =[1]請求書管理!$P8 -> 0 | Q8: =[1]請求書管理!$Q8 -> INV-260316-105 | R8: =[1]請求書管理!$R8 -> DEL-260316-105 | S8: =[1]請求書管理!$S8 -> REC-260324-105
A9: =[1]請求書管理!$A9 -> 6 | B9: =[1]請求書管理!$B9 -> TD SYNNEX株式会社 | C9: =[1]請求書管理!$C9 -> 108-0023 | D9: =[1]請求書管理!$D9 -> 東京都港区芝浦3丁目1番1号 | E9: =[1]請求書管理!$E9 -> msb Tamachi 田町ステーションタワーN 21階 | F9: =[1]請求書管理!$F9 -> 03-4595-4550 | G9: =[1]請求書管理!$G9 -> 03-5931-0618 | H9: =[1]請求書管理!$H9 -> https://jp.tdsynnex.com | I9: =[1]請求書管理!$I9 -> 担当：村林 | J9: =[1]請求書管理!$J9 -> t-murabayashi@synnex.co.jp | K9: =[1]請求書管理!$K9 -> T6010601037905 | L9: =[1]請求書管理!$L9 -> 三菱UFJ銀行 田町支店 普通 4576541 | M9: =[1]請求書管理!$M9 -> ティーディーシネックス（カ | N9: =[1]請求書管理!$N9 -> 6712-116 | O9: =[1]請求書管理!$O9 -> ◎ | P9: =[1]請求書管理!$P9 -> https://jp.tdsynnex.com/vendor/vendors#line_sa | Q9: =[1]請求書管理!$Q9 -> INV-260316-106 | R9: =[1]請求書管理!$R9 -> DEL-260316-106 | S9: =[1]請求書管理!$S9 -> REC-260324-106
A10: =[1]請求書管理!$A10 -> 7 | B10: =[1]請求書管理!$B10 -> SB C&S株式会社 | C10: =[1]請求書管理!$C10 -> 105-7529 | D10: =[1]請求書管理!$D10 -> 東京都港区海岸1丁目7番1号 | E10: =[1]請求書管理!$E10 -> 東京ポートシティ竹芝オフィスタワー | F10: =[1]請求書管理!$F10 -> 03-6858-6470 | G10: =[1]請求書管理!$G10 -> 0 | H10: =[1]請求書管理!$H10 -> https://cas.softbank.jp | I10: =[1]請求書管理!$I10 -> 0 | J10: =[1]請求書管理!$J10 -> 0 | K10: =[1]請求書管理!$K10 -> T9010403011485 | L10: =[1]請求書管理!$L10 -> 三菱UFJ銀行 新橋支店 普通 9514626 | M10: =[1]請求書管理!$M10 -> エスビー シーアンドエス（カ | N10: =[1]請求書管理!$N10 -> 4309-117 | O10: =[1]請求書管理!$O10 -> ◎ | P10: =[1]請求書管理!$P10 -> https://www.it-ex.com/makers/ | Q10: =[1]請求書管理!$Q10 -> INV-260316-107 | R10: =[1]請求書管理!$R10 -> DEL-260316-107 | S10: =[1]請求書管理!$S10 -> REC-260324-107
A11: =[1]請求書管理!$A11 -> 8 | B11: =[1]請求書管理!$B11 -> Hamee株式会社 | C11: =[1]請求書管理!$C11 -> 250-0011 | D11: =[1]請求書管理!$D11 -> 神奈川県小田原市栄町2丁目12番10号 | E11: =[1]請求書管理!$E11 -> Square O2 | F11: =[1]請求書管理!$F11 -> 0465-22-8064 | G11: =[1]請求書管理!$G11 -> 0465-22-8065 | H11: =[1]請求書管理!$H11 -> https://hamee.co.jp | I11: =[1]請求書管理!$I11 -> 0 | J11: =[1]請求書管理!$J11 -> oroshi@hamee.co.jp | K11: =[1]請求書管理!$K11 -> T9021001033474 | L11: =[1]請求書管理!$L11 -> みずほ銀行 小田原支店 普通1429575 | M11: =[1]請求書管理!$M11 -> ハミィ（カ | N11: =[1]請求書管理!$N11 -> 8935-118 | O11: =[1]請求書管理!$O11 -> × | P11: =[1]請求書管理!$P11 -> 0 | Q11: =[1]請求書管理!$Q11 -> INV-260316-108 | R11: =[1]請求書管理!$R11 -> DEL-260316-108 | S11: =[1]請求書管理!$S11 -> REC-260324-108
A12: =[1]請求書管理!$A12 -> 9 | B12: =[1]請求書管理!$B12 -> サンディスク合同会社 | C12: =[1]請求書管理!$C12 -> 108-0075 | D12: =[1]請求書管理!$D12 -> 東京都港区港南1丁目6番31号 | E12: =[1]請求書管理!$E12 -> 品川東急ビル3階 | F12: =[1]請求書管理!$F12 -> 0120-893-009 | G12: =[1]請求書管理!$G12 -> 0 | H12: =[1]請求書管理!$H12 -> https://www.sandisk.com | I12: =[1]請求書管理!$I12 -> 0 | J12: =[1]請求書管理!$J12 -> retail_support@sandisk.com | K12: =[1]請求書管理!$K12 -> T2010401090562 | L12: =[1]請求書管理!$L12 -> みずほ銀行 品川支店 普通7759780 | M12: =[1]請求書管理!$M12 -> サンディスク（ド | N12: =[1]請求書管理!$N12 -> 3176-119 | O12: =[1]請求書管理!$O12 -> ◎ | P12: =[1]請求書管理!$P12 -> 0 | Q12: =[1]請求書管理!$Q12 -> INV-260316-109 | R12: =[1]請求書管理!$R12 -> DEL-260316-109 | S12: =[1]請求書管理!$S12 -> REC-260324-109
A13: =[1]請求書管理!$A13 -> 10 | B13: =[1]請求書管理!$B13 -> シー・エフ・デー販売株式会社 | C13: =[1]請求書管理!$C13 -> 460-8315 | D13: =[1]請求書管理!$D13 -> 愛知県名古屋市中区大須3丁目30番20号 | E13: =[1]請求書管理!$E13 -> 赤門通ビル | F13: =[1]請求書管理!$F13 -> 052-249-6606 | G13: =[1]請求書管理!$G13 -> 050-5830-8824 | H13: =[1]請求書管理!$H13 -> https://www.cfd.co.jp | I13: =[1]請求書管理!$I13 -> 0 | J13: =[1]請求書管理!$J13 -> corporate@cfd.co.jp | K13: =[1]請求書管理!$K13 -> T1180001051148 | L13: =[1]請求書管理!$L13 -> 三菱ＵＦＪ銀行 名古屋営業部 普通預金 1488133 | M13: =[1]請求書管理!$M13 -> シー・エフ・デーハンバイ（カ | N13: =[1]請求書管理!$N13 -> 7542-120 | O13: =[1]請求書管理!$O13 -> ◎ | P13: =[1]請求書管理!$P13 -> https://www.cfd.co.jp/biz/brand/sandisk.html#maker-category | Q13: =[1]請求書管理!$Q13 -> INV-260316-110 | R13: =[1]請求書管理!$R13 -> DEL-260316-110 | S13: =[1]請求書管理!$S13 -> REC-260324-110
A14: =[1]請求書管理!$A14 -> 11 | B14: =[1]請求書管理!$B14 -> 加賀電子株式会社 | C14: =[1]請求書管理!$C14 -> 101-8629 | D14: =[1]請求書管理!$D14 -> 東京都千代田区神田松永町20番地 | E14: =[1]請求書管理!$E14 -> 0 | F14: =[1]請求書管理!$F14 -> 03-5657-0111 | G14: =[1]請求書管理!$G14 -> 03-3254-7131 | H14: =[1]請求書管理!$H14 -> https://www.taxan.co.jp/jp | I14: =[1]請求書管理!$I14 -> 0 | J14: =[1]請求書管理!$J14 -> sales2@taxan.co.jp | K14: =[1]請求書管理!$K14 -> T4010001001752 | L14: =[1]請求書管理!$L14 -> みずほ銀行 神田支店 普通7054169 | M14: =[1]請求書管理!$M14 -> カガデンシ（カ | N14: =[1]請求書管理!$N14 -> 2698-121 | O14: =[1]請求書管理!$O14 -> × | P14: =[1]請求書管理!$P14 -> 0 | Q14: =[1]請求書管理!$Q14 -> INV-260316-111 | R14: =[1]請求書管理!$R14 -> DEL-260316-111 | S14: =[1]請求書管理!$S14 -> REC-260324-111
A15: =[1]請求書管理!$A15 -> 12 | B15: =[1]請求書管理!$B15 -> 丸文株式会社 | C15: =[1]請求書管理!$C15 -> 103-8577 | D15: =[1]請求書管理!$D15 -> 東京都中央区日本橋大伝馬町8番1号 | E15: =[1]請求書管理!$E15 -> 0 | F15: =[1]請求書管理!$F15 -> 03-3639-9801 | G15: =[1]請求書管理!$G15 -> 03-3669-2304 | H15: =[1]請求書管理!$H15 -> https://www.marubun.co.jp | I15: =[1]請求書管理!$I15 -> 0 | J15: =[1]請求書管理!$J15 -> info@marubun.co.jp | K15: =[1]請求書管理!$K15 -> T8010001057337 | L15: =[1]請求書管理!$L15 -> 三菱UFJ銀行 大伝馬町支店 普通9914787 | M15: =[1]請求書管理!$M15 -> マルブン（カ | N15: =[1]請求書管理!$N15 -> 6081-122 | O15: =[1]請求書管理!$O15 -> ◎ | P15: =[1]請求書管理!$P15 -> https://www.marubun.co.jp/maker/ | Q15: =[1]請求書管理!$Q15 -> INV-260316-112 | R15: =[1]請求書管理!$R15 -> DEL-260316-112 | S15: =[1]請求書管理!$S15 -> REC-260324-112
... A33: =[1]請求書管理!$A33 -> 109 | B33: =[1]請求書管理!$B33 -> 0 | C33: =[1]請求書管理!$C33 -> 0 | D33: =[1]請求書管理!$D33 -> 0 | E33: =[1]請求書管理!$E33 -> 0 | F33: =[1]請求書管理!$F33 -> 0 | G33: =[1]請求書管理!$G33 -> 0 | H33: =[1]請求書管理!$H33 -> 0 | I33: =[1]請求書管理!$I33 -> 0 | J33: =[1]請求書管理!$J33 -> 0 | K33: =[1]請求書管理!$K33 -> 0 | L33: =[1]請求書管理!$L33 -> 0 | M33: =[1]請求書管理!$M33 -> 0 | N33: =[1]請求書管理!$N33 -> 0 | O33: =[1]請求書管理!$O33 -> 0 | P33: =[1]請求書管理!$P33 -> 0 | Q33: =[1]請求書管理!$Q33 -> 0 | R33: =[1]請求書管理!$R33 -> 0 | S33: =[1]請求書管理!$S33 -> 0

Sheet 目次
B1: 業者名 | C1: 備考 | D1: 備考
A2: 1 | B2: ウエスタンデジタル株式会社
A3: 1_ | B3: ウエスタンデジタル株式会社 | C3: 最新版
A4: 1-2 | B4: ウエスタンデジタル株式会社
A5: 1-3 | B5: サンディスク合同会社
A6: 1-4 | B6: ウエスタンデジタル株式会社 | C6: 数式入り 2026.02.23
A7: 1-5 | B7: ウエスタンデジタル株式会社 | C7: 最新版 | D7: 数式最適化済2026.5.22
A8: 1-6 | B8: サンディスク合同会社 | C8: 最新版 | D8: 数式最適化済2026.5.22
A9: 1-7 | B9: サンディスク合同会社 | C9: 図形バージョン 最新 | D9: 数式最適化済2026.5.22
A10: 1-8 | B10: ウエスタンデジタル株式会社 | C10: 図形バージョン 最新 | D10: 数式最適化済2026.5.22
A11: 2 | B11: キヤノンマーケティングジャパン株式会社
A12: 2-1 | B12: キヤノンマーケティングジャパン株式会社
A13: 2-2 | B13: キヤノンマーケティングジャパン株式会社 | C13: 最新版
A14: 2-3 | B14: キヤノンマーケティングジャパン株式会社 | C14: ジャンコードあり
A15: 2-4 | B15: キヤノンマーケティングジャパン株式会社 | C15: 2026.2.10作成
A16: 2-5 | B16: キヤノンマーケティングジャパン株式会社 | C16: 2026.2.23 作成
A17: 2-6 | B17: キヤノンマーケティングジャパン株式会社 | C17: 2026.2.23 手直し
A18: 2-7 | B18: キヤノンマーケティングジャパン株式会社 | C18: 最新版
A19: 3 | B19: SB C＆S 株式会社
A20: 3-1 | B20: SB C＆S 株式会社 | C20: 修正版
A21: 4-1 | B21: 浜田電機株式会社
A22: 4-2 | B22: 浜田電機株式会社
A23: 4-3 | B23: 浜田電機株式会社
A24: 4-4 | B24: 浜田電機株式会社
A25: 4-5 | B25: 浜田電機株式会社
A26: 4-6 | B26: 浜田電機株式会社
A27: 4-7 | B27: 浜田電機株式会社
A28: 4-8 | B28: 浜田電機株式会社
A29: 4-9 | B29: 浜田電機株式会社 | C29: インボイスなし
A30: 5 | B30: 株式会社ビックカメラ
A31: 6 | B31: 株式会社ヤマダ電機（ツクモ）
A32: 7-1 | B32: ダイワボウ情報システム株式会社
A33: 7-2 | B33: ダイワボウ情報システム株式会社
A34: 7-3 | B34: ダイワボウ情報システム株式会社
A35: 8-1 | B35: 東映無線株式会社 アスビック
A36: 8-2 | B36: 東映無線株式会社 アスビック
A37: 8-3 | B37: 東映無線株式会社 アスビック
A38: 8-4 | B38: 東映無線株式会社 アスビック
A39: 8-5 | B39: 東映無線株式会社 アスビック | C39: 最新版
A40: 9 | B40: 株式会社アーキサイト
A41: 10 | B41: 日本サンプル株式会社
A42: 11 | B42: INVOY
A43: 12 | B43: エレコムダイレクトショップ
A44: 12-1 | B44: エレコムダイレクトショップ | C44: 最新版
A45: 13 | B45: 会計フリー | C45: 最新版
A46: 14 | B46: 試作1
A47: 15

Sheet 会計フリー
A1: 請求書
A2: 東映無線株式会社 御中
E3: 請求日 | F3: 45762
A4: 〒11010021 | E4: 請求書番号 | F4: 3003877451
A5: 東京都千代田区外神田1丁目10番11号 | E5: 登録番号 | F5: T2010401090562
A6: 東京ラジオデパート内
A7: TEL：03-3527-1006
A8: 登録番号T1010001023790 | E8: ウエスタンデジタル合同会社
E9: 〒108-0075
E10: 東京都港区港南1丁目6番31号
E11: 品川東急ビル 3階
E12: TEL：0120-893-009
E13: https://shop.sandisk.com
E14: westerndigital_jp@custhelp.com
A15: 下記の通りご請求申し上げます。
A16: 件名 | B16: SanDisk製品の件
A17: 小計 | B17: 消費税 | C17: 請求金額
A18: =F42 -> 144900 | B18: =F43 -> 14490 | C18: =A18+B18 -> 159390 | I18: №
I19: 1 | J19: 180 | K19: 型番： | L19: SDSQXA2-064G-GN6MA | M19: コード： | N19: 619659169770 | O19: SanDisk | Q19: 89 | R19: 4 | S19: 150
A20: 入金期日 | B20: 振込先 | I20: 2 | J20: 199 | K20: 型番： | L20: SDSQXA1-128G-GN6MN | M20: コード： | N20: 619659180034 | O20: SanDisk | Q20: 114 | R20: 5 | S20: 550
A21: 45765 | B21: みずほ銀行 品川支店 普通7759780 | I21: 3 | J21: 214 | K21: 型番： | L21: SDSQXA1-256G-GN6MN | M21: コード： | N21: 619659180041 | O21: SanDisk | Q21: 167 | R21: 15 | S21: 50
I22: 4 | J22: 89 | K22: 型番： | L22: SDSQUAB-128G-GH3MA | M22: コード： | N22: 619659201579 | O22: SanDisk | Q22: 179 | R22: 16 | S22: 80
A23: 摘要 | D23: 数量 | E23: 単価 | F23: 明細金額 | I23: 5 | J23: 114 | K23: 型番： | L23: SDSQUAC-256G-GH3MA | M23: コード： | N23: 619659201555 | O23: SanDisk | Q23: 197 | R23: 17 | S23: 150
A24: =O19&" "&M19&N19&" "&K19&L19 -> SanDisk コード：619659169770 型番：SDSQXA2-064G-GN6MA | D24: 300 | E24: 0 | F24: =E24*D24 -> 0 | I24: 6 | J24: 287 | K24: 型番： | L24: SDSQQNR-032G-GH3IA | M24: コード： | N24: 619659197704 | O24: SanDisk | Q24: 212 | S24: 70
A25: =O20&" "&M20&N20&" "&K20&L20 -> SanDisk コード：619659180034 型番：SDSQXA1-128G-GN6MN | D25: 350 | E25: 0 | F25: =E25*D25 -> 0 | I25: 7 | J25: 292 | K25: 型番： | L25: SDSQQNR-064G-GH3IA | M25: コード： | N25: 619659197711 | O25: SanDisk | Q25: 287 | R25: 6 | S25: 35
A26: =O21&" "&M21&N21&" "&K21&L21 -> SanDisk コード：619659180041 型番：SDSQXA1-256G-GN6MN | D26: 150 | E26: 0 | F26: =E26*D26 -> 0 | I26: 8 | J26: 297 | K26: 型番： | L26: SDSQQNR-128G-GH3IA | M26: コード： | N26: 619659198923 | O26: SanDisk | Q26: 292 | R26: 7 | S26: 40
A27: =O22&" "&M22&N22&" "&K22&L22 -> SanDisk コード：619659201579 型番：SDSQUAB-128G-GH3MA | D27: 150 | E27: 70 | F27: =E27*D27 -> 10500 | I27: 9 | J27: 195 | K27: 型番： | L27: SDSQXAH-064G-GN6MN | M27: コード： | N27: 619659193416 | O27: SanDisk | Q27: 297 | R27: 8 | S27: 70
A28: =O23&" "&M23&N23&" "&K23&L23 -> SanDisk コード：619659201555 型番：SDSQUAC-256G-GH3MA | D28: 20 | E28: 0 | F28: =E28*D28 -> 0 | I28: 10 | J28: 198 | K28: 型番： | L28: SDSQXAA-128G-GN6MN | M28: コード： | N28: 619659188467 | O28: SanDisk | Q28: 302 | S28: 25
A29: =O24&" "&M24&N24&" "&K24&L24 -> SanDisk コード：619659197704 型番：SDSQQNR-032G-GH3IA | D29: 35 | E29: 0 | F29: =E29*D29 -> 0 | I29: 11 | J29: 213 | K29: 型番： | L29: SDSQXAV-256G-GN6MN | M29: コード： | N29: 619659188511 | O29: SanDisk | Q29: 365 | R29: 12 | S29: 50
A30: =O25&" "&M25&N25&" "&K25&L25 -> SanDisk コード：619659197711 型番：SDSQQNR-064G-GH3IA | D30: 40 | E30: 0 | F30: =E30*D30 -> 0 | I30: 12 | J30: 365 | K30: 型番： | L30: SDSDXV2-064G-GHJIN | M30: コード： | N30: 619659197834 | O30: SanDisk | Q30: 373 | R30: 13 | S30: 650
A31: =O26&" "&M26&N26&" "&K26&L26 -> SanDisk コード：619659198923 型番：SDSQQNR-128G-GH3IA | D31: 70 | E31: 0 | F31: =E31*D31 -> 0 | I31: 13 | J31: 373 | K31: 型番： | L31: SDSDXVA-128G-GHJIN | M31: コード： | N31: 619659197841 | O31: SanDisk | Q31: 380 | R31: 14 | S31: 250
A32: =O27&" "&M27&N27&" "&K27&L27 -> SanDisk コード：619659193416 型番：SDSQXAH-064G-GN6MN | D32: 90 | E32: 100 | F32: =E32*D32 -> 9000 | I32: 14 | J32: 380 | K32: 型番： | L32: SDSDXVV-256G-GHJIN | M32: コード： | N32: 619659197858 | O32: SanDisk | Q32: 407 | S32: 350
A33: =O28&" "&M28&N28&" "&K28&L28 -> SanDisk コード：619659188467 型番：SDSQXAA-128G-GN6MN | D33: 400 | E33: 125 | F33: =E33*D33 -> 50000 | I33: 15 | J33: 167 | K33: 型番： | L33: SDSQXAT-032G-GH3MA | M33: コード： | N33: 619659197940 | O33: SanDisk | Q33: 419 | S33: 100
A34: =O29&" "&M29&N29&" "&K29&L29 -> SanDisk コード：619659188511 型番：SDSQXAV-256G-GN6MN | D34: 390 | E34: 40 | F34: =E34*D34 -> 15600 | I34: 16 | J34: 179 | K34: 型番： | L34: SDSQXAH-064G-GH3MA | M34: コード： | N34: 619659197933 | O34: SanDisk | Q34: 434 | S34: 20
A35: =O30&" "&M30&N30&" "&K30&L30 -> SanDisk コード：619659197834 型番：SDSDXV2-064G-GHJIN | D35: 50 | E35: 0 | F35: =E35*D35 -> 0 | I35: 17 | J35: 197 | K35: 型番： | L35: SDSQXAA-128G-GH3MA | M35: コード： | N35: 619659197926 | O35: SanDisk | Q35: 437 | S35: 15
A36: =O31&" "&M31&N31&" "&K31&L31 -> SanDisk コード：619659197841 型番：SDSDXVA-128G-GHJIN | D36: 650 | E36: 50 | F36: =E36*D36 -> 32500 | I36: 18 | K36: 型番： | L36: #N/A | M36: コード： | N36: #N/A | O36: SanDisk | Q36: 180 | R36: 1 | S36: 300
A37: =O32&" "&M32&N32&" "&K32&L32 -> SanDisk コード：619659197858 型番：SDSDXVV-256G-GHJIN | D37: 250 | E37: 0 | F37: =E37*D37 -> 0 | I37: 19 | K37: 型番： | L37: #N/A | M37: コード： | N37: #N/A | O37: SanDisk | Q37: 199 | R37: 2 | S37: 350
A38: =O33&" "&M33&N33&" "&K33&L33 -> SanDisk コード：619659197940 型番：SDSQXAT-032G-GH3MA | D38: 50 | E38: 0 | F38: =E38*D38 -> 0 | I38: 20 | K38: 型番： | L38: #N/A | M38: コード： | N38: #N/A | O38: SanDisk | Q38: 214 | R38: 3 | S38: 150
A39: =O34&" "&M34&N34&" "&K34&L34 -> SanDisk コード：619659197933 型番：SDSQXAH-064G-GH3MA | D39: 80 | E39: 60 | F39: =E39*D39 -> 4800 | I39: 21 | K39: 型番： | L39: #N/A | M39: コード： | N39: #N/A | O39: SanDisk | Q39: 168 | S39: 80
A40: =O35&" "&M35&N35&" "&K35&L35 -> SanDisk コード：619659197926 型番：SDSQXAA-128G-GH3MA | D40: 150 | E40: 150 | F40: =E40*D40 -> 22500 | I40: 22 | K40: 型番： | L40: #N/A | M40: コード： | N40: #N/A | O40: SanDisk | Q40: 195 | R40: 9 | S40: 90
I41: 23 | K41: 型番： | L41: #N/A | M41: コード： | N41: #N/A | O41: SanDisk | Q41: 198 | R41: 10 | S41: 400
D42: 内訳 10％対象（税抜） | F42: =SUM(F24:F40) -> 144900 | I42: 24 | K42: 型番： | L42: #N/A | M42: コード： | N42: #N/A | O42: SanDisk | Q42: 213 | R42: 11 | S42: 390
D43: 10％消費税 | F43: =F42*10% -> 14490 | I43: 25 | K43: 型番： | L43: #N/A | M43: コード： | N43: #N/A | O43: SanDisk | Q43: 63 | S43: 70
I44: 26 | K44: 型番： | L44: #N/A | M44: コード： | N44: #N/A | O44: SanDisk | Q44: 90 | S44: 150
I45: 27 | K45: 型番： | L45: #N/A | M45: コード： | N45: #N/A | O45: SanDisk | Q45: 115 | S45: 20
I46: 28
I47: 29
I48: 30

Sheet 会計フリー　最新 
A1: 請求書
A2: =VLOOKUP(管理!$C$2,管理!$A$4:$V$100,2,0)&" 御中" -> 柏尾奏利（KASIOshop） 御中
E3: 請求日 | G3: =管理!F1 -> 46097
A4: ="〒"&VLOOKUP(管理!$C$2,管理!$A$4:$V$100,3,0) -> 〒174-0072 | E4: 請求書番号 | G4: =VLOOKUP(管理!$C$1,管理!$A$4:$V$100,15,0) -> ◎
A5: =VLOOKUP(管理!$C$2,管理!$A$4:$V$100,4,0) -> 東京都板橋区南常盤台1丁目11番6号 | E5: 登録番号 | G5: =VLOOKUP(管理!$C$1,管理!$A$4:$V$100,11,0) -> T2010401090562
A6: =VLOOKUP(管理!$C$2,管理!$A$4:$V$100,5,0) -> ウエアーハウス303号室
A7: ="担当者："&VLOOKUP(管理!$C$2,管理!A4:S50,9,0)&" 様" -> 担当者：柏尾奏利 様
E8: =VLOOKUP(管理!$C$1,管理!$A$4:$V$100,2,0) -> サンディスク合同会社
E9: ="〒"&VLOOKUP(管理!$C$1,管理!$A$4:$V$100,3,0) -> 〒108-0075
E10: =VLOOKUP(管理!$C$1,管理!$A$4:$V$100,4,0) -> 東京都港区港南1丁目6番31号
E11: =VLOOKUP(管理!$C$1,管理!$A$4:$V$100,5,0) -> 品川東急ビル3階
E12: TEL | F12: =VLOOKUP(管理!$C$1,管理!$A$4:$V$100,6,0) -> 0120-893-009
E13: MAIL | F13: =VLOOKUP(管理!$C$1,管理!$A$4:$V$100,8,0) -> https://www.sandisk.com
E14: WEB | F14: =VLOOKUP(管理!$C$1,管理!$A$4:$V$100,10,0) -> retail_support@sandisk.com
A15: 下記の通りご請求申し上げます。
A16: 件名 | B16: SanDisk製品の件
A17: 小計 | B17: 消費税 | C17: 請求金額
A18: =G42 -> 2050055 | B18: =G43 -> 205005.5 | C18: =A18+B18 -> 2255060.5 | J18: №
J19: 1 | K19: 180 | L19: 型番： | M19: SDSQXA2-064G-GN6MA | N19: コード： | O19: 619659169770 | P19: SanDisk | R19: 89 | S19: 4 | T19: 150
A20: 入金期日 | B20: 振込先 | J20: 2 | K20: 199 | L20: 型番： | M20: SDSQXA1-128G-GN6MN | N20: コード： | O20: 619659180034 | P20: SanDisk | R20: 114 | S20: 5 | T20: 550
A21: =管理!O1 -> 46105 | B21: =VLOOKUP(管理!$C$1,管理!$A$4:$V$100,12,0) -> みずほ銀行 品川支店 普通7759780 | J21: 3 | K21: 214 | L21: 型番： | M21: SDSQXA1-256G-GN6MN | N21: コード： | O21: 619659180041 | P21: SanDisk | R21: 167 | S21: 15 | T21: 50
J22: 4 | K22: 89 | L22: 型番： | M22: SDSQUAB-128G-GH3MA | N22: コード： | O22: 619659201579 | P22: SanDisk | R22: 179 | S22: 16 | T22: 80
A23: 摘要 | D23: 数量 | E23: 単価 | G23: 明細金額 | J23: 5 | K23: 114 | L23: 型番： | M23: SDSQUAC-256G-GH3MA | N23: コード： | O23: 619659201555 | P23: SanDisk | R23: 197 | S23: 17 | T23: 150
A24: SanDisk 商品コード：619659201593 商品モデル番号：SDSQUA4-032G-GH3MA | D24: 0 | E24: 1463 | G24: =E24*D24 -> 0 | J24: 6 | K24: 287 | L24: 型番： | M24: SDSQQNR-032G-GH3IA | N24: コード： | O24: 619659197704 | P24: SanDisk | R24: 212 | T24: 70
A25: SanDisk 商品コード：619659201586 商品モデル番号：SDSQUAB-064G-GH3MA | D25: 0 | E25: 1715 | G25: =E25*D25 -> 0 | J25: 7 | K25: 292 | L25: 型番： | M25: SDSQQNR-064G-GH3IA | N25: コード： | O25: 619659197711 | P25: SanDisk | R25: 287 | S25: 6 | T25: 35
A26: SanDisk 商品コード：619659201579 商品モデル番号：SDSQUAB-128G-GH3MA | D26: 70 | E26: 2555 | G26: =E26*D26 -> 178850 | J26: 8 | K26: 297 | L26: 型番： | M26: SDSQQNR-128G-GH3IA | N26: コード： | O26: 619659198923 | P26: SanDisk | R26: 292 | S26: 7 | T26: 40
A27: SanDisk 商品コード：619659200480 商品モデル番号：SDSQUAB-128G-GN6MN | D27: 55 | E27: 2555 | G27: =E27*D27 -> 140525 | J27: 9 | K27: 195 | L27: 型番： | M27: SDSQXAH-064G-GN6MN | N27: コード： | O27: 619659193416 | P27: SanDisk | R27: 297 | S27: 8 | T27: 70
A28: SanDisk 商品コード：619659201555 商品モデル番号：SDSQUAC-256G-GH3MA | D28: 0 | E28: 4445 | G28: =E28*D28 -> 0 | J28: 10 | K28: 198 | L28: 型番： | M28: SDSQXAA-128G-GN6MN | N28: コード： | O28: 619659188467 | P28: SanDisk | R28: 302 | T28: 25
A29: SanDisk 商品コード：619659201562 商品モデル番号：SDSQUAC-512G-GH3MA | D29: 0 | E29: 8050 | G29: =E29*D29 -> 0 | J29: 11 | K29: 213 | L29: 型番： | M29: SDSQXAV-256G-GN6MN | N29: コード： | O29: 619659188511 | P29: SanDisk | R29: 365 | S29: 12 | T29: 50
A30: SanDisk 商品コード：619659201609 商品モデル番号：SDSQUAC-1T00-GH3MA | D30: 0 | E30: 15470 | G30: =E30*D30 -> 0 | J30: 12 | K30: 365 | L30: 型番： | M30: SDSDXV2-064G-GHJIN | N30: コード： | O30: 619659197834 | P30: SanDisk | R30: 373 | S30: 13 | T30: 650
A31: SanDisk 商品コード：619659203566 商品モデル番号：SDSQUAC-1T50-GH3MA | D31: 0 | E31: 17220 | G31: =E31*D31 -> 0 | J31: 13 | K31: 373 | L31: 型番： | M31: SDSDXVA-128G-GHJIN | N31: コード： | O31: 619659197841 | P31: SanDisk | R31: 380 | S31: 14 | T31: 250
A32: SanDisk 商品コード：619659197940 商品モデル番号：SDSQXAT-032G-GH3MA | D32: 0 | E32: 1785 | G32: =E32*D32 -> 0 | J32: 14 | K32: 380 | L32: 型番： | M32: SDSDXVV-256G-GHJIN | N32: コード： | O32: 619659197858 | P32: SanDisk | R32: 407 | T32: 350
A33: SanDisk 商品コード：619659197933 商品モデル番号：SDSQXAH-064G-GH3MA | D33: 60 | E33: 2093 | G33: =E33*D33 -> 125580 | J33: 15 | K33: 167 | L33: 型番： | M33: SDSQXAT-032G-GH3MA | N33: コード： | O33: 619659197940 | P33: SanDisk | R33: 419 | T33: 100
A34: SanDisk 商品コード：619659193416 商品モデル番号：SDSQXAH-064G-GN6MN | D34: 100 | E34: 2093 | G34: =E34*D34 -> 209300 | J34: 16 | K34: 179 | L34: 型番： | M34: SDSQXAH-064G-GH3MA | N34: コード： | O34: 619659197933 | P34: SanDisk | R34: 434 | T34: 20
A35: SanDisk 商品コード：619659197926 商品モデル番号：SDSQXAA-128G-GH3MA | D35: 150 | E35: 2926 | G35: =E35*D35 -> 438900 | J35: 17 | K35: 197 | L35: 型番： | M35: SDSQXAA-128G-GH3MA | N35: コード： | O35: 619659197926 | P35: SanDisk | R35: 437 | T35: 15
A36: SanDisk 商品コード：619659188467 商品モデル番号：SDSQXAA-128G-GN6MN | D36: 125 | E36: 2926 | G36: =E36*D36 -> 365750 | J36: 18 | L36: 型番： | M36: #N/A | N36: コード： | O36: #N/A | P36: SanDisk | R36: 180 | S36: 1 | T36: 300
A37: SanDisk 商品コード：619659197964 商品モデル番号：SDSQXAV-256G-GH3MA | D37: 35 | E37: 5530 | G37: =E37*D37 -> 193550 | J37: 19 | L37: 型番： | M37: #N/A | N37: コード： | O37: #N/A | P37: SanDisk | R37: 199 | S37: 2 | T37: 350
A38: SanDisk 商品コード：619659188511 商品モデル番号：SDSQXAV-256G-GN6MN | D38: 40 | E38: 5530 | G38: =E38*D38 -> 221200 | J38: 20 | L38: 型番： | M38: #N/A | N38: コード： | O38: #N/A | P38: SanDisk | R38: 214 | S38: 3 | T38: 150
A39: SanDisk 商品コード：619659197971 商品モデル番号：SDSQXAV-512G-GH3MA | D39: 20 | E39: 8820 | G39: =E39*D39 -> 176400 | J39: 21 | L39: 型番： | M39: #N/A | N39: コード： | O39: #N/A | P39: SanDisk | R39: 168 | T39: 80
A40: SanDisk 商品コード：619659197957 商品モデル番号：SDSQXAV-1T00-GH3MA | D40: 0 | E40: 16660 | G40: =E40*D40 -> 0 | J40: 22 | L40: 型番： | M40: #N/A | N40: コード： | O40: #N/A | P40: SanDisk | R40: 195 | S40: 9 | T40: 90
J41: 23 | L41: 型番： | M41: #N/A | N41: コード： | O41: #N/A | P41: SanDisk | R41: 198 | S41: 10 | T41: 400
D42: 内訳 10％対象（税抜） | G42: =SUM(G24:G40) -> 2050055 | J42: 24 | L42: 型番： | M42: #N/A | N42: コード： | O42: #N/A | P42: SanDisk | R42: 213 | S42: 11 | T42: 390
D43: 10％消費税 | G43: =G42*10% -> 205005.5 | J43: 25 | L43: 型番： | M43: #N/A | N43: コード： | O43: #N/A | P43: SanDisk | R43: 63 | T43: 70
J44: 26 | L44: 型番： | M44: #N/A | N44: コード： | O44: #N/A | P44: SanDisk | R44: 90 | T44: 150
J45: 27 | L45: 型番： | M45: #N/A | N45: コード： | O45: #N/A | P45: SanDisk | R45: 115 | T45: 20
J46: 28
J47: 29
J48: 30

Sheet エレコムダイレクトショップ本店
B2: 〒174-0072
B3: 東京都板橋区南常盤台1丁目11番6号
B4: ウエアーハウス303号室 | H4: 46062
G5: 登録番号: T5120001094974
B6: 柏尾奏利（KASIOshop） 様 | G6: 〒541-8765
D7: 請求書在中 | G7: 大阪市中央区伏見町4丁目1番1号
G8: 明治安田生命大阪御堂筋ビル9F
G9: エレコムダイレクトショップ本店
B11: 請求書 | M11: № | P11: 型番 | R11: JANコード
B12: 〒174-0072 | M12: 1 | N12: 63 | O12: 型番： | P12: SDSQUAB-064G-GN6MN | Q12: JANコード： | R12: 4549550356145
B13: 東京都板橋区南常盤台1丁目11番6号 | G13: 請求書No.： | H13: ORDER-198103 | M13: 2 | N13: 90 | O13: 型番： | P13: SDSQUAB-128G-GN6MN | Q13: JANコード： | R13: 619659200480
B14: ウエアーハウス303号室 | G14: お客様番号： | H14: 187271 | M14: 3 | N14: 115 | O14: 型番： | P14: SDSQUAC-256G-GN6MN | Q14: JANコード： | R14: 619659200497
B15: 柏尾奏利（KASIOshop） 様 | M15: 4 | N15: 138 | O15: 型番： | P15: SDSQUAC-512G-GN6MN | Q15: JANコード： | R15: 619659200503
B16: 取引日：2026年2月9日 | M16: 5 | N16: 168 | O16: 型番： | P16: SDSQXAF-032G-GN6MN | Q16: JANコード： | R16: 619659177416
B17: 支払方法：下記の口座にお振込願います。 | M17: 6 | N17: 180 | O17: 型番： | P17: SDSQXA2-064G-GN6MA | Q17: JANコード： | R17: 619659169770
B18: 支払期日：2026年2月20日 | M18: 7 | N18: 199 | O18: 型番： | P18: SDSQXA1-128G-GN6MN | Q18: JANコード： | R18: 619659180034
B19: お振込口座： | D19: 三井住友銀行 | M19: 8 | N19: 214 | O19: 型番： | P19: SDSQXA1-256G-GN6MN | Q19: JANコード： | R19: 619659180041
D20: 備後町支店 (支店コード：103) | M20: 9 | N20: 195 | O20: 型番： | P20: SDSQXAH-064G-GN6MN | Q20: JANコード： | R20: 619659193416
D21: 普通 1583633 | M21: 10 | N21: 198 | O21: 型番： | P21: SDSQXAA-128G-GN6MN | Q21: JANコード： | R21: 619659188467
D22: エレコム（カ | M22: 11 | N22: 213 | O22: 型番： | P22: SDSQXAV-256G-GN6MN | Q22: JANコード： | R22: 619659188511
M23: 12 | N23: 230 | O23: 型番： | P23: SDSQXAV-512G-GN6MN | Q23: JANコード： | R23: 619659189655
B24: № | C24: 製品名 | E24: 単価 | G24: 数量 | H24: 商品金額 | M24: 13 | N24: 330 | O24: 型番： | P24: SDSDUNB-064G-GH3NN | Q24: JANコード： | R24: 619659200671
M25: 14 | N25: 340 | O25: 型番： | P25: SDSDUNB-128G-GH3NN | Q25: JANコード： | R25: 619659200107
B26: 1 | C26: iPhone 16e ハイブリッドガラスケース 極限 メタルステッカー付 PM-A25SHVCGKCR 商品コード：4549550356145 | E26: 100 | G26: 50 | H26: =E26*G26 -> 5000 | M26: 15 | N26: 350 | O26: 型番： | P26: SDSDUNC-256G-GH3NN | Q26: JANコード： | R26: 619659200701
M27: 16 | N27: 390 | O27: 型番： | P27: SDSDXXO-032G-GN4IN | Q27: JANコード： | R27: 619659188689
B28: 2 | C28: iPhone 16e ソフトケース サイドメッキ メタルステッカー付 PM-A25SUCTMBU 商品コード：4549550357326 | E28: 100 | G28: 50 | H28: =E28*G28 -> 5000
C42: =O28&P28&" "&Q28&R28
B48: ＜納品先住所＞ | F48: 送料 | H48: 0
B49: =B12 -> 〒174-0072
B50: =B13 -> 東京都板橋区南常盤台1丁目11番6号 | F50: 税抜合計 | H50: =SUM(H24:I27) -> 5000
B51: =B14 -> ウエアーハウス303号室 | F51: 消費税10％対象 | H51: =H50*10% -> 500
F52: 税込合計 | H52: =H50+H51 -> 5500
B53: =B15 -> 柏尾奏利（KASIOshop） 様
C54: TEL：090-7446-7403 | F54: 支払合計 | H54: =H52+H53 -> 5500

Sheet エレコム株式会社
A2: 〒174-0072
A3: 東京都板橋区南常盤台1丁目11番6号
A4: ウエアーハウス303号室 | G4: 46062
F5: 登録番号: T5120001094974
A6: 柏尾奏利（KASIOshop） 様 | F6: 〒541-8765
C7: 請求書在中 | F7: 大阪市中央区伏見町4丁目1番1号
F8: 明治安田生命大阪御堂筋ビル9F
F9: エレコム株式会社
A11: 請求書 | L11: № | O11: 型番 | Q11: JANコード
A12: 〒174-0072 | L12: 1 | M12: 63 | N12: 型番： | O12: SDSQUAB-064G-GN6MN | P12: JANコード： | Q12: 4549550356145
A13: 東京都板橋区南常盤台1丁目11番6号 | F13: 請求書No.： | G13: ORDER-198103 | L13: 2 | M13: 90 | N13: 型番： | O13: SDSQUAB-128G-GN6MN | P13: JANコード： | Q13: 619659200480
A14: ウエアーハウス303号室 | F14: お客様番号： | G14: 187271 | L14: 3 | M14: 115 | N14: 型番： | O14: SDSQUAC-256G-GN6MN | P14: JANコード： | Q14: 619659200497
A15: 柏尾奏利（KASIOshop） 様 | L15: 4 | M15: 138 | N15: 型番： | O15: SDSQUAC-512G-GN6MN | P15: JANコード： | Q15: 619659200503
A16: 取引日：2026年2月9日 | L16: 5 | M16: 168 | N16: 型番： | O16: SDSQXAF-032G-GN6MN | P16: JANコード： | Q16: 619659177416
A17: 支払方法：下記の口座にお振込願います。 | L17: 6 | M17: 180 | N17: 型番： | O17: SDSQXA2-064G-GN6MA | P17: JANコード： | Q17: 619659169770
A18: 支払期日：2026年2月20日 | L18: 7 | M18: 199 | N18: 型番： | O18: SDSQXA1-128G-GN6MN | P18: JANコード： | Q18: 619659180034
A19: お振込口座： | C19: 三井住友銀行 | L19: 8 | M19: 214 | N19: 型番： | O19: SDSQXA1-256G-GN6MN | P19: JANコード： | Q19: 619659180041
C20: 備後町支店 (支店コード：103) | L20: 9 | M20: 195 | N20: 型番： | O20: SDSQXAH-064G-GN6MN | P20: JANコード： | Q20: 619659193416
C21: 普通 1583633 | L21: 10 | M21: 198 | N21: 型番： | O21: SDSQXAA-128G-GN6MN | P21: JANコード： | Q21: 619659188467
C22: エレコム（カ | L22: 11 | M22: 213 | N22: 型番： | O22: SDSQXAV-256G-GN6MN | P22: JANコード： | Q22: 619659188511
L23: 12 | M23: 230 | N23: 型番： | O23: SDSQXAV-512G-GN6MN | P23: JANコード： | Q23: 619659189655
A24: № | B24: 製品名 | D24: 単価 | F24: 数量 | G24: 商品金額 | L24: 13 | M24: 330 | N24: 型番： | O24: SDSDUNB-064G-GH3NN | P24: JANコード： | Q24: 619659200671
L25: 14 | M25: 340 | N25: 型番： | O25: SDSDUNB-128G-GH3NN | P25: JANコード： | Q25: 619659200107
A26: 1 | B26: iPhone 16e ハイブリッドガラスケース 極限 メタルステッカー付 PM-A25SHVCGKCR 商品コード：4549550356145 | D26: 100 | F26: 50 | G26: =D26*F26 -> 5000 | L26: 15 | M26: 350 | N26: 型番： | O26: SDSDUNC-256G-GH3NN | P26: JANコード： | Q26: 619659200701
L27: 16 | M27: 390 | N27: 型番： | O27: SDSDXXO-032G-GN4IN | P27: JANコード： | Q27: 619659188689
A28: 2 | B28: iPhone 16e ソフトケース サイドメッキ メタルステッカー付 PM-A25SUCTMBU 商品コード：4549550357326 | D28: 100 | F28: 50 | G28: =D28*F28 -> 5000
B42: =N28&O28&" "&P28&Q28
A48: ＜納品先住所＞ | E48: 送料 | G48: 0
A49: =A12 -> 〒174-0072
A50: =A13 -> 東京都板橋区南常盤台1丁目11番6号 | E50: 税抜合計 | G50: =SUM(G24:H27) -> 5000
A51: =A14 -> ウエアーハウス303号室 | E51: 消費税10％対象 | G51: =G50*10% -> 500
E52: 税込合計 | G52: =G50+G51 -> 5500
A53: =A15 -> 柏尾奏利（KASIOshop） 様
B54: TEL：090-7446-7403 | E54: 支払合計 | G54: =G52+G53 -> 5500

Sheet エレコム株式会社　最新
A2: ="〒"&VLOOKUP(管理!$C$2,管理!$A$4:$V$100,3,0) -> 〒174-0072
A3: =VLOOKUP(管理!$C$2,管理!$A$4:$V$100,4,0) -> 東京都板橋区南常盤台1丁目11番6号
A4: =VLOOKUP(管理!$C$2,管理!$A$4:$V$100,5,0) -> ウエアーハウス303号室 | H4: =管理!F1 -> 46097
G5: ="登録番号："&VLOOKUP(管理!$C$1,管理!A4:T53,11,0) -> 登録番号：T2010401090562
A6: =VLOOKUP(管理!$C$2,管理!$A$4:$V$100,2,0)&" 御中" -> 柏尾奏利（KASIOshop） 御中 | G6: ="〒"&VLOOKUP(管理!$C$1,管理!A4:T53,3,0) -> 〒108-0075
C7: 請求書在中 | G7: =VLOOKUP(管理!$C$1,管理!A4:T53,4,0) -> 東京都港区港南1丁目6番31号
G8: =VLOOKUP(管理!$C$1,管理!A4:T53,5,0) -> 品川東急ビル3階
G9: =VLOOKUP(管理!$C$1,管理!A4:T53,2,0) -> サンディスク合同会社
A11: 請求書
A12: =A2 -> 〒174-0072
A13: =A3 -> 東京都板橋区南常盤台1丁目11番6号 | G13: 請求書No. | H13: =VLOOKUP(管理!$C$1,管理!A4:T53,15,0) -> ◎
A14: =A4 -> ウエアーハウス303号室 | G14: お客様番号 | H14: =VLOOKUP(管理!$C$1,管理!A4:T53,14,0) -> 3176-119
A15: =A6 -> 柏尾奏利（KASIOshop） 御中
A16: 取引日 | C16: =H4 -> 46097
A17: 支払方法 | C17: 下記の口座にお振込願います。
A18: 支払期日 | C18: =管理!O1 -> 46105
A19: お振込口座 | C19: =VLOOKUP(管理!$C$1,管理!$A$4:$V$100,12,0) -> みずほ銀行 品川支店 普通7759780
C20: =VLOOKUP(管理!$C$1,管理!$A$4:$V$100,13,0) -> サンディスク（ド
A22: № | B22: 製品名 | E22: 単価 | G22: 数量 | H22: 商品金額
A24: 1 | B24: メーカー：SanDisk 商品コード：619659201593 商品モデル番号：SDSQUA4-032G-GH3MA | E24: 1463 | G24: 0 | H24: =E24*G24 -> 0
A25: 2 | B25: メーカー：SanDisk 商品コード：619659201586 商品モデル番号：SDSQUAB-064G-GH3MA | E25: 1715 | G25: 0 | H25: =E25*G25 -> 0
A26: 3 | B26: メーカー：SanDisk 商品コード：619659201579 商品モデル番号：SDSQUAB-128G-GH3MA | E26: 2555 | G26: 70 | H26: =E26*G26 -> 178850
A27: 4 | B27: メーカー：SanDisk 商品コード：619659200480 商品モデル番号：SDSQUAB-128G-GN6MN | E27: 2555 | G27: 55 | H27: =E27*G27 -> 140525
A28: 5 | B28: メーカー：SanDisk 商品コード：619659201555 商品モデル番号：SDSQUAC-256G-GH3MA | E28: 4445 | G28: 0 | H28: =E28*G28 -> 0
A29: 6 | B29: メーカー：SanDisk 商品コード：619659201562 商品モデル番号：SDSQUAC-512G-GH3MA | E29: 8050 | G29: 0 | H29: =E29*G29 -> 0
A30: 7 | B30: メーカー：SanDisk 商品コード：619659201609 商品モデル番号：SDSQUAC-1T00-GH3MA | E30: 15470 | G30: 0 | H30: =E30*G30 -> 0
A31: 8 | B31: メーカー：SanDisk 商品コード：619659203566 商品モデル番号：SDSQUAC-1T50-GH3MA | E31: 17220 | G31: 0 | H31: =E31*G31 -> 0
A32: 9 | B32: メーカー：SanDisk 商品コード：619659197940 商品モデル番号：SDSQXAT-032G-GH3MA | E32: 1785 | G32: 0 | H32: =E32*G32 -> 0
A33: 10 | B33: メーカー：SanDisk 商品コード：619659197933 商品モデル番号：SDSQXAH-064G-GH3MA | E33: 2093 | G33: 60 | H33: =E33*G33 -> 125580
A34: 11 | B34: メーカー：SanDisk 商品コード：619659193416 商品モデル番号：SDSQXAH-064G-GN6MN | E34: 2093 | G34: 100 | H34: =E34*G34 -> 209300
A35: 12 | B35: メーカー：SanDisk 商品コード：619659197926 商品モデル番号：SDSQXAA-128G-GH3MA | E35: 2926 | G35: 150 | H35: =E35*G35 -> 438900
... A44: 21 | B44: メーカー：SanDisk 商品コード：619659198923 商品モデル番号：SDSQQNR-128G-GH3IA | E44: 3080 | G44: 0 | H44: =E44*G44 -> 0
A46: ＜納品先住所＞ | F46: 送料 | H46: 0
A47: =A12 -> 〒174-0072
A48: =A13 -> 東京都板橋区南常盤台1丁目11番6号 | F48: 税抜合計 | H48: =SUM(H24:I27) -> 319375
A49: =A14 -> ウエアーハウス303号室 | F49: 消費税10％対象 | H49: =H48*10% -> 31937.5
F50: 税込合計 | H50: =H48+H49 -> 351312.5
A51: =VLOOKUP(管理!$C$2,管理!$A$4:$V$100,2,0) -> 柏尾奏利（KASIOshop）
B52: ="TEL："&VLOOKUP(管理!$C$2,管理!$A$4:$V$100,6,0) -> TEL：03-3600-3333 | F52: 支払合計 | H52: =H50+H51 -> 351312.5

Sheet 1_見積書
A3: 御見積書
A5: 株式会社レイディスク 御中
F6: NO | G6: 1285
F7: 見積日 | G7: 2025.7.28
A9: 下記の通り、お見積り申し上げます。 | F9: 〒108-0075
A10: 件名 | B10: 特価ご依頼の件 | F10: 東京都港区港南1-6-31 品川東急ビル3F
A11: 納期 | B11: 決済後1～2営業日 | F11: ウエスタンデジタル合同会社
A12: 支払条件 | B12: クレジットカード払い | F12: TEL:03-4334-7100(代) FAX:03-5463-2010(代)
A13: 有効期限 | B13: 御見積後1週間
A15: 合計 | B15: 48,620円（税込）
A17: 摘要 | E17: 数量 | F17: 単位 | G17: 単価（税別） | H17: 金額
A18: SDSQQNR-128G-GH3IA | E18: 20 | F18: 式 | G18: 2210 | H18: 44200
G28: 合計（税別） | H28: 44200
G29: 消費税 | H29: 4420
G30: 合計（税込） | H30: 48620
A32: 備考

Sheet 1_請求書
D2: ウエスタンデジタル合同会社 | M2: 請求書 兼 領収書
D3: 〒108-0075 東京都港区港南1-6-31
D4: 品川東急ビル3F
G6: 発送番号 | K6: 発送日 | N6: ページ
G7: 87482297 | K7: 45405 | N7: 1の1
D8: 登録番号: T2010401090562 | G8: 発送業者 | L8: B/L
G9: 佐川急便
D11: 請求番号 | F11: 請求日 | J11: 注文番号
D12: 3003877451 | F12: 04/23/2024
D13: 受注番号 | F13: 配送条件 | J13: 貿易取引条件
D14: 0022047564 | F14: 元払い
D15: 出荷先: | I15: 請求先: | K15: OT91990
D16: 山之内雄一 | I16: 山之内雄一
D17: 1130033 東京都 文京区 | I17: 1130033 東京都 文京区
D18: 本郷2-25-14 | I18: 本郷2-25-14
D19: 第一ライトビル５階４号室 | I19: 日本国
D20: 日本国
A22: № | B22: 製品型番 | F22: 数量 | H22: 単位 | J22: 商品単価 | M22: 商品金額
B23: 製品詳細
A24: 1 | B24: SDSQQNR-032G-GH3IA | G24: 1 | H24: EA | J24: 円 | L24: 1200 | O24: 1200
C25: SDSQQNR-032G-GH3IA,High Endurance uSD,10
B45: 支払い方法:
B46: Mastercard
H49: 税率（％）: 10 | K49: 円 | L49: 小計: | O49: =SUM(O24:O45) -> 1200
L50: 割引額: | O50: 0
L51: 配送料: | O51: 0
H52: 税率（％）: 10 | L52: 消費税額: | O52: =O49*10% -> 120
K53: 円 | L53: 合計: | O53: =O49+O52 -> 1320
A58: お買い上げいただきありがとうございました。

Sheet 1_1_請求書兼領収書 ウエスタンデジタル
D2: ウエスタンデジタル合同会社 | K2: 請求書 兼 領収書
D3: 〒108-0075 東京都港区港南1-6-31 | S3: 番号
D4: 品川東急ビル3F | R4: 仕入れ元
R5: 仕入れ先
G6: 発送番号 | J6: 発送日 | M6: ページ
G7: 87482297 | J7: 45405 | M7: 1の1
D8: 登録番号: T2010401090562 | G8: 発送業者 | K8: B/L | R8: № | U8: 型番 | W8: JANコード
G9: 佐川急便 | R9: 1 | S9: 63 | T9: 型番： | U9: SDSQUAB-064G-GN6MN | V9: JANコード： | W9: 619659200473
R10: 2 | S10: 90 | T10: 型番： | U10: SDSQUAB-128G-GN6MN | V10: JANコード： | W10: 619659200480
D11: 請求番号 | F11: 請求日 | J11: 注文番号 | R11: 3 | S11: 115 | T11: 型番： | U11: SDSQUAC-256G-GN6MN | V11: JANコード： | W11: 619659200497
D12: 3003877451 | F12: =J7 -> 45405 | R12: 4 | S12: 138 | T12: 型番： | U12: SDSQUAC-512G-GN6MN | V12: JANコード： | W12: 619659200503
D13: 受注番号 | F13: 配送条件 | J13: 貿易取引条件 | R13: 5 | S13: 168 | T13: 型番： | U13: SDSQXAF-032G-GN6MN | V13: JANコード： | W13: 619659177416
D14: S0022047564 | F14: 元払い | R14: 6 | S14: 180 | T14: 型番： | U14: SDSQXA2-064G-GN6MA | V14: JANコード： | W14: 619659169770
D15: 出荷先: | E15: OT91990 | I15: 請求先: | J15: =E15 -> OT91990 | R15: 7 | S15: 199 | T15: 型番： | U15: SDSQXA1-128G-GN6MN | V15: JANコード： | W15: 619659180034
D16: 東映無線株式会社 | I16: =D16 -> 東映無線株式会社 | R16: 8 | S16: 214 | T16: 型番： | U16: SDSQXA1-256G-GN6MN | V16: JANコード： | W16: 619659180041
D17: 101-0021 東京都千代田区 | I17: =D17 -> 101-0021 東京都千代田区 | R17: 9 | S17: 195 | T17: 型番： | U17: SDSQXAH-064G-GN6MN | V17: JANコード： | W17: 619659193416
D18: 外神田1丁目10番11号 | I18: =D18 -> 外神田1丁目10番11号 | R18: 10 | S18: 198 | T18: 型番： | U18: SDSQXAA-128G-GN6MN | V18: JANコード： | W18: 619659188467
D19: 東京ラジオデパート | I19: =D19 -> 東京ラジオデパート | R19: 11 | S19: 213 | T19: 型番： | U19: SDSQXAV-256G-GN6MN | V19: JANコード： | W19: 619659188511
D20: 日本国 | I20: =D20 -> 日本国 | R20: 12 | S20: 230 | T20: 型番： | U20: SDSQXAV-512G-GN6MN | V20: JANコード： | W20: 619659189655
R21: 13 | S21: 330 | T21: 型番： | U21: SDSDUNB-064G-GH3NN | V21: JANコード： | W21: 619659200671
R22: 14 | S22: 340 | T22: 型番： | U22: SDSDUNB-128G-GH3NN | V22: JANコード： | W22: 619659200107
R23: 15 | S23: 350 | T23: 型番： | U23: SDSDUNC-256G-GH3NN | V23: JANコード： | W23: 619659200701
A24: № | R24: 16 | S24: 390 | T24: 型番： | U24: SDSDXXO-032G-GN4IN | V24: JANコード： | W24: 619659188689
A26: 1 | B26: =T9&U9&" "&V9&W9 -> 型番：SDSQUAB-064G-GN6MN JANコード：619659200473 | G26: 1 | H26: EA | I26: 円 | K26: 0 | N26: =K26*G26 -> 0
A28: 2 | B28: =T10&U10&" "&V10&W10 -> 型番：SDSQUAB-128G-GN6MN JANコード：619659200480 | G28: 2 | H28: EA | I28: 円 | K28: 55 | N28: =K28*G28 -> 110
B29: UHS-I / U1 / A1 / C10 /
A30: 3 | B30: =T11&U11&" "&V11&W11 -> 型番：SDSQUAC-256G-GN6MN JANコード：619659200497 | G30: 3 | H30: EA | I30: 円 | K30: 0 | N30: =K30*G30 -> 0
A32: 4 | B32: =T12&U12&" "&V12&W12 -> 型番：SDSQUAC-512G-GN6MN JANコード：619659200503 | G32: 4 | H32: EA | I32: 円 | K32: 0 | N32: =K32*G32 -> 0
B33: UHS-I / Nintendo Switch /
A34: 5 | B34: =T13&U13&" "&V13&W13 -> 型番：SDSQXAF-032G-GN6MN JANコード：619659177416 | G34: 5 | H34: EA | I34: 円 | K34: 0 | N34: =K34*G34 -> 0
B35: U3 / Class10 /
A36: 6 | B36: =T14&U14&" "&V14&W14 -> 型番：SDSQXA2-064G-GN6MA JANコード：619659169770 | G36: 6 | H36: EA | I36: 円 | K36: 0 | N36: =K36*G36 -> 0
A38: 7 | B38: =T15&U15&" "&V15&W15 -> 型番：SDSQXA1-128G-GN6MN JANコード：619659180034 | G38: 7 | H38: EA | I38: 円 | K38: 0 | N38: =K38*G38 -> 0
B39: U3 / V30 / 4K /
A40: 8 | B40: =T16&U16&" "&V16&W16 -> 型番：SDSQXA1-256G-GN6MN JANコード：619659180041 | G40: 8 | H40: EA | I40: 円 | K40: 0 | N40: =K40*G40 -> 0
B41: U3 / V30 / A1 / 4K /
A42: 9 | B42: =T17&U17&" "&V17&W17 -> 型番：SDSQXAH-064G-GN6MN JANコード：619659193416 | G42: 9 | H42: EA | I42: 円 | K42: 100 | N42: =K42*G42 -> 900
B43: 4K /
A44: 10 | B44: =T18&U18&" "&V18&W18 -> 型番：SDSQXAA-128G-GN6MN JANコード：619659188467 | G44: 11 | H44: EA | I44: 円 | K44: 125 | N44: =K44*G44 -> 1375
B45: UHS-I / U3 / V30 / 4K /
A46: 11 | B46: =T19&U19&" "&V19&W19 -> 型番：SDSQXAV-256G-GN6MN JANコード：619659188511 | G46: 12 | H46: EA | I46: 円 | K46: 40 | N46: =K46*G46 -> 480
B47: Nintendo Switch /
A48: 12 | B48: =T20&U20&" "&V20&W20 -> 型番：SDSQXAV-512G-GN6MN JANコード：619659189655 | G48: 13 | H48: EA | I48: 円 | K48: 0 | N48: =K48*G48 -> 0
B49: UHS-I /
A50: 13 | B50: =T21&U21&" "&V21&W21 -> 型番：SDSDUNB-064G-GH3NN JANコード：619659200671 | G50: 14 | H50: EA | I50: 円 | K50: 0 | N50: =K50*G50 -> 0
B51: UHS-I / Class10 /
A52: 14 | B52: =T22&U22&" "&V22&W22 -> 型番：SDSDUNB-128G-GH3NN JANコード：619659200107 | G52: 15 | H52: EA | I52: 円 | K52: 0 | N52: =K52*G52 -> 0
B53: UHS-I / Class10 /
A54: 15 | B54: =T23&U23&" "&V23&W23 -> 型番：SDSDUNC-256G-GH3NN JANコード：619659200701 | G54: 16 | H54: EA | I54: 円 | K54: 0 | N54: =K54*G54 -> 0
B55: UHS-I / Class10 /
A56: 16 | B56: =T24&U24&" "&V24&W24 -> 型番：SDSDXXO-032G-GN4IN JANコード：619659188689 | G56: 17 | H56: EA | I56: 円 | K56: 0 | N56: =K56*G56 -> 0
B57: UHS-I / U3 / V30 / C10 / 4K /
B59: 支払い方法:
B60: Mastercard
H63: 税率（％）: 10 | J63: 円 | K63: 小計: | N63: =SUM(N26:N59) -> 2865
K64: 割引額: | N64: 0
K65: 配送料: | N65: 0
H66: 税率（％）: 10 | K66: 消費税額: | N66: =N63*10% -> 286.5
J67: 円 | K67: 合計: | N67: =N63+N66 -> 3151.5
A72: お買い上げいただきありがとうございました。

Sheet 1_1_納品書ウエスタンデジタル
G2: Page | H2: 1 of 1
C3: 納品書 | I3: ウエスタンデジタル合同会社
I4: 東京都港区港南1-6-31
I5: 品川東急ビル3F
I6: カスタマーサービス電話番号：0066-3381-4967
A7: 注文番号： | C7: 配送番号： | D7: 90259161
A8: お名前： | B8: 東映無線株式会社 | E8: 日付： | F8: 45405
A9: 住所： | B9: 外神田1丁目10番11号 | E9: 連絡先：
B10: 東京ラジオデパート | E10: 電話番号： | F10: 03-32535660
B11: 〒101-0021
B12: JAPAN
A14: 製品名 | G14: 数量
A15: 型番：SDSQUAB-064G-GN6MN JANコード：619659200473 | G15: 1
A16: 型番：SDSQUAB-128G-GN6MN JANコード：619659200480 | G16: 2
A17: 型番：SDSQUAC-256G-GN6MN JANコード：619659200497 | G17: 3
A18: 型番：SDSQUAC-512G-GN6MN JANコード：619659200503 | G18: 4
A19: 型番：SDSQXAF-032G-GN6MN JANコード：619659177416 | G19: 5
A20: 型番：SDSQXA2-064G-GN6MA JANコード：619659169770 | G20: 6
A21: 型番：SDSQXA1-128G-GN6MN JANコード：619659180034 | G21: 7
A22: 型番：SDSQXA1-256G-GN6MN JANコード：619659180041 | G22: 8
A23: 型番：SDSQXAH-064G-GN6MN JANコード：619659193416 | G23: 9
A24: 型番：SDSQXAA-128G-GN6MN JANコード：619659188467 | G24: 11
A25: 型番：SDSQXAV-256G-GN6MN JANコード：619659188511 | G25: 12
A26: 型番：SDSQXAV-512G-GN6MN JANコード：619659189655 | G26: 13
... A30: 型番：SDSDXXO-032G-GN4IN JANコード：619659188689 | G30: 17
F31: 合計： | G31: =SUM(G15:I30) -> 143
A33: この度はサンディスクストアにて商品をお買い上げいただき誠にありがとうございます。
A34: 商品を送付させていただきます。今後ともご愛顧賜りますよう何卒よろしくお願い申し上げます。

Sheet 1_2_請求書兼領収書 ウエスタンデジタル線引き
E2: ウエスタンデジタル合同会社 | L2: 請求書 兼 領収書
E3: 〒108-0075 東京都港区港南1-6-31 | T3: アカウント
E4: 品川東急ビル3F | S4: 番号 | T4: 105
H6: 発送番号 | K6: 発送日 | N6: ページ
H7: 87482297 | K7: 45762 | N7: 1の1
E8: 登録番号: T2010401090562 | H8: 発送業者 | L8: B/L | S8: № | V8: 型番 | X8: JANコード
H9: 佐川急便 | S9: 1 | T9: 89 | U9: 型番： | V9: SDSQUAB-128G-GH3MA | W9: コード： | X9: 619659201579 | Y9: SanDisk
S10: 2 | T10: 114 | U10: 型番： | V10: SDSQUAC-256G-GH3MA | W10: コード： | X10: 619659201555 | Y10: SanDisk
E11: 請求番号 | G11: 請求日 | K11: 注文番号 | S11: 3 | T11: 167 | U11: 型番： | V11: SDSQXAT-032G-GH3MA | W11: コード： | X11: 619659197940 | Y11: SanDisk
E12: 3003877451 | G12: =K7 -> 45762 | S12: 4 | T12: 179 | U12: 型番： | V12: SDSQXAH-064G-GH3MA | W12: コード： | X12: 619659197933 | Y12: SanDisk
E13: 受注番号 | G13: 配送条件 | K13: 貿易取引条件 | S13: 5 | T13: 197 | U13: 型番： | V13: SDSQXAA-128G-GH3MA | W13: コード： | X13: 619659197926 | Y13: SanDisk
E14: S0022047564 | G14: 元払い | S14: 6 | T14: 212 | U14: 型番： | V14: SDSQXAV-256G-GH3MA | W14: コード： | X14: 619659197964 | Y14: SanDisk
E15: 出荷先: | F15: OT91990 | J15: 請求先: | K15: =F15 -> OT91990 | S15: 7 | T15: 287 | U15: 型番： | V15: SDSQQNR-032G-GH3IA | W15: コード： | X15: 619659197704 | Y15: SanDisk
E16: 東映無線株式会社 | J16: =E16 -> 東映無線株式会社 | S16: 8 | T16: 292 | U16: 型番： | V16: SDSQQNR-064G-GH3IA | W16: コード： | X16: 619659197711 | Y16: SanDisk
E17: 101-0021 東京都千代田区 | J17: =E17 -> 101-0021 東京都千代田区 | S17: 9 | T17: 297 | U17: 型番： | V17: SDSQQNR-128G-GH3IA | W17: コード： | X17: 619659198923 | Y17: SanDisk
E18: 外神田1丁目10番11号 | J18: =E18 -> 外神田1丁目10番11号 | S18: 10 | T18: 302 | U18: 型番： | V18: SDSQQNR-256G-GH3IA | W18: コード： | X18: 619659198930 | Y18: SanDisk
E19: 東京ラジオデパート | J19: =E19 -> 東京ラジオデパート | S19: 11 | T19: 365 | U19: 型番： | V19: SDSDXV2-064G-GHJIN | W19: コード： | X19: 619659197834 | Y19: SanDisk
E20: 日本国 | J20: =E20 -> 日本国 | S20: 12 | T20: 373 | U20: 型番： | V20: SDSDXVA-128G-GHJIN | W20: コード： | X20: 619659197841 | Y20: SanDisk
S21: 13 | T21: 380 | U21: 型番： | V21: SDSDXVV-256G-GHJIN | W21: コード： | X21: 619659197858 | Y21: SanDisk
S22: 14 | T22: 407 | U22: 型番： | V22: SDSDXXD-128G-GHJIN | W22: コード： | X22: 619659197889 | Y22: SanDisk
S23: 15 | T23: 419 | U23: 型番： | V23: SDSDXXD-256G-GHJIN | W23: コード： | X23: 619659197896 | Y23: SanDisk
A24: No. | B24: 製品型番 | G24: 数量 | I24: 単価 | J24: 商品単価 | M24: 商品金額 | S24: 16 | T24: 434 | U24: 型番： | V24: SDSDXEP-064G-GHJIN | W24: コード： | X24: 619659201494 | Y24: SanDisk
B25: 製品詳細 | S25: 17 | T25: 437 | U25: 型番： | V25: SDSDXEP-128G-GHJIN | W25: コード： | X25: 619659201500 | Y25: SanDisk
A26: 1 | B26: =Y9&" "&W9&X9&" "&U9&V9 -> SanDisk コード：619659201579 型番：SDSQUAB-128G-GH3MA | H26: 150 | I26: EA | J26: 円 | L26: 70 | O26: =L26*H26 -> 10500 | S26: 18 | T26: 180 | U26: 型番： | V26: SDSQXA2-064G-GN6MA | W26: コード： | X26: 619659169770 | Y26: SanDisk
A27: 2 | B27: =Y10&" "&W10&X10&" "&U10&V10 -> SanDisk コード：619659201555 型番：SDSQUAC-256G-GH3MA | H27: 550 | I27: EA | J27: 円 | L27: 0 | O27: =L27*H27 -> 0 | S27: 19 | T27: 199 | U27: 型番： | V27: SDSQXA1-128G-GN6MN | W27: コード： | X27: 619659180034 | Y27: SanDisk
A28: 3 | B28: =Y11&" "&W11&X11&" "&U11&V11 -> SanDisk コード：619659197940 型番：SDSQXAT-032G-GH3MA | H28: 50 | I28: EA | J28: 円 | L28: 0 | O28: =L28*H28 -> 0 | S28: 20 | T28: 214 | U28: 型番： | V28: SDSQXA1-256G-GN6MN | W28: コード： | X28: 619659180041 | Y28: SanDisk
A29: 4 | B29: =Y12&" "&W12&X12&" "&U12&V12 -> SanDisk コード：619659197933 型番：SDSQXAH-064G-GH3MA | H29: 80 | I29: EA | J29: 円 | L29: 60 | O29: =L29*H29 -> 4800 | S29: 21 | T29: 168 | U29: 型番： | V29: SDSQXAF-032G-GN6MN | W29: コード： | X29: 619659177416 | Y29: SanDisk
A30: 5 | B30: =Y13&" "&W13&X13&" "&U13&V13 -> SanDisk コード：619659197926 型番：SDSQXAA-128G-GH3MA | H30: 150 | I30: EA | J30: 円 | L30: 150 | O30: =L30*H30 -> 22500 | S30: 22 | T30: 195 | U30: 型番： | V30: SDSQXAH-064G-GN6MN | W30: コード： | X30: 619659193416 | Y30: SanDisk
A31: 6 | B31: =Y14&" "&W14&X14&" "&U14&V14 -> SanDisk コード：619659197964 型番：SDSQXAV-256G-GH3MA | H31: 70 | I31: EA | J31: 円 | L31: 35 | O31: =L31*H31 -> 2450 | S31: 23 | T31: 198 | U31: 型番： | V31: SDSQXAA-128G-GN6MN | W31: コード： | X31: 619659188467 | Y31: SanDisk
A32: 7 | B32: =Y15&" "&W15&X15&" "&U15&V15 -> SanDisk コード：619659197704 型番：SDSQQNR-032G-GH3IA | H32: 35 | I32: EA | J32: 円 | L32: 0 | O32: =L32*H32 -> 0 | S32: 24 | T32: 213 | U32: 型番： | V32: SDSQXAV-256G-GN6MN | W32: コード： | X32: 619659188511 | Y32: SanDisk
A33: 8 | B33: =Y16&" "&W16&X16&" "&U16&V16 -> SanDisk コード：619659197711 型番：SDSQQNR-064G-GH3IA | H33: 40 | I33: EA | J33: 円 | L33: 0 | O33: =L33*H33 -> 0 | S33: 25 | T33: 63 | U33: 型番： | V33: SDSQUAB-064G-GN6MN | W33: コード： | X33: 619659200473 | Y33: SanDisk
A34: 9 | B34: =Y17&" "&W17&X17&" "&U17&V17 -> SanDisk コード：619659198923 型番：SDSQQNR-128G-GH3IA | H34: 70 | I34: EA | J34: 円 | L34: 0 | O34: =L34*H34 -> 0 | S34: 26 | T34: 90 | U34: 型番： | V34: SDSQUAB-128G-GN6MN | W34: コード： | X34: 619659200480 | Y34: SanDisk
A35: 10 | B35: =Y18&" "&W18&X18&" "&U18&V18 -> SanDisk コード：619659198930 型番：SDSQQNR-256G-GH3IA | H35: 25 | I35: EA | J35: 円 | L35: 0 | O35: =L35*H35 -> 0 | S35: 27 | T35: 115 | U35: 型番： | V35: SDSQUAC-256G-GN6MN | W35: コード： | X35: 619659200497 | Y35: SanDisk
A36: 11 | B36: =Y19&" "&W19&X19&" "&U19&V19 -> SanDisk コード：619659197834 型番：SDSDXV2-064G-GHJIN | H36: 50 | I36: EA | J36: 円 | L36: 0 | O36: =L36*H36 -> 0 | S36: 28 | U36: 型番： | V36: #N/A | W36: コード： | X36: #N/A | Y36: SanDisk
A37: 12 | B37: =Y20&" "&W20&X20&" "&U20&V20 -> SanDisk コード：619659197841 型番：SDSDXVA-128G-GHJIN | H37: 650 | I37: EA | J37: 円 | L37: 50 | O37: =L37*H37 -> 32500 | S37: 29 | U37: 型番： | V37: #N/A | W37: コード： | X37: #N/A | Y37: SanDisk
A38: 13 | B38: =Y21&" "&W21&X21&" "&U21&V21 -> SanDisk コード：619659197858 型番：SDSDXVV-256G-GHJIN | H38: 250 | I38: EA | J38: 円 | L38: 0 | O38: =L38*H38 -> 0 | S38: 30 | U38: 型番： | V38: #N/A | W38: コード： | X38: #N/A | Y38: SanDisk
A39: 14 | B39: =Y22&" "&W22&X22&" "&U22&V22 -> SanDisk コード：619659197889 型番：SDSDXXD-128G-GHJIN | H39: 350 | I39: EA | J39: 円 | L39: 0 | O39: =L39*H39 -> 0
A40: 15 | B40: =Y23&" "&W23&X23&" "&U23&V23 -> SanDisk コード：619659197896 型番：SDSDXXD-256G-GHJIN | H40: 100 | I40: EA | J40: 円 | L40: 0 | O40: =L40*H40 -> 0
A41: 16 | B41: =Y24&" "&W24&X24&" "&U24&V24 -> SanDisk コード：619659201494 型番：SDSDXEP-064G-GHJIN | H41: 20 | I41: EA | J41: 円 | L41: 0 | O41: =L41*H41 -> 0
A42: 17 | B42: =Y25&" "&W25&X25&" "&U25&V25 -> SanDisk コード：619659201500 型番：SDSDXEP-128G-GHJIN | H42: 15 | I42: EA | J42: 円 | L42: 9999 | O42: =L42*H42 -> 149985
A43: 18 | B43: =Y26&" "&W26&X26&" "&U26&V26 -> SanDisk コード：619659169770 型番：SDSQXA2-064G-GN6MA | H43: 300 | I43: EA | J43: 円 | L43: 0 | O43: =L43*H43 -> 0
A44: 19 | B44: =Y27&" "&W27&X27&" "&U27&V27 -> SanDisk コード：619659180034 型番：SDSQXA1-128G-GN6MN | H44: 350 | I44: EA | J44: 円 | L44: 0 | O44: =L44*H44 -> 0
A45: 20 | B45: =Y28&" "&W28&X28&" "&U28&V28 -> SanDisk コード：619659180041 型番：SDSQXA1-256G-GN6MN | H45: 150 | I45: EA | J45: 円 | L45: 0 | O45: =L45*H45 -> 0
A46: 21 | B46: =Y29&" "&W29&X29&" "&U29&V29 -> SanDisk コード：619659177416 型番：SDSQXAF-032G-GN6MN | H46: 80 | I46: EA | J46: 円 | L46: 0 | O46: =L46*H46 -> 0
A47: 22 | B47: =Y30&" "&W30&X30&" "&U30&V30 -> SanDisk コード：619659193416 型番：SDSQXAH-064G-GN6MN | H47: 90 | I47: EA | J47: 円 | L47: 100 | O47: =L47*H47 -> 9000
A48: 23 | B48: =Y31&" "&W31&X31&" "&U31&V31 -> SanDisk コード：619659188467 型番：SDSQXAA-128G-GN6MN | H48: 400 | I48: EA | J48: 円 | L48: 125 | O48: =L48*H48 -> 50000
A49: 24 | B49: =Y32&" "&W32&X32&" "&U32&V32 -> SanDisk コード：619659188511 型番：SDSQXAV-256G-GN6MN | H49: 390 | I49: EA | J49: 円 | L49: 40 | O49: =L49*H49 -> 15600
A50: 25 | B50: =Y33&" "&W33&X33&" "&U33&V33 -> SanDisk コード：619659200473 型番：SDSQUAB-064G-GN6MN | H50: 70 | I50: EA | J50: 円 | L50: 0 | O50: =L50*H50 -> 0
... A52: 27 | B52: =Y35&" "&W35&X35&" "&U35&V35 -> SanDisk コード：619659200497 型番：SDSQUAC-256G-GN6MN | H52: 20 | I52: EA | J52: 円 | L52: 0 | O52: =L52*H52 -> 0
B54: 支払い方法:
B55: 銀行振込
I58: 税率（％） | J58: : 10 | K58: 円 | L58: 小計: | O58: =SUM(O26:O54) -> 305585
L59: 割引額: | O59: 0
L60: 配送料: | O60: 0
I61: 税率（％） | J61: : 10 | L61: 消費税額: | O61: =O58*10% -> 30558.5
K62: 円 | L62: 合計: | O62: =O58+O61 -> 336143.5
A65: お買い上げいただきありがとうございました。

Sheet 1_2_請求書兼領収書 ウエスタンデジタル
E2: ウエスタンデジタル合同会社 | L2: 請求書 兼 領収書
E3: 〒108-0075 東京都港区港南1-6-31 | T3: 番号
E4: 品川東急ビル3F | S4: 仕入れ元
S5: 仕入れ先
H6: 発送番号 | K6: 発送日 | N6: ページ
H7: 87482297 | K7: 45762 | N7: 1の1
E8: 登録番号: T2010401090562 | H8: 発送業者 | L8: B/L | S8: № | V8: 型番 | X8: JANコード
H9: 佐川急便 | S9: 1 | T9: 89 | U9: 型番： | V9: SDSQUAB-128G-GH3MA | W9: コード： | X9: 619659201579 | Y9: SanDisk
S10: 2 | T10: 114 | U10: 型番： | V10: SDSQUAC-256G-GH3MA | W10: コード： | X10: 619659201555 | Y10: SanDisk
E11: 請求番号 | G11: 請求日 | K11: 注文番号 | S11: 3 | T11: 167 | U11: 型番： | V11: SDSQXAT-032G-GH3MA | W11: コード： | X11: 619659197940 | Y11: SanDisk
E12: 3003877451 | G12: =K7 -> 45762 | S12: 4 | T12: 179 | U12: 型番： | V12: SDSQXAH-064G-GH3MA | W12: コード： | X12: 619659197933 | Y12: SanDisk
E13: 受注番号 | G13: 配送条件 | K13: 貿易取引条件 | S13: 5 | T13: 197 | U13: 型番： | V13: SDSQXAA-128G-GH3MA | W13: コード： | X13: 619659197926 | Y13: SanDisk
E14: S0022047564 | G14: 元払い | S14: 6 | T14: 212 | U14: 型番： | V14: SDSQXAV-256G-GH3MA | W14: コード： | X14: 619659197964 | Y14: SanDisk
E15: 出荷先: | F15: OT91990 | J15: 請求先: | K15: =F15 -> OT91990 | S15: 7 | T15: 287 | U15: 型番： | V15: SDSQQNR-032G-GH3IA | W15: コード： | X15: 619659197704 | Y15: SanDisk
E16: 東映無線株式会社 | J16: =E16 -> 東映無線株式会社 | S16: 8 | T16: 292 | U16: 型番： | V16: SDSQQNR-064G-GH3IA | W16: コード： | X16: 619659197711 | Y16: SanDisk
E17: 101-0021 東京都千代田区 | J17: =E17 -> 101-0021 東京都千代田区 | S17: 9 | T17: 297 | U17: 型番： | V17: SDSQQNR-128G-GH3IA | W17: コード： | X17: 619659198923 | Y17: SanDisk
E18: 外神田1丁目10番11号 | J18: =E18 -> 外神田1丁目10番11号 | S18: 10 | T18: 302 | U18: 型番： | V18: SDSQQNR-256G-GH3IA | W18: コード： | X18: 619659198930 | Y18: SanDisk
E19: 東京ラジオデパート | J19: =E19 -> 東京ラジオデパート | S19: 11 | T19: 365 | U19: 型番： | V19: SDSDXV2-064G-GHJIN | W19: コード： | X19: 619659197834 | Y19: SanDisk
E20: 日本国 | J20: =E20 -> 日本国 | S20: 12 | T20: 373 | U20: 型番： | V20: SDSDXVA-128G-GHJIN | W20: コード： | X20: 619659197841 | Y20: SanDisk
S21: 13 | T21: 380 | U21: 型番： | V21: SDSDXVV-256G-GHJIN | W21: コード： | X21: 619659197858 | Y21: SanDisk
S22: 14 | T22: 407 | U22: 型番： | V22: SDSDXXD-128G-GHJIN | W22: コード： | X22: 619659197889 | Y22: SanDisk
S23: 15 | T23: 419 | U23: 型番： | V23: SDSDXXD-256G-GHJIN | W23: コード： | X23: 619659197896 | Y23: SanDisk
B24: № | S24: 16 | T24: 434 | U24: 型番： | V24: SDSDXEP-064G-GHJIN | W24: コード： | X24: 619659201494 | Y24: SanDisk
S25: 17 | T25: 437 | U25: 型番： | V25: SDSDXEP-128G-GHJIN | W25: コード： | X25: 619659201500 | Y25: SanDisk
B26: 1 | C26: =Y9&" "&W9&X9&" "&U9&V9 -> SanDisk コード：619659201579 型番：SDSQUAB-128G-GH3MA | H26: 150 | I26: EA | J26: 円 | L26: 70 | O26: =L26*H26 -> 10500 | S26: 18 | T26: 180 | U26: 型番： | V26: SDSQXA2-064G-GN6MA | W26: コード： | X26: 619659169770 | Y26: SanDisk
B27: 2 | C27: =Y10&" "&W10&X10&" "&U10&V10 -> SanDisk コード：619659201555 型番：SDSQUAC-256G-GH3MA | H27: 550 | I27: EA | J27: 円 | L27: 0 | O27: =L27*H27 -> 0 | S27: 19 | T27: 199 | U27: 型番： | V27: SDSQXA1-128G-GN6MN | W27: コード： | X27: 619659180034 | Y27: SanDisk
B28: 3 | C28: =Y11&" "&W11&X11&" "&U11&V11 -> SanDisk コード：619659197940 型番：SDSQXAT-032G-GH3MA | H28: 50 | I28: EA | J28: 円 | L28: 0 | O28: =L28*H28 -> 0 | S28: 20 | T28: 214 | U28: 型番： | V28: SDSQXA1-256G-GN6MN | W28: コード： | X28: 619659180041 | Y28: SanDisk
B29: 4 | C29: =Y12&" "&W12&X12&" "&U12&V12 -> SanDisk コード：619659197933 型番：SDSQXAH-064G-GH3MA | H29: 80 | I29: EA | J29: 円 | L29: 60 | O29: =L29*H29 -> 4800 | S29: 21 | T29: 168 | U29: 型番： | V29: SDSQXAF-032G-GN6MN | W29: コード： | X29: 619659177416 | Y29: SanDisk
B30: 5 | C30: =Y13&" "&W13&X13&" "&U13&V13 -> SanDisk コード：619659197926 型番：SDSQXAA-128G-GH3MA | H30: 150 | I30: EA | J30: 円 | L30: 150 | O30: =L30*H30 -> 22500 | S30: 22 | T30: 195 | U30: 型番： | V30: SDSQXAH-064G-GN6MN | W30: コード： | X30: 619659193416 | Y30: SanDisk
B31: 6 | C31: =Y14&" "&W14&X14&" "&U14&V14 -> SanDisk コード：619659197964 型番：SDSQXAV-256G-GH3MA | H31: 70 | I31: EA | J31: 円 | L31: 35 | O31: =L31*H31 -> 2450 | S31: 23 | T31: 198 | U31: 型番： | V31: SDSQXAA-128G-GN6MN | W31: コード： | X31: 619659188467 | Y31: SanDisk
B32: 7 | C32: =Y15&" "&W15&X15&" "&U15&V15 -> SanDisk コード：619659197704 型番：SDSQQNR-032G-GH3IA | H32: 35 | I32: EA | J32: 円 | L32: 0 | O32: =L32*H32 -> 0 | S32: 24 | T32: 213 | U32: 型番： | V32: SDSQXAV-256G-GN6MN | W32: コード： | X32: 619659188511 | Y32: SanDisk
B33: 8 | C33: =Y16&" "&W16&X16&" "&U16&V16 -> SanDisk コード：619659197711 型番：SDSQQNR-064G-GH3IA | H33: 40 | I33: EA | J33: 円 | L33: 0 | O33: =L33*H33 -> 0 | S33: 25 | T33: 63 | U33: 型番： | V33: SDSQUAB-064G-GN6MN | W33: コード： | X33: 619659200473 | Y33: SanDisk
B34: 9 | C34: =Y17&" "&W17&X17&" "&U17&V17 -> SanDisk コード：619659198923 型番：SDSQQNR-128G-GH3IA | H34: 70 | I34: EA | J34: 円 | L34: 0 | O34: =L34*H34 -> 0 | S34: 26 | T34: 90 | U34: 型番： | V34: SDSQUAB-128G-GN6MN | W34: コード： | X34: 619659200480 | Y34: SanDisk
B35: 10 | C35: =Y18&" "&W18&X18&" "&U18&V18 -> SanDisk コード：619659198930 型番：SDSQQNR-256G-GH3IA | H35: 25 | I35: EA | J35: 円 | L35: 0 | O35: =L35*H35 -> 0 | S35: 27 | T35: 115 | U35: 型番： | V35: SDSQUAC-256G-GN6MN | W35: コード： | X35: 619659200497 | Y35: SanDisk
B36: 11 | C36: =Y19&" "&W19&X19&" "&U19&V19 -> SanDisk コード：619659197834 型番：SDSDXV2-064G-GHJIN | H36: 50 | I36: EA | J36: 円 | L36: 0 | O36: =L36*H36 -> 0 | S36: 28 | U36: 型番： | V36: #N/A | W36: コード： | X36: #N/A | Y36: SanDisk
B37: 12 | C37: =Y20&" "&W20&X20&" "&U20&V20 -> SanDisk コード：619659197841 型番：SDSDXVA-128G-GHJIN | H37: 650 | I37: EA | J37: 円 | L37: 50 | O37: =L37*H37 -> 32500 | S37: 29 | U37: 型番： | V37: #N/A | W37: コード： | X37: #N/A | Y37: SanDisk
B38: 13 | C38: =Y21&" "&W21&X21&" "&U21&V21 -> SanDisk コード：619659197858 型番：SDSDXVV-256G-GHJIN | H38: 250 | I38: EA | J38: 円 | L38: 0 | O38: =L38*H38 -> 0 | S38: 30 | U38: 型番： | V38: #N/A | W38: コード： | X38: #N/A | Y38: SanDisk
B39: 14 | C39: =Y22&" "&W22&X22&" "&U22&V22 -> SanDisk コード：619659197889 型番：SDSDXXD-128G-GHJIN | H39: 350 | I39: EA | J39: 円 | L39: 0 | O39: =L39*H39 -> 0
B40: 15 | C40: =Y23&" "&W23&X23&" "&U23&V23 -> SanDisk コード：619659197896 型番：SDSDXXD-256G-GHJIN | H40: 100 | I40: EA | J40: 円 | L40: 0 | O40: =L40*H40 -> 0
B41: 16 | C41: =Y24&" "&W24&X24&" "&U24&V24 -> SanDisk コード：619659201494 型番：SDSDXEP-064G-GHJIN | H41: 20 | I41: EA | J41: 円 | L41: 0 | O41: =L41*H41 -> 0
B42: 17 | C42: =Y25&" "&W25&X25&" "&U25&V25 -> SanDisk コード：619659201500 型番：SDSDXEP-128G-GHJIN | H42: 15 | I42: EA | J42: 円 | L42: 9999 | O42: =L42*H42 -> 149985
B43: 18 | C43: =Y26&" "&W26&X26&" "&U26&V26 -> SanDisk コード：619659169770 型番：SDSQXA2-064G-GN6MA | H43: 300 | I43: EA | J43: 円 | L43: 0 | O43: =L43*H43 -> 0
B44: 19 | C44: =Y27&" "&W27&X27&" "&U27&V27 -> SanDisk コード：619659180034 型番：SDSQXA1-128G-GN6MN | H44: 350 | I44: EA | J44: 円 | L44: 0 | O44: =L44*H44 -> 0
B45: 20 | C45: =Y28&" "&W28&X28&" "&U28&V28 -> SanDisk コード：619659180041 型番：SDSQXA1-256G-GN6MN | H45: 150 | I45: EA | J45: 円 | L45: 0 | O45: =L45*H45 -> 0
B46: 21 | C46: =Y29&" "&W29&X29&" "&U29&V29 -> SanDisk コード：619659177416 型番：SDSQXAF-032G-GN6MN | H46: 80 | I46: EA | J46: 円 | L46: 0 | O46: =L46*H46 -> 0
B47: 22 | C47: =Y30&" "&W30&X30&" "&U30&V30 -> SanDisk コード：619659193416 型番：SDSQXAH-064G-GN6MN | H47: 90 | I47: EA | J47: 円 | L47: 100 | O47: =L47*H47 -> 9000
B48: 23 | C48: =Y31&" "&W31&X31&" "&U31&V31 -> SanDisk コード：619659188467 型番：SDSQXAA-128G-GN6MN | H48: 400 | I48: EA | J48: 円 | L48: 125 | O48: =L48*H48 -> 50000
B49: 24 | C49: =Y32&" "&W32&X32&" "&U32&V32 -> SanDisk コード：619659188511 型番：SDSQXAV-256G-GN6MN | H49: 390 | I49: EA | J49: 円 | L49: 40 | O49: =L49*H49 -> 15600
B50: 25 | C50: =Y33&" "&W33&X33&" "&U33&V33 -> SanDisk コード：619659200473 型番：SDSQUAB-064G-GN6MN | H50: 70 | I50: EA | J50: 円 | L50: 0 | O50: =L50*H50 -> 0
... B52: 27 | C52: =Y35&" "&W35&X35&" "&U35&V35 -> SanDisk コード：619659200497 型番：SDSQUAC-256G-GN6MN | H52: 20 | I52: EA | J52: 円 | L52: 0 | O52: =L52*H52 -> 0
B53: 28
B54: 29
B55: 30
C57: 支払い方法:
C58: 銀行振込
I61: 税率（％）: 10 | K61: 円 | L61: 小計: | O61: =SUM(O26:O57) -> 305585
L62: 割引額: | O62: 0
L63: 配送料: | O63: 0
I64: 税率（％）: 10 | L64: 消費税額: | O64: =O61*10% -> 30558.5
K65: 円 | L65: 合計: | O65: =O61+O64 -> 336143.5
B70: お買い上げいただきありがとうございました。

Sheet 1_2_納品書ウエスタンデジタル 
G2: Page | H2: 1 of 1
C3: 納品書 | I3: ウエスタンデジタル合同会社
I4: 東京都港区港南1-6-31
I5: 品川東急ビル3F
I6: カスタマーサービス電話番号：0066-3381-4967
A7: 注文番号： | C7: 配送番号： | D7: 90259161
A8: お名前： | B8: ='1_2_請求書兼領収書 ウエスタンデジタル'!E16 -> 東映無線株式会社 | E8: 日付： | F8: ='1_2_請求書兼領収書 ウエスタンデジタル'!K7 -> 45762
A9: 住所： | B9: ='1_2_請求書兼領収書 ウエスタンデジタル'!E18 -> 外神田1丁目10番11号 | E9: 連絡先：
B10: ='1_2_請求書兼領収書 ウエスタンデジタル'!E19 -> 東京ラジオデパート | E10: 電話番号： | F10: 03-32535660
B11: ="〒"&LEFT('1_2_請求書兼領収書 ウエスタンデジタル'!E17,8) -> 〒101-0021
B12: JAPAN
A14: 製品名 | G14: 数量
A15: ='1_2_請求書兼領収書 ウエスタンデジタル'!C26 -> SanDisk コード：619659201579 型番：SDSQUAB-128G-GH3MA | G15: ='1_2_請求書兼領収書 ウエスタンデジタル'!H26 -> 150
A16: ='1_2_請求書兼領収書 ウエスタンデジタル'!C27 -> SanDisk コード：619659201555 型番：SDSQUAC-256G-GH3MA | G16: ='1_2_請求書兼領収書 ウエスタンデジタル'!H27 -> 550
A17: ='1_2_請求書兼領収書 ウエスタンデジタル'!C28 -> SanDisk コード：619659197940 型番：SDSQXAT-032G-GH3MA | G17: ='1_2_請求書兼領収書 ウエスタンデジタル'!H28 -> 50
A18: ='1_2_請求書兼領収書 ウエスタンデジタル'!C29 -> SanDisk コード：619659197933 型番：SDSQXAH-064G-GH3MA | G18: ='1_2_請求書兼領収書 ウエスタンデジタル'!H29 -> 80
A19: ='1_2_請求書兼領収書 ウエスタンデジタル'!C30 -> SanDisk コード：619659197926 型番：SDSQXAA-128G-GH3MA | G19: ='1_2_請求書兼領収書 ウエスタンデジタル'!H30 -> 150
A20: ='1_2_請求書兼領収書 ウエスタンデジタル'!C31 -> SanDisk コード：619659197964 型番：SDSQXAV-256G-GH3MA | G20: ='1_2_請求書兼領収書 ウエスタンデジタル'!H31 -> 70
A21: ='1_2_請求書兼領収書 ウエスタンデジタル'!C32 -> SanDisk コード：619659197704 型番：SDSQQNR-032G-GH3IA | G21: ='1_2_請求書兼領収書 ウエスタンデジタル'!H32 -> 35
A22: ='1_2_請求書兼領収書 ウエスタンデジタル'!C33 -> SanDisk コード：619659197711 型番：SDSQQNR-064G-GH3IA | G22: ='1_2_請求書兼領収書 ウエスタンデジタル'!H33 -> 40
A23: ='1_2_請求書兼領収書 ウエスタンデジタル'!C34 -> SanDisk コード：619659198923 型番：SDSQQNR-128G-GH3IA | G23: ='1_2_請求書兼領収書 ウエスタンデジタル'!H34 -> 70
A24: ='1_2_請求書兼領収書 ウエスタンデジタル'!C35 -> SanDisk コード：619659198930 型番：SDSQQNR-256G-GH3IA | G24: ='1_2_請求書兼領収書 ウエスタンデジタル'!H35 -> 25
A25: ='1_2_請求書兼領収書 ウエスタンデジタル'!C36 -> SanDisk コード：619659197834 型番：SDSDXV2-064G-GHJIN | G25: ='1_2_請求書兼領収書 ウエスタンデジタル'!H36 -> 50
A26: ='1_2_請求書兼領収書 ウエスタンデジタル'!C37 -> SanDisk コード：619659197841 型番：SDSDXVA-128G-GHJIN | G26: ='1_2_請求書兼領収書 ウエスタンデジタル'!H37 -> 650
... A44: ='1_2_請求書兼領収書 ウエスタンデジタル'!C55 -> 0 | G44: ='1_2_請求書兼領収書 ウエスタンデジタル'!H55 -> 0
F45: 合計： | G45: =SUM(G15:I44) -> 4655
A47: この度はサンディスクストアにて商品をお買い上げいただき誠にありがとうございます。
A48: 商品を送付させていただきます。今後ともご愛顧賜りますよう何卒よろしくお願い申し上げます。

Sheet 1_3_請求書兼領収書
D2: サンディスク合同会社 | K2: 請求書 兼 領収書
D3: 〒108-0075 東京都港区港南1-6-31
D4: 品川東急ビル3F
G6: 発送番号 | J6: 発送日 | M6: ページ
G7: 87482297 | J7: 45405 | M7: 1の1
D8: 登録番号: T2010401090562 | G8: 発送業者 | K8: B/L | R8: № | U8: 型番 | W8: JANコード
G9: 佐川急便 | R9: 1 | S9: 63 | T9: 型番： | U9: SDSQUAB-064G-GN6MN | V9: JANコード： | W9: 619659200473
R10: 2 | S10: 90 | T10: 型番： | U10: SDSQUAB-128G-GN6MN | V10: JANコード： | W10: 619659200480
D11: 請求番号 | F11: 請求日 | J11: 注文番号 | R11: 3 | S11: 115 | T11: 型番： | U11: SDSQUAC-256G-GN6MN | V11: JANコード： | W11: 619659200497
D12: 3003877451 | F12: =J7 -> 45405 | R12: 4 | S12: 138 | T12: 型番： | U12: SDSQUAC-512G-GN6MN | V12: JANコード： | W12: 619659200503
D13: 受注番号 | F13: 配送条件 | J13: 貿易取引条件 | R13: 5 | S13: 168 | T13: 型番： | U13: SDSQXAF-032G-GN6MN | V13: JANコード： | W13: 619659177416
D14: S0022047564 | F14: 元払い | R14: 6 | S14: 180 | T14: 型番： | U14: SDSQXA2-064G-GN6MA | V14: JANコード： | W14: 619659169770
D15: 出荷先: | E15: OT91990 | I15: 請求先: | J15: =E15 -> OT91990 | R15: 7 | S15: 199 | T15: 型番： | U15: SDSQXA1-128G-GN6MN | V15: JANコード： | W15: 619659180034
D16: 東映無線株式会社 | I16: =D16 -> 東映無線株式会社 | R16: 8 | S16: 214 | T16: 型番： | U16: SDSQXA1-256G-GN6MN | V16: JANコード： | W16: 619659180041
D17: 101-0021 東京都千代田区 | I17: =D17 -> 101-0021 東京都千代田区 | R17: 9 | S17: 195 | T17: 型番： | U17: SDSQXAH-064G-GN6MN | V17: JANコード： | W17: 619659193416
D18: 外神田1丁目10番11号 | I18: =D18 -> 外神田1丁目10番11号 | R18: 10 | S18: 198 | T18: 型番： | U18: SDSQXAA-128G-GN6MN | V18: JANコード： | W18: 619659188467
D19: 東京ラジオデパート | I19: =D19 -> 東京ラジオデパート | R19: 11 | S19: 213 | T19: 型番： | U19: SDSQXAV-256G-GN6MN | V19: JANコード： | W19: 619659188511
D20: 日本国 | I20: =D20 -> 日本国 | R20: 12 | S20: 230 | T20: 型番： | U20: SDSQXAV-512G-GN6MN | V20: JANコード： | W20: 619659189655
R21: 13 | S21: 330 | T21: 型番： | U21: SDSDUNB-064G-GH3NN | V21: JANコード： | W21: 619659200671
R22: 14 | S22: 340 | T22: 型番： | U22: SDSDUNB-128G-GH3NN | V22: JANコード： | W22: 619659200107
R23: 15 | S23: 350 | T23: 型番： | U23: SDSDUNC-256G-GH3NN | V23: JANコード： | W23: 619659200701
A24: № | R24: 16 | S24: 390 | T24: 型番： | U24: SDSDXXO-032G-GN4IN | V24: JANコード： | W24: 619659188689
A26: 1 | B26: =T9&U9&" "&V9&W9 -> 型番：SDSQUAB-064G-GN6MN JANコード：619659200473 | G26: 1 | H26: EA | I26: 円 | K26: 0 | N26: =K26*G26 -> 0
A28: 2 | B28: =T10&U10&" "&V10&W10 -> 型番：SDSQUAB-128G-GN6MN JANコード：619659200480 | G28: 2 | H28: EA | I28: 円 | K28: 55 | N28: =K28*G28 -> 110
B29: UHS-I / U1 / A1 / C10 /
A30: 3 | B30: =T11&U11&" "&V11&W11 -> 型番：SDSQUAC-256G-GN6MN JANコード：619659200497 | G30: 3 | H30: EA | I30: 円 | K30: 0 | N30: =K30*G30 -> 0
A32: 4 | B32: =T12&U12&" "&V12&W12 -> 型番：SDSQUAC-512G-GN6MN JANコード：619659200503 | G32: 4 | H32: EA | I32: 円 | K32: 0 | N32: =K32*G32 -> 0
B33: UHS-I / Nintendo Switch /
A34: 5 | B34: =T13&U13&" "&V13&W13 -> 型番：SDSQXAF-032G-GN6MN JANコード：619659177416 | G34: 5 | H34: EA | I34: 円 | K34: 0 | N34: =K34*G34 -> 0
B35: U3 / Class10 /
A36: 6 | B36: =T14&U14&" "&V14&W14 -> 型番：SDSQXA2-064G-GN6MA JANコード：619659169770 | G36: 6 | H36: EA | I36: 円 | K36: 0 | N36: =K36*G36 -> 0
A38: 7 | B38: =T15&U15&" "&V15&W15 -> 型番：SDSQXA1-128G-GN6MN JANコード：619659180034 | G38: 7 | H38: EA | I38: 円 | K38: 0 | N38: =K38*G38 -> 0
B39: U3 / V30 / 4K /
A40: 8 | B40: =T16&U16&" "&V16&W16 -> 型番：SDSQXA1-256G-GN6MN JANコード：619659180041 | G40: 8 | H40: EA | I40: 円 | K40: 0 | N40: =K40*G40 -> 0
B41: U3 / V30 / A1 / 4K /
A42: 9 | B42: =T17&U17&" "&V17&W17 -> 型番：SDSQXAH-064G-GN6MN JANコード：619659193416 | G42: 9 | H42: EA | I42: 円 | K42: 100 | N42: =K42*G42 -> 900
B43: 4K /
A44: 10 | B44: =T18&U18&" "&V18&W18 -> 型番：SDSQXAA-128G-GN6MN JANコード：619659188467 | G44: 11 | H44: EA | I44: 円 | K44: 125 | N44: =K44*G44 -> 1375
B45: UHS-I / U3 / V30 / 4K /
A46: 11 | B46: =T19&U19&" "&V19&W19 -> 型番：SDSQXAV-256G-GN6MN JANコード：619659188511 | G46: 12 | H46: EA | I46: 円 | K46: 40 | N46: =K46*G46 -> 480
B47: Nintendo Switch /
A48: 12 | B48: =T20&U20&" "&V20&W20 -> 型番：SDSQXAV-512G-GN6MN JANコード：619659189655 | G48: 13 | H48: EA | I48: 円 | K48: 0 | N48: =K48*G48 -> 0
B49: UHS-I /
A50: 13 | B50: =T21&U21&" "&V21&W21 -> 型番：SDSDUNB-064G-GH3NN JANコード：619659200671 | G50: 14 | H50: EA | I50: 円 | K50: 0 | N50: =K50*G50 -> 0
B51: UHS-I / Class10 /
A52: 14 | B52: =T22&U22&" "&V22&W22 -> 型番：SDSDUNB-128G-GH3NN JANコード：619659200107 | G52: 15 | H52: EA | I52: 円 | K52: 0 | N52: =K52*G52 -> 0
B53: UHS-I / Class10 /
A54: 15 | B54: =T23&U23&" "&V23&W23 -> 型番：SDSDUNC-256G-GH3NN JANコード：619659200701 | G54: 16 | H54: EA | I54: 円 | K54: 0 | N54: =K54*G54 -> 0
B55: UHS-I / Class10 /
A56: 16 | B56: =T24&U24&" "&V24&W24 -> 型番：SDSDXXO-032G-GN4IN JANコード：619659188689 | G56: 17 | H56: EA | I56: 円 | K56: 0 | N56: =K56*G56 -> 0
B57: UHS-I / U3 / V30 / C10 / 4K /
B59: 支払い方法:
B60: Mastercard
H63: 税率（％）: 10 | J63: 円 | K63: 小計: | N63: =SUM(N26:N59) -> 2865
K64: 割引額: | N64: 0
K65: 配送料: | N65: 0
H66: 税率（％）: 10 | K66: 消費税額: | N66: =N63*10% -> 286.5
J67: 円 | K67: 合計: | N67: =N63+N66 -> 3151.5
A72: お買い上げいただきありがとうございました。

Sheet 1_3_納品書 
G2: Page | H2: 1 of 1
C3: 納品書 | I3: サンディスク合同会社
I4: 東京都港区港南1-6-31
I5: 品川東急ビル3F
I6: カスタマーサービス電話番号：0120-893-009
A7: 注文番号： | C7: 配送番号： | D7: 90259161
A8: お名前： | B8: 東映無線株式会社 | E8: 日付： | F8: 45405
A9: 住所： | B9: 外神田1丁目10番11号 | E9: 連絡先：
B10: 東京ラジオデパート | E10: 電話番号： | F10: 03-32535660
B11: 〒101-0021
B12: JAPAN
A14: 製品名 | G14: 数量
A15: 型番：SDSQUAB-064G-GN6MN JANコード：619659200473 | G15: 1
A16: 型番：SDSQUAB-128G-GN6MN JANコード：619659200480 | G16: 2
A17: 型番：SDSQUAC-256G-GN6MN JANコード：619659200497 | G17: 3
A18: 型番：SDSQUAC-512G-GN6MN JANコード：619659200503 | G18: 4
A19: 型番：SDSQXAF-032G-GN6MN JANコード：619659177416 | G19: 5
A20: 型番：SDSQXA2-064G-GN6MA JANコード：619659169770 | G20: 6
A21: 型番：SDSQXA1-128G-GN6MN JANコード：619659180034 | G21: 7
A22: 型番：SDSQXA1-256G-GN6MN JANコード：619659180041 | G22: 8
A23: 型番：SDSQXAH-064G-GN6MN JANコード：619659193416 | G23: 9
A24: 型番：SDSQXAA-128G-GN6MN JANコード：619659188467 | G24: 11
A25: 型番：SDSQXAV-256G-GN6MN JANコード：619659188511 | G25: 12
A26: 型番：SDSQXAV-512G-GN6MN JANコード：619659189655 | G26: 13
... A30: 型番：SDSDXXO-032G-GN4IN JANコード：619659188689 | G30: 17
F31: 合計： | G31: =SUM(G15:I30) -> 143
A33: この度はサンディスクストアにて商品をお買い上げいただき誠にありがとうございます。
A34: 商品を送付させていただきます。今後ともご愛顧賜りますよう何卒よろしくお願い申し上げます。

Sheet 1_4_請求書兼領収書 ウエスタンデジタル　数式入り
E2: ウエスタンデジタル合同会社 | L2: 請求書 兼 領収書
E3: 〒108-0075 東京都港区港南1-6-31 | T3: アカウント
E4: 品川東急ビル3F | S4: 番号 | T4: 105
H6: 発送番号 | K6: 発送日 | N6: ページ
H7: 87482297 | K7: 45762 | N7: 1の1
E8: 登録番号: T2010401090562 | H8: 発送業者 | L8: B/L | S8: № | V8: 型番 | X8: JANコード
H9: 佐川急便 | S9: 1 | T9: 89 | U9: 型番： | V9: SDSQUAB-128G-GH3MA | W9: コード： | X9: 619659201579 | Y9: SanDisk
S10: 2 | T10: 114 | U10: 型番： | V10: SDSQUAC-256G-GH3MA | W10: コード： | X10: 619659201555 | Y10: SanDisk
E11: 請求番号 | G11: 請求日 | K11: 注文番号 | S11: 3 | T11: 167 | U11: 型番： | V11: SDSQXAT-032G-GH3MA | W11: コード： | X11: 619659197940 | Y11: SanDisk
E12: 3003877451 | G12: =K7 -> 45762 | S12: 4 | T12: 179 | U12: 型番： | V12: SDSQXAH-064G-GH3MA | W12: コード： | X12: 619659197933 | Y12: SanDisk
E13: 受注番号 | G13: 配送条件 | K13: 貿易取引条件 | S13: 5 | T13: 197 | U13: 型番： | V13: SDSQXAA-128G-GH3MA | W13: コード： | X13: 619659197926 | Y13: SanDisk
E14: S0022047564 | G14: 元払い | S14: 6 | T14: 212 | U14: 型番： | V14: SDSQXAV-256G-GH3MA | W14: コード： | X14: 619659197964 | Y14: SanDisk
E15: 出荷先: | F15: OT91990 | J15: 請求先: | K15: =F15 -> OT91990 | S15: 7 | T15: 287 | U15: 型番： | V15: SDSQQNR-032G-GH3IA | W15: コード： | X15: 619659197704 | Y15: SanDisk
E16: 東葛電子販売 | J16: =E16 -> 東葛電子販売 | S16: 8 | T16: 292 | U16: 型番： | V16: SDSQQNR-064G-GH3IA | W16: コード： | X16: 619659197711 | Y16: SanDisk
E17: 〒124-0014 | J17: =E17 -> 〒124-0014 | S17: 9 | T17: 297 | U17: 型番： | V17: SDSQQNR-128G-GH3IA | W17: コード： | X17: 619659198923 | Y17: SanDisk
E18: 東京都葛飾区東四つ木4－44－1 | J18: =E18 -> 東京都葛飾区東四つ木4－44－1 | S18: 10 | T18: 302 | U18: 型番： | V18: SDSQQNR-256G-GH3IA | W18: コード： | X18: 619659198930 | Y18: SanDisk
E19: 17階1号室 | J19: =E19 -> 17階1号室 | S19: 11 | T19: 365 | U19: 型番： | V19: SDSDXV2-064G-GHJIN | W19: コード： | X19: 619659197834 | Y19: SanDisk
E20: 日本国 | J20: =E20 -> 日本国 | S20: 12 | T20: 373 | U20: 型番： | V20: SDSDXVA-128G-GHJIN | W20: コード： | X20: 619659197841 | Y20: SanDisk
S21: 13 | T21: 380 | U21: 型番： | V21: SDSDXVV-256G-GHJIN | W21: コード： | X21: 619659197858 | Y21: SanDisk
S22: 14 | T22: 407 | U22: 型番： | V22: SDSDXXD-128G-GHJIN | W22: コード： | X22: 619659197889 | Y22: SanDisk
S23: 15 | T23: 419 | U23: 型番： | V23: SDSDXXD-256G-GHJIN | W23: コード： | X23: 619659197896 | Y23: SanDisk
A24: No. | B24: 製品型番 | G24: 数量 | I24: 単価 | J24: 商品単価 | M24: 商品金額 | S24: 16 | T24: 434 | U24: 型番： | V24: SDSDXEP-064G-GHJIN | W24: コード： | X24: 619659201494 | Y24: SanDisk
B25: 製品詳細 | S25: 17 | T25: 437 | U25: 型番： | V25: SDSDXEP-128G-GHJIN | W25: コード： | X25: 619659201500 | Y25: SanDisk
A26: 1 | B26: =Y9&" "&W9&X9&" "&U9&V9 -> SanDisk コード：619659201579 型番：SDSQUAB-128G-GH3MA | H26: 150 | I26: EA | J26: 円 | L26: 70 | O26: =L26*H26 -> 10500 | S26: 18 | T26: 180 | U26: 型番： | V26: SDSQXA2-064G-GN6MA | W26: コード： | X26: 619659169770 | Y26: SanDisk
A27: 2 | B27: =Y10&" "&W10&X10&" "&U10&V10 -> SanDisk コード：619659201555 型番：SDSQUAC-256G-GH3MA | H27: 550 | I27: EA | J27: 円 | L27: 0 | O27: =L27*H27 -> 0 | S27: 19 | T27: 199 | U27: 型番： | V27: SDSQXA1-128G-GN6MN | W27: コード： | X27: 619659180034 | Y27: SanDisk
A28: 3 | B28: =Y11&" "&W11&X11&" "&U11&V11 -> SanDisk コード：619659197940 型番：SDSQXAT-032G-GH3MA | H28: 50 | I28: EA | J28: 円 | L28: 0 | O28: =L28*H28 -> 0 | S28: 20 | T28: 214 | U28: 型番： | V28: SDSQXA1-256G-GN6MN | W28: コード： | X28: 619659180041 | Y28: SanDisk
A29: 4 | B29: =Y12&" "&W12&X12&" "&U12&V12 -> SanDisk コード：619659197933 型番：SDSQXAH-064G-GH3MA | H29: 80 | I29: EA | J29: 円 | L29: 60 | O29: =L29*H29 -> 4800 | S29: 21 | T29: 168 | U29: 型番： | V29: SDSQXAF-032G-GN6MN | W29: コード： | X29: 619659177416 | Y29: SanDisk
A30: 5 | B30: =Y13&" "&W13&X13&" "&U13&V13 -> SanDisk コード：619659197926 型番：SDSQXAA-128G-GH3MA | H30: 150 | I30: EA | J30: 円 | L30: 150 | O30: =L30*H30 -> 22500 | S30: 22 | T30: 195 | U30: 型番： | V30: SDSQXAH-064G-GN6MN | W30: コード： | X30: 619659193416 | Y30: SanDisk
A31: 6 | B31: =Y14&" "&W14&X14&" "&U14&V14 -> SanDisk コード：619659197964 型番：SDSQXAV-256G-GH3MA | H31: 70 | I31: EA | J31: 円 | L31: 35 | O31: =L31*H31 -> 2450 | S31: 23 | T31: 198 | U31: 型番： | V31: SDSQXAA-128G-GN6MN | W31: コード： | X31: 619659188467 | Y31: SanDisk
A32: 7 | B32: =Y15&" "&W15&X15&" "&U15&V15 -> SanDisk コード：619659197704 型番：SDSQQNR-032G-GH3IA | H32: 35 | I32: EA | J32: 円 | L32: 0 | O32: =L32*H32 -> 0 | S32: 24 | T32: 213 | U32: 型番： | V32: SDSQXAV-256G-GN6MN | W32: コード： | X32: 619659188511 | Y32: SanDisk
A33: 8 | B33: =Y16&" "&W16&X16&" "&U16&V16 -> SanDisk コード：619659197711 型番：SDSQQNR-064G-GH3IA | H33: 40 | I33: EA | J33: 円 | L33: 0 | O33: =L33*H33 -> 0 | S33: 25 | T33: 63 | U33: 型番： | V33: SDSQUAB-064G-GN6MN | W33: コード： | X33: 619659200473 | Y33: SanDisk
A34: 9 | B34: =Y17&" "&W17&X17&" "&U17&V17 -> SanDisk コード：619659198923 型番：SDSQQNR-128G-GH3IA | H34: 70 | I34: EA | J34: 円 | L34: 0 | O34: =L34*H34 -> 0 | S34: 26 | T34: 90 | U34: 型番： | V34: SDSQUAB-128G-GN6MN | W34: コード： | X34: 619659200480 | Y34: SanDisk
A35: 10 | B35: =Y18&" "&W18&X18&" "&U18&V18 -> SanDisk コード：619659198930 型番：SDSQQNR-256G-GH3IA | H35: 25 | I35: EA | J35: 円 | L35: 0 | O35: =L35*H35 -> 0 | S35: 27 | T35: 115 | U35: 型番： | V35: SDSQUAC-256G-GN6MN | W35: コード： | X35: 619659200497 | Y35: SanDisk
A36: 11 | B36: =Y19&" "&W19&X19&" "&U19&V19 -> SanDisk コード：619659197834 型番：SDSDXV2-064G-GHJIN | H36: 50 | I36: EA | J36: 円 | L36: 0 | O36: =L36*H36 -> 0 | S36: 28 | U36: 型番： | V36: #N/A | W36: コード： | X36: #N/A | Y36: SanDisk
A37: 12 | B37: =Y20&" "&W20&X20&" "&U20&V20 -> SanDisk コード：619659197841 型番：SDSDXVA-128G-GHJIN | H37: 650 | I37: EA | J37: 円 | L37: 50 | O37: =L37*H37 -> 32500 | S37: 29 | U37: 型番： | V37: #N/A | W37: コード： | X37: #N/A | Y37: SanDisk
A38: 13 | B38: =Y21&" "&W21&X21&" "&U21&V21 -> SanDisk コード：619659197858 型番：SDSDXVV-256G-GHJIN | H38: 250 | I38: EA | J38: 円 | L38: 0 | O38: =L38*H38 -> 0 | S38: 30 | U38: 型番： | V38: #N/A | W38: コード： | X38: #N/A | Y38: SanDisk
A39: 14 | B39: =Y22&" "&W22&X22&" "&U22&V22 -> SanDisk コード：619659197889 型番：SDSDXXD-128G-GHJIN | H39: 350 | I39: EA | J39: 円 | L39: 0 | O39: =L39*H39 -> 0
A40: 15 | B40: =Y23&" "&W23&X23&" "&U23&V23 -> SanDisk コード：619659197896 型番：SDSDXXD-256G-GHJIN | H40: 100 | I40: EA | J40: 円 | L40: 0 | O40: =L40*H40 -> 0
A41: 16 | B41: =Y24&" "&W24&X24&" "&U24&V24 -> SanDisk コード：619659201494 型番：SDSDXEP-064G-GHJIN | H41: 20 | I41: EA | J41: 円 | L41: 0 | O41: =L41*H41 -> 0
A42: 17 | B42: =Y25&" "&W25&X25&" "&U25&V25 -> SanDisk コード：619659201500 型番：SDSDXEP-128G-GHJIN | H42: 15 | I42: EA | J42: 円 | L42: 9999 | O42: =L42*H42 -> 149985
A43: 18 | B43: =Y26&" "&W26&X26&" "&U26&V26 -> SanDisk コード：619659169770 型番：SDSQXA2-064G-GN6MA | H43: 300 | I43: EA | J43: 円 | L43: 0 | O43: =L43*H43 -> 0
A44: 19 | B44: =Y27&" "&W27&X27&" "&U27&V27 -> SanDisk コード：619659180034 型番：SDSQXA1-128G-GN6MN | H44: 350 | I44: EA | J44: 円 | L44: 0 | O44: =L44*H44 -> 0
A45: 20 | B45: =Y28&" "&W28&X28&" "&U28&V28 -> SanDisk コード：619659180041 型番：SDSQXA1-256G-GN6MN | H45: 150 | I45: EA | J45: 円 | L45: 0 | O45: =L45*H45 -> 0
A46: 21 | B46: =Y29&" "&W29&X29&" "&U29&V29 -> SanDisk コード：619659177416 型番：SDSQXAF-032G-GN6MN | H46: 80 | I46: EA | J46: 円 | L46: 0 | O46: =L46*H46 -> 0
A47: 22 | B47: =Y30&" "&W30&X30&" "&U30&V30 -> SanDisk コード：619659193416 型番：SDSQXAH-064G-GN6MN | H47: 90 | I47: EA | J47: 円 | L47: 100 | O47: =L47*H47 -> 9000
A48: 23 | B48: =Y31&" "&W31&X31&" "&U31&V31 -> SanDisk コード：619659188467 型番：SDSQXAA-128G-GN6MN | H48: 400 | I48: EA | J48: 円 | L48: 125 | O48: =L48*H48 -> 50000
A49: 24 | B49: =Y32&" "&W32&X32&" "&U32&V32 -> SanDisk コード：619659188511 型番：SDSQXAV-256G-GN6MN | H49: 390 | I49: EA | J49: 円 | L49: 40 | O49: =L49*H49 -> 15600
A50: 25 | B50: =Y33&" "&W33&X33&" "&U33&V33 -> SanDisk コード：619659200473 型番：SDSQUAB-064G-GN6MN | H50: 70 | I50: EA | J50: 円 | L50: 0 | O50: =L50*H50 -> 0
... A52: 27 | B52: =Y35&" "&W35&X35&" "&U35&V35 -> SanDisk コード：619659200497 型番：SDSQUAC-256G-GN6MN | H52: 20 | I52: EA | J52: 円 | L52: 0 | O52: =L52*H52 -> 0
B54: 支払い方法:
B55: 銀行振込
I58: 税率（％） | J58: : 10 | K58: 円 | L58: 小計: | O58: =SUM(O26:O54) -> 305585
L59: 割引額: | O59: 0
L60: 配送料: | O60: 0
I61: 税率（％） | J61: : 10 | L61: 消費税額: | O61: =O58*10% -> 30558.5
K62: 円 | L62: 合計: | O62: =O58+O61 -> 336143.5
A65: お買い上げいただきありがとうございました。

Sheet 1_4_納品書ウエスタンデジタル 　数式入り
G2: Page | H2: 1 of 1
C3: 納品書 | I3: ウエスタンデジタル合同会社
I4: 東京都港区港南1-6-31
I5: 品川東急ビル3F | N5: アカウント
I6: カスタマーサービス電話番号：0066-3381-4967 | N6: ='1_4_請求書兼領収書 ウエスタンデジタル 数式入り'!T4 -> 105
A7: 注文番号： | C7: 配送番号： | D7: ='1_4_請求書兼領収書 ウエスタンデジタル 数式入り'!H7 -> 87482297
A8: お名前： | B8: ='1_4_請求書兼領収書 ウエスタンデジタル 数式入り'!E16 -> 東葛電子販売 | E8: 日付： | F8: ='1_4_請求書兼領収書 ウエスタンデジタル 数式入り'!K7 -> 45762
A9: 住所： | B9: ='1_4_請求書兼領収書 ウエスタンデジタル 数式入り'!E18 -> 東京都葛飾区東四つ木4－44－1 | E9: 連絡先：
B10: ='1_4_請求書兼領収書 ウエスタンデジタル 数式入り'!E19 -> 17階1号室 | E10: 電話番号： | F10: 050-1792-1508
B11: ='1_4_請求書兼領収書 ウエスタンデジタル 数式入り'!E17 -> 〒124-0014
B12: JAPAN
A14: 製品名 | G14: 数量
A15: ='1_4_請求書兼領収書 ウエスタンデジタル 数式入り'!B26 -> SanDisk コード：619659201579 型番：SDSQUAB-128G-GH3MA | G15: ='1_4_請求書兼領収書 ウエスタンデジタル 数式入り'!H26 -> 150
A16: ='1_4_請求書兼領収書 ウエスタンデジタル 数式入り'!B27 -> SanDisk コード：619659201555 型番：SDSQUAC-256G-GH3MA | G16: ='1_4_請求書兼領収書 ウエスタンデジタル 数式入り'!H27 -> 550
A17: ='1_4_請求書兼領収書 ウエスタンデジタル 数式入り'!B28 -> SanDisk コード：619659197940 型番：SDSQXAT-032G-GH3MA | G17: ='1_4_請求書兼領収書 ウエスタンデジタル 数式入り'!H28 -> 50
A18: ='1_4_請求書兼領収書 ウエスタンデジタル 数式入り'!B29 -> SanDisk コード：619659197933 型番：SDSQXAH-064G-GH3MA | G18: ='1_4_請求書兼領収書 ウエスタンデジタル 数式入り'!H29 -> 80
A19: ='1_4_請求書兼領収書 ウエスタンデジタル 数式入り'!B30 -> SanDisk コード：619659197926 型番：SDSQXAA-128G-GH3MA | G19: ='1_4_請求書兼領収書 ウエスタンデジタル 数式入り'!H30 -> 150
A20: ='1_4_請求書兼領収書 ウエスタンデジタル 数式入り'!B31 -> SanDisk コード：619659197964 型番：SDSQXAV-256G-GH3MA | G20: ='1_4_請求書兼領収書 ウエスタンデジタル 数式入り'!H31 -> 70
A21: ='1_4_請求書兼領収書 ウエスタンデジタル 数式入り'!B32 -> SanDisk コード：619659197704 型番：SDSQQNR-032G-GH3IA | G21: ='1_4_請求書兼領収書 ウエスタンデジタル 数式入り'!H32 -> 35
A22: ='1_4_請求書兼領収書 ウエスタンデジタル 数式入り'!B33 -> SanDisk コード：619659197711 型番：SDSQQNR-064G-GH3IA | G22: ='1_4_請求書兼領収書 ウエスタンデジタル 数式入り'!H33 -> 40
A23: ='1_4_請求書兼領収書 ウエスタンデジタル 数式入り'!B34 -> SanDisk コード：619659198923 型番：SDSQQNR-128G-GH3IA | G23: ='1_4_請求書兼領収書 ウエスタンデジタル 数式入り'!H34 -> 70
A24: ='1_4_請求書兼領収書 ウエスタンデジタル 数式入り'!B35 -> SanDisk コード：619659198930 型番：SDSQQNR-256G-GH3IA | G24: ='1_4_請求書兼領収書 ウエスタンデジタル 数式入り'!H35 -> 25
A25: ='1_4_請求書兼領収書 ウエスタンデジタル 数式入り'!B36 -> SanDisk コード：619659197834 型番：SDSDXV2-064G-GHJIN | G25: ='1_4_請求書兼領収書 ウエスタンデジタル 数式入り'!H36 -> 50
A26: ='1_4_請求書兼領収書 ウエスタンデジタル 数式入り'!B37 -> SanDisk コード：619659197841 型番：SDSDXVA-128G-GHJIN | G26: ='1_4_請求書兼領収書 ウエスタンデジタル 数式入り'!H37 -> 650
... A41: ='1_4_請求書兼領収書 ウエスタンデジタル 数式入り'!B52 -> SanDisk コード：619659200497 型番：SDSQUAC-256G-GN6MN | G41: ='1_4_請求書兼領収書 ウエスタンデジタル 数式入り'!H52 -> 20
F45: 合計： | G45: =SUM(G15:I44) -> 4655
A47: この度はサンディスクストアにて商品をお買い上げいただき誠にありがとうございます。
A48: 商品を送付させていただきます。今後ともご愛顧賜りますよう何卒よろしくお願い申し上げます。

Sheet 1_5_請求書兼領収書 ウエスタンデジタル　最新
E2: =VLOOKUP(管理!$C$1,管理!A4:S53,2,0) -> サンディスク合同会社 | L2: 請求書 兼 領収書
E3: ="〒"&VLOOKUP(管理!$C$1,管理!A4:S53,3,0)&" "&VLOOKUP(管理!$C$1,管理!A4:T53,4,0) -> 〒108-0075 東京都港区港南1丁目6番31号
E4: =IFERROR( IF(OR(VLOOKUP(管理!$C$1,管理!$A$4:$V$100,5,0)=0, VLOOKUP(管理!$C$1,管理!$A$4:$V$100,5,0)=""), "", VLOOKUP(管理!$C$1,管理!A5:T54,5,0) ), "") -> 品川東急ビル3階
H6: 発送番号 | K6: 発送日 | N6: ページ
H7: 87482297 | K7: =G12 -> 46097 | N7: 1の1
E8: ="登録番号："&VLOOKUP(管理!$C$1,管理!A4:T53,11,0) -> 登録番号：T2010401090562 | H8: 発送業者 | L8: B/L
H9: 佐川急便
E11: 請求番号 | G11: 請求日 | K11: 注文番号
E12: =VLOOKUP(管理!$C$2,管理!A4:S50,17,0) -> 0 | G12: =管理!F1 -> 46097
E13: 受注番号 | G13: 配送条件 | K13: 貿易取引条件
E14: S0022047564 | G14: 元払い
E15: ="出荷先:"&VLOOKUP(管理!C2,管理!A4:T100,14,0) -> 出荷先:245141 | J15: ="請求先:"&VLOOKUP(管理!C2,管理!A4:T100,14,0) -> 請求先:245141
E16: =VLOOKUP(管理!$C2,管理!A4:$AA$103,2,0) -> 柏尾奏利（KASIOshop） | J16: =E16 -> 柏尾奏利（KASIOshop）
E17: ="〒"&VLOOKUP(管理!$C$2,管理!A3:S49,3,0) -> 〒174-0072 | J17: =E17 -> 〒174-0072
E18: =VLOOKUP(管理!$C$2,管理!A4:S50,4,0) -> 東京都板橋区南常盤台1丁目11番6号 | J18: =E18 -> 東京都板橋区南常盤台1丁目11番6号
E19: =VLOOKUP(管理!$C$2,管理!A5:S51,5,0) -> ウエアーハウス303号室 | J19: =E19 -> ウエアーハウス303号室
E20: 日本国 | J20: =E20 -> 日本国
A24: No. | B24: 製品型番 | G24: 数量 | I24: 単価 | J24: 商品単価 | M24: 商品金額
B25: 製品詳細
A26: 1 | B26: ="メーカー : "&[1]SD新基準!$AQ2&" 商品コード : "&[1]SD新基準!$AP2&" 商品モデル番号 : "&[1]SD新基準!$AR2 -> メーカー : SanDisk 商品コード : 9349220005022 商品モデル番号 : 7545783945 | H26: =[1]SD新基準!$L2 -> 0 | I26: EA | J26: 円 | L26: =[1]SD新基準!$AF2 -> 714 | O26: =L26*H26 -> 0
A27: 2 | B27: ="メーカー : "&[1]SD新基準!$AQ3&" 商品コード : "&[1]SD新基準!$AP3&" 商品モデル番号 : "&[1]SD新基準!$AR3 -> メーカー : SanDisk 商品コード : 9349220005039 商品モデル番号 : 9349220005039 | H27: =[1]SD新基準!$L3 -> 0 | I27: EA | J27: 円 | L27: =[1]SD新基準!$AF3 -> 976 | O27: =L27*H27 -> 0
A28: 3 | B28: ="メーカー : "&[1]SD新基準!$AQ4&" 商品コード : "&[1]SD新基準!$AP4&" 商品モデル番号 : "&[1]SD新基準!$AR4 -> メーカー : SanDisk 商品コード : 0619659161651 商品モデル番号 : SDSQUNS-032G-GN3MN | H28: =[1]SD新基準!$L4 -> 200 | I28: EA | J28: 円 | L28: =[1]SD新基準!$AF4 -> 6308 | O28: =L28*H28 -> 1261600
A29: 4 | B29: ="メーカー : "&[1]SD新基準!$AQ5&" 商品コード : "&[1]SD新基準!$AP5&" 商品モデル番号 : "&[1]SD新基準!$AR5 -> メーカー : SanDisk 商品コード : 0619659184384 商品モデル番号 : SDSQUNS-032G-GN3MN | H29: =[1]SD新基準!$L5 -> 200 | I29: EA | J29: 円 | L29: =[1]SD新基準!$AF5 -> 3714 | O29: =L29*H29 -> 742800
A30: 5 | B30: ="メーカー : "&[1]SD新基準!$AQ6&" 商品コード : "&[1]SD新基準!$AP6&" 商品モデル番号 : "&[1]SD新基準!$AR6 -> メーカー : SanDisk 商品コード : 0619659161644, 6195765406328, 7840000001712 商品モデル番号 : SDSQUNS-032G-GN3MA | H30: =[1]SD新基準!$L6 -> 200 | I30: EA | J30: 円 | L30: =[1]SD新基準!$AF6 -> 6686 | O30: =L30*H30 -> 1337200
A31: 6 | B31: ="メーカー : "&[1]SD新基準!$AQ7&" 商品コード : "&[1]SD新基準!$AP7&" 商品モデル番号 : "&[1]SD新基準!$AR7 -> メーカー : SanDisk 商品コード : 0619659134044 商品モデル番号 : SDSQUNB-032G-GN3MN | H31: =[1]SD新基準!$L7 -> 200 | I31: EA | J31: 円 | L31: =[1]SD新基準!$AF7 -> 6127 | O31: =L31*H31 -> 1225400
A32: 7 | B32: ="メーカー : "&[1]SD新基準!$AQ8&" 商品コード : "&[1]SD新基準!$AP8&" 商品モデル番号 : "&[1]SD新基準!$AR8 -> メーカー : SanDisk 商品コード : 0619659078645, 5053460346961, 5554442365203, 6196590786456, 7044447834692, 7123290469845, 7987987901489 商品モデル番号 : SDSDQUA-032G-U46A | H32: =[1]SD新基準!$L8 -> 200 | I32: EA | J32: 円 | L32: =[1]SD新基準!$AF8 -> 6870 | O32: =L32*H32 -> 1374000
A33: 8 | B33: ="メーカー : "&[1]SD新基準!$AQ9&" 商品コード : "&[1]SD新基準!$AP9&" 商品モデル番号 : "&[1]SD新基準!$AR9 -> メーカー : SanDisk 商品コード : 0068888807494, 0619659246518 商品モデル番号 : 43237-2 | H33: =[1]SD新基準!$L9 -> 200 | I33: EA | J33: 円 | L33: =[1]SD新基準!$AF9 -> 8893 | O33: =L33*H33 -> 1778600
A34: 9 | B34: ="メーカー : "&[1]SD新基準!$AQ10&" 商品コード : "&[1]SD新基準!$AP10&" 商品モデル番号 : "&[1]SD新基準!$AR10 -> メーカー : SanDisk 商品コード : 0619659134747 商品モデル番号 : SDSQUNC-032G-GN6MA | H34: =[1]SD新基準!$L10 -> 10 | I34: EA | J34: 円 | L34: =[1]SD新基準!$AF10 -> 26210 | O34: =L34*H34 -> 262100
A35: 10 | B35: ="メーカー : "&[1]SD新基準!$AQ11&" 商品コード : "&[1]SD新基準!$AP11&" 商品モデル番号 : "&[1]SD新基準!$AR11 -> メーカー : SanDisk 商品コード : 0619659172916 商品モデル番号 : SDSQUNS-064G-GHEMA | H35: =[1]SD新基準!$L11 -> 200 | I35: EA | J35: 円 | L35: =[1]SD新基準!$AF11 -> 4316 | O35: =L35*H35 -> 863200
A36: 11 | B36: ="メーカー : "&[1]SD新基準!$AQ12&" 商品コード : "&[1]SD新基準!$AP12&" 商品モデル番号 : "&[1]SD新基準!$AR12 -> メーカー : SanDisk 商品コード : 0619659185077, 0799833000614 商品モデル番号 : SDSQUNR-064G-GN3MN | H36: =[1]SD新基準!$L12 -> 200 | I36: EA | J36: 円 | L36: =[1]SD新基準!$AF12 -> 4253 | O36: =L36*H36 -> 850600
A37: 12 | B37: ="メーカー : "&[1]SD新基準!$AQ13&" 商品コード : "&[1]SD新基準!$AP13&" 商品モデル番号 : "&[1]SD新基準!$AR13 -> メーカー : SanDisk 商品コード : 0619659161927 商品モデル番号 : SDSQUNS-064G-GN3MN | H37: =[1]SD新基準!$L13 -> 200 | I37: EA | J37: 円 | L37: =[1]SD新基準!$AF13 -> 6803 | O37: =L37*H37 -> 1360600
... A52: 27 | B52: ="メーカー : "&[1]SD新基準!$AQ28&" 商品コード : "&[1]SD新基準!$AP28&" 商品モデル番号 : "&[1]SD新基準!$AR28 -> メーカー : SanDisk 商品コード : 0619659185091, 4607117451167 商品モデル番号 : SDSQUNS-128G-GN6MN | H52: =[1]SD新基準!$L28 -> 200 | I52: EA | J52: 円 | L52: =[1]SD新基準!$AF28 -> 5770 | O52: =L52*H52 -> 1154000
B54: 支払い方法 | C54: 銀行振込
B55: お支払期日 | C55: =管理!O1 -> 46105
B56: お振込先 | C56: =VLOOKUP(管理!C1,管理!A4:U100,12,0) -> みずほ銀行 品川支店 普通7759780
C57: =VLOOKUP(管理!C1,管理!A4:U100,13,0) -> サンディスク（ド
I58: 税率(％) | J58: : 10 | K58: 円 | L58: 小計: | O58: =SUM(O26:O52) -> 31534500
L59: 割引額: | O59: 0
L60: 配送料: | O60: 0
I61: 税率(％) | J61: : 10 | L61: 消費税額: | O61: =O58*10% -> 3153450
K62: 円 | L62: 合計: | O62: =O58+O61 -> 34687950
A65: お買い上げいただきありがとうございました。

Sheet 1_5_納品書ウエスタンデジタル 　最新
G2: Page | H2: 1 of 1
C3: 納品書 | I3: =VLOOKUP(管理!$C$1,管理!A4:S53,2,0) -> サンディスク合同会社
I4: =VLOOKUP(管理!$C$1,管理!A4:T53,4,0) -> 東京都港区港南1丁目6番31号
I5: =IFERROR( IF(OR(VLOOKUP(管理!$C$1,管理!$A$4:$V$100,5,0)=0, VLOOKUP(管理!$C$1,管理!$A$4:$V$100,5,0)=""), "", VLOOKUP(管理!$C$1,管理!A5:T54,5,0) ), "") -> 品川東急ビル3階
I6: =VLOOKUP(管理!$C$1,管理!$A$4:$V$100,6,0) -> 0120-893-009
A7: 注文番号 | C7: 配送番号 | D7: ='1_5_請求書兼領収書 ウエスタンデジタル 最新'!H7 -> 87482297
A8: お名前 | B8: =VLOOKUP(管理!$C2,管理!A4:$AA$103,2,0) -> 柏尾奏利（KASIOshop） | E8: 日付 | F8: =管理!I1 -> 46097
A9: 住所 | B9: =VLOOKUP(管理!$C$2,管理!A4:S50,4,0) -> 東京都板橋区南常盤台1丁目11番6号 | E9: 連絡先 | F9: =VLOOKUP(管理!$C2,管理!A4:$AA$103,6,0) -> 03-3600-3333
B10: =VLOOKUP(管理!$C$2,管理!A5:S51,5,0) -> ウエアーハウス303号室 | E10: 電話番号 | F10: =VLOOKUP(管理!$C2,管理!A4:$AA$103,6,0) -> 03-3600-3333
B11: ="〒"&VLOOKUP(管理!$C$2,管理!A3:S49,3,0) -> 〒174-0072
B12: JAPAN
A14: 製品名 | G14: 数量
A15: ='1_5_請求書兼領収書 ウエスタンデジタル 最新'!B26 -> メーカー : SanDisk 商品コード : 9349220005022 商品モデル番号 : 7545783945 | G15: ='1_5_請求書兼領収書 ウエスタンデジタル 最新'!H26 -> 0
A16: ='1_5_請求書兼領収書 ウエスタンデジタル 最新'!B27 -> メーカー : SanDisk 商品コード : 9349220005039 商品モデル番号 : 9349220005039 | G16: ='1_5_請求書兼領収書 ウエスタンデジタル 最新'!H27 -> 0
A17: ='1_5_請求書兼領収書 ウエスタンデジタル 最新'!B28 -> メーカー : SanDisk 商品コード : 0619659161651 商品モデル番号 : SDSQUNS-032G-GN3MN | G17: ='1_5_請求書兼領収書 ウエスタンデジタル 最新'!H28 -> 200
A18: ='1_5_請求書兼領収書 ウエスタンデジタル 最新'!B29 -> メーカー : SanDisk 商品コード : 0619659184384 商品モデル番号 : SDSQUNS-032G-GN3MN | G18: ='1_5_請求書兼領収書 ウエスタンデジタル 最新'!H29 -> 200
A19: ='1_5_請求書兼領収書 ウエスタンデジタル 最新'!B30 -> メーカー : SanDisk 商品コード : 0619659161644, 6195765406328, 7840000001712 商品モデル番号 : SDSQUNS-032G-GN3MA | G19: ='1_5_請求書兼領収書 ウエスタンデジタル 最新'!H30 -> 200
A20: ='1_5_請求書兼領収書 ウエスタンデジタル 最新'!B31 -> メーカー : SanDisk 商品コード : 0619659134044 商品モデル番号 : SDSQUNB-032G-GN3MN | G20: ='1_5_請求書兼領収書 ウエスタンデジタル 最新'!H31 -> 200
A21: ='1_5_請求書兼領収書 ウエスタンデジタル 最新'!B32 -> メーカー : SanDisk 商品コード : 0619659078645, 5053460346961, 5554442365203, 6196590786456, 7044447834692, 7123290469845, 7987987901489 商品モデル番号 : SDSDQUA-032G-U46A | G21: ='1_5_請求書兼領収書 ウエスタンデジタル 最新'!H32 -> 200
A22: ='1_5_請求書兼領収書 ウエスタンデジタル 最新'!B33 -> メーカー : SanDisk 商品コード : 0068888807494, 0619659246518 商品モデル番号 : 43237-2 | G22: ='1_5_請求書兼領収書 ウエスタンデジタル 最新'!H33 -> 200
A23: ='1_5_請求書兼領収書 ウエスタンデジタル 最新'!B34 -> メーカー : SanDisk 商品コード : 0619659134747 商品モデル番号 : SDSQUNC-032G-GN6MA | G23: ='1_5_請求書兼領収書 ウエスタンデジタル 最新'!H34 -> 10
A24: ='1_5_請求書兼領収書 ウエスタンデジタル 最新'!B35 -> メーカー : SanDisk 商品コード : 0619659172916 商品モデル番号 : SDSQUNS-064G-GHEMA | G24: ='1_5_請求書兼領収書 ウエスタンデジタル 最新'!H35 -> 200
A25: ='1_5_請求書兼領収書 ウエスタンデジタル 最新'!B36 -> メーカー : SanDisk 商品コード : 0619659185077, 0799833000614 商品モデル番号 : SDSQUNR-064G-GN3MN | G25: ='1_5_請求書兼領収書 ウエスタンデジタル 最新'!H36 -> 200
A26: ='1_5_請求書兼領収書 ウエスタンデジタル 最新'!B37 -> メーカー : SanDisk 商品コード : 0619659161927 商品モデル番号 : SDSQUNS-064G-GN3MN | G26: ='1_5_請求書兼領収書 ウエスタンデジタル 最新'!H37 -> 200
... A41: ='1_5_請求書兼領収書 ウエスタンデジタル 最新'!B52 -> メーカー : SanDisk 商品コード : 0619659185091, 4607117451167 商品モデル番号 : SDSQUNS-128G-GN6MN | G41: ='1_5_請求書兼領収書 ウエスタンデジタル 最新'!H52 -> 200
F42: 合計： | G42: =SUM(G15:I41) -> 4810
A44: この度はサンディスクストアにて商品をお買い上げいただき誠にありがとうございます。
A45: 商品を送付させていただきます。今後ともご愛顧賜りますよう何卒よろしくお願い申し上げます。

Sheet 1_6_請求書兼領収書 サンディスク　最新 
E2: =VLOOKUP(管理!$C$1,管理!A4:S53,2,0) -> サンディスク合同会社 | L2: 請求書 兼 領収書
E3: ="〒"&VLOOKUP(管理!$C$1,管理!A4:S53,3,0)&" "&VLOOKUP(管理!$C$1,管理!A4:T53,4,0) -> 〒108-0075 東京都港区港南1丁目6番31号
E4: =IFERROR( IF(OR(VLOOKUP(管理!$C$1,管理!$A$4:$V$100,5,0)=0, VLOOKUP(管理!$C$1,管理!$A$4:$V$100,5,0)=""), "", VLOOKUP(管理!$C$1,管理!A5:T54,5,0) ), "") -> 品川東急ビル3階
H6: 発送番号 | K6: 発送日 | N6: ページ
H7: 87482297 | K7: =G12 -> 46097 | N7: 1の1
E8: ="登録番号："&VLOOKUP(管理!$C$1,管理!A4:T53,11,0) -> 登録番号：T2010401090562 | H8: 発送業者 | L8: B/L
H9: 佐川急便
E11: 請求番号 | G11: 請求日 | K11: 注文番号
E12: =VLOOKUP(管理!$C$2,管理!A4:S50,17,0) -> 0 | G12: =管理!F1 -> 46097
E13: 受注番号 | G13: 配送条件 | K13: 貿易取引条件
E14: S0022047564 | G14: 元払い
E15: ="出荷先:"&VLOOKUP(管理!C2,管理!A4:T100,14,0) -> 出荷先:245141 | J15: ="請求先:"&VLOOKUP(管理!C2,管理!A4:T100,14,0) -> 請求先:245141
E16: =VLOOKUP(管理!$C2,管理!A4:$AA$103,2,0) -> 柏尾奏利（KASIOshop） | J16: =E16 -> 柏尾奏利（KASIOshop）
E17: ="〒"&VLOOKUP(管理!$C$2,管理!A3:S49,3,0) -> 〒174-0072 | J17: =E17 -> 〒174-0072
E18: =VLOOKUP(管理!$C$2,管理!A4:S50,4,0) -> 東京都板橋区南常盤台1丁目11番6号 | J18: =E18 -> 東京都板橋区南常盤台1丁目11番6号
E19: =VLOOKUP(管理!$C$2,管理!A5:S51,5,0) -> ウエアーハウス303号室 | J19: =E19 -> ウエアーハウス303号室
E20: 日本国 | J20: =E20 -> 日本国
A24: No. | B24: 製品型番 | G24: 数量 | I24: 単価 | J24: 商品単価 | M24: 商品金額
B25: 製品詳細
A26: 1 | B26: ="メーカー : "&[1]SD新基準!$AQ2&" 商品コード : "&[1]SD新基準!$AP2&" 商品モデル番号 : "&[1]SD新基準!$AR2 -> メーカー : SanDisk 商品コード : 9349220005022 商品モデル番号 : 7545783945 | H26: =[1]SD新基準!$L2 -> 0 | I26: EA | J26: 円 | L26: =[1]SD新基準!$AF2 -> 714 | O26: =L26*H26 -> 0
A27: 2 | B27: ="メーカー : "&[1]SD新基準!$AQ3&" 商品コード : "&[1]SD新基準!$AP3&" 商品モデル番号 : "&[1]SD新基準!$AR3 -> メーカー : SanDisk 商品コード : 9349220005039 商品モデル番号 : 9349220005039 | H27: =[1]SD新基準!$L3 -> 0 | I27: EA | J27: 円 | L27: =[1]SD新基準!$AF3 -> 976 | O27: =L27*H27 -> 0
A28: 3 | B28: ="メーカー : "&[1]SD新基準!$AQ4&" 商品コード : "&[1]SD新基準!$AP4&" 商品モデル番号 : "&[1]SD新基準!$AR4 -> メーカー : SanDisk 商品コード : 0619659161651 商品モデル番号 : SDSQUNS-032G-GN3MN | H28: =[1]SD新基準!$L4 -> 200 | I28: EA | J28: 円 | L28: =[1]SD新基準!$AF4 -> 6308 | O28: =L28*H28 -> 1261600
A29: 4 | B29: ="メーカー : "&[1]SD新基準!$AQ5&" 商品コード : "&[1]SD新基準!$AP5&" 商品モデル番号 : "&[1]SD新基準!$AR5 -> メーカー : SanDisk 商品コード : 0619659184384 商品モデル番号 : SDSQUNS-032G-GN3MN | H29: =[1]SD新基準!$L5 -> 200 | I29: EA | J29: 円 | L29: =[1]SD新基準!$AF5 -> 3714 | O29: =L29*H29 -> 742800
A30: 5 | B30: ="メーカー : "&[1]SD新基準!$AQ6&" 商品コード : "&[1]SD新基準!$AP6&" 商品モデル番号 : "&[1]SD新基準!$AR6 -> メーカー : SanDisk 商品コード : 0619659161644, 6195765406328, 7840000001712 商品モデル番号 : SDSQUNS-032G-GN3MA | H30: =[1]SD新基準!$L6 -> 200 | I30: EA | J30: 円 | L30: =[1]SD新基準!$AF6 -> 6686 | O30: =L30*H30 -> 1337200
A31: 6 | B31: ="メーカー : "&[1]SD新基準!$AQ7&" 商品コード : "&[1]SD新基準!$AP7&" 商品モデル番号 : "&[1]SD新基準!$AR7 -> メーカー : SanDisk 商品コード : 0619659134044 商品モデル番号 : SDSQUNB-032G-GN3MN | H31: =[1]SD新基準!$L7 -> 200 | I31: EA | J31: 円 | L31: =[1]SD新基準!$AF7 -> 6127 | O31: =L31*H31 -> 1225400
A32: 7 | B32: ="メーカー : "&[1]SD新基準!$AQ8&" 商品コード : "&[1]SD新基準!$AP8&" 商品モデル番号 : "&[1]SD新基準!$AR8 -> メーカー : SanDisk 商品コード : 0619659078645, 5053460346961, 5554442365203, 6196590786456, 7044447834692, 7123290469845, 7987987901489 商品モデル番号 : SDSDQUA-032G-U46A | H32: =[1]SD新基準!$L8 -> 200 | I32: EA | J32: 円 | L32: =[1]SD新基準!$AF8 -> 6870 | O32: =L32*H32 -> 1374000
A33: 8 | B33: ="メーカー : "&[1]SD新基準!$AQ9&" 商品コード : "&[1]SD新基準!$AP9&" 商品モデル番号 : "&[1]SD新基準!$AR9 -> メーカー : SanDisk 商品コード : 0068888807494, 0619659246518 商品モデル番号 : 43237-2 | H33: =[1]SD新基準!$L9 -> 200 | I33: EA | J33: 円 | L33: =[1]SD新基準!$AF9 -> 8893 | O33: =L33*H33 -> 1778600
A34: 9 | B34: ="メーカー : "&[1]SD新基準!$AQ10&" 商品コード : "&[1]SD新基準!$AP10&" 商品モデル番号 : "&[1]SD新基準!$AR10 -> メーカー : SanDisk 商品コード : 0619659134747 商品モデル番号 : SDSQUNC-032G-GN6MA | H34: =[1]SD新基準!$L10 -> 10 | I34: EA | J34: 円 | L34: =[1]SD新基準!$AF10 -> 26210 | O34: =L34*H34 -> 262100
A35: 10 | B35: ="メーカー : "&[1]SD新基準!$AQ11&" 商品コード : "&[1]SD新基準!$AP11&" 商品モデル番号 : "&[1]SD新基準!$AR11 -> メーカー : SanDisk 商品コード : 0619659172916 商品モデル番号 : SDSQUNS-064G-GHEMA | H35: =[1]SD新基準!$L11 -> 200 | I35: EA | J35: 円 | L35: =[1]SD新基準!$AF11 -> 4316 | O35: =L35*H35 -> 863200
A36: 11 | B36: ="メーカー : "&[1]SD新基準!$AQ12&" 商品コード : "&[1]SD新基準!$AP12&" 商品モデル番号 : "&[1]SD新基準!$AR12 -> メーカー : SanDisk 商品コード : 0619659185077, 0799833000614 商品モデル番号 : SDSQUNR-064G-GN3MN | H36: =[1]SD新基準!$L12 -> 200 | I36: EA | J36: 円 | L36: =[1]SD新基準!$AF12 -> 4253 | O36: =L36*H36 -> 850600
A37: 12 | B37: ="メーカー : "&[1]SD新基準!$AQ13&" 商品コード : "&[1]SD新基準!$AP13&" 商品モデル番号 : "&[1]SD新基準!$AR13 -> メーカー : SanDisk 商品コード : 0619659161927 商品モデル番号 : SDSQUNS-064G-GN3MN | H37: =[1]SD新基準!$L13 -> 200 | I37: EA | J37: 円 | L37: =[1]SD新基準!$AF13 -> 6803 | O37: =L37*H37 -> 1360600
... A52: 27 | B52: ="メーカー : "&[1]SD新基準!$AQ28&" 商品コード : "&[1]SD新基準!$AP28&" 商品モデル番号 : "&[1]SD新基準!$AR28 -> メーカー : SanDisk 商品コード : 0619659185091, 4607117451167 商品モデル番号 : SDSQUNS-128G-GN6MN | H52: =[1]SD新基準!$L28 -> 200 | I52: EA | J52: 円 | L52: =[1]SD新基準!$AF28 -> 5770 | O52: =L52*H52 -> 1154000
B54: 支払い方法 | C54: 銀行振込
B55: お支払期日 | C55: =管理!O1 -> 46105
B56: お振込先 | C56: =VLOOKUP(管理!C1,管理!A4:U100,12,0) -> みずほ銀行 品川支店 普通7759780
C57: =VLOOKUP(管理!C1,管理!A4:U100,13,0) -> サンディスク（ド
I58: 税率(％) | J58: : 10 | K58: 円 | L58: 小計: | O58: =SUM(O26:O54) -> 31534500
L59: 割引額: | O59: 0
L60: 配送料: | O60: 0
I61: 税率(％) | J61: : 10 | L61: 消費税額: | O61: =O58*10% -> 3153450
K62: 円 | L62: 合計: | O62: =O58+O61 -> 34687950
A65: お買い上げいただきありがとうございました。

Sheet 1_6_納品書サンディスク 　最新
G2: Page | H2: 1 of 1
C3: 納品書 | I3: =VLOOKUP(管理!$C$1,管理!A4:S53,2,0) -> サンディスク合同会社
I4: =VLOOKUP(管理!$C$1,管理!A4:T53,4,0) -> 東京都港区港南1丁目6番31号
I5: =IFERROR( IF(OR(VLOOKUP(管理!$C$1,管理!$A$4:$V$100,5,0)=0, VLOOKUP(管理!$C$1,管理!$A$4:$V$100,5,0)=""), "", VLOOKUP(管理!$C$1,管理!A5:T54,5,0) ), "") -> 品川東急ビル3階
I6: =VLOOKUP(管理!$C$1,管理!$A$4:$V$100,6,0) -> 0120-893-009
A7: 注文番号 | C7: 配送番号 | D7: ='1_6_請求書兼領収書 サンディスク 最新 '!H7 -> 87482297
A8: お名前 | B8: =VLOOKUP(管理!$C2,管理!A4:$AA$103,2,0) -> 柏尾奏利（KASIOshop） | E8: 日付 | F8: =管理!I1 -> 46097
A9: 住所 | B9: =VLOOKUP(管理!$C$2,管理!A4:S50,4,0) -> 東京都板橋区南常盤台1丁目11番6号 | E9: 連絡先 | F9: =VLOOKUP(管理!$C2,管理!A4:$AA$103,6,0) -> 03-3600-3333
B10: =VLOOKUP(管理!$C$2,管理!A5:S51,5,0) -> ウエアーハウス303号室 | E10: 電話番号 | F10: =VLOOKUP(管理!$C2,管理!A4:$AA$103,6,0) -> 03-3600-3333
B11: ="〒"&VLOOKUP(管理!$C$2,管理!A3:S49,3,0) -> 〒174-0072
B12: JAPAN
A14: 製品名 | G14: 数量
A15: ='1_6_請求書兼領収書 サンディスク 最新 '!B26 -> メーカー : SanDisk 商品コード : 9349220005022 商品モデル番号 : 7545783945 | G15: ='1_6_請求書兼領収書 サンディスク 最新 '!H26 -> 0
A16: ='1_6_請求書兼領収書 サンディスク 最新 '!B27 -> メーカー : SanDisk 商品コード : 9349220005039 商品モデル番号 : 9349220005039 | G16: ='1_6_請求書兼領収書 サンディスク 最新 '!H27 -> 0
A17: ='1_6_請求書兼領収書 サンディスク 最新 '!B28 -> メーカー : SanDisk 商品コード : 0619659161651 商品モデル番号 : SDSQUNS-032G-GN3MN | G17: ='1_6_請求書兼領収書 サンディスク 最新 '!H28 -> 200
A18: ='1_6_請求書兼領収書 サンディスク 最新 '!B29 -> メーカー : SanDisk 商品コード : 0619659184384 商品モデル番号 : SDSQUNS-032G-GN3MN | G18: ='1_6_請求書兼領収書 サンディスク 最新 '!H29 -> 200
A19: ='1_6_請求書兼領収書 サンディスク 最新 '!B30 -> メーカー : SanDisk 商品コード : 0619659161644, 6195765406328, 7840000001712 商品モデル番号 : SDSQUNS-032G-GN3MA | G19: ='1_6_請求書兼領収書 サンディスク 最新 '!H30 -> 200
A20: ='1_6_請求書兼領収書 サンディスク 最新 '!B31 -> メーカー : SanDisk 商品コード : 0619659134044 商品モデル番号 : SDSQUNB-032G-GN3MN | G20: ='1_6_請求書兼領収書 サンディスク 最新 '!H31 -> 200
A21: ='1_6_請求書兼領収書 サンディスク 最新 '!B32 -> メーカー : SanDisk 商品コード : 0619659078645, 5053460346961, 5554442365203, 6196590786456, 7044447834692, 7123290469845, 7987987901489 商品モデル番号 : SDSDQUA-032G-U46A | G21: ='1_6_請求書兼領収書 サンディスク 最新 '!H32 -> 200
A22: ='1_6_請求書兼領収書 サンディスク 最新 '!B33 -> メーカー : SanDisk 商品コード : 0068888807494, 0619659246518 商品モデル番号 : 43237-2 | G22: ='1_6_請求書兼領収書 サンディスク 最新 '!H33 -> 200
A23: ='1_6_請求書兼領収書 サンディスク 最新 '!B34 -> メーカー : SanDisk 商品コード : 0619659134747 商品モデル番号 : SDSQUNC-032G-GN6MA | G23: ='1_6_請求書兼領収書 サンディスク 最新 '!H34 -> 10
A24: ='1_6_請求書兼領収書 サンディスク 最新 '!B35 -> メーカー : SanDisk 商品コード : 0619659172916 商品モデル番号 : SDSQUNS-064G-GHEMA | G24: ='1_6_請求書兼領収書 サンディスク 最新 '!H35 -> 200
A25: ='1_6_請求書兼領収書 サンディスク 最新 '!B36 -> メーカー : SanDisk 商品コード : 0619659185077, 0799833000614 商品モデル番号 : SDSQUNR-064G-GN3MN | G25: ='1_6_請求書兼領収書 サンディスク 最新 '!H36 -> 200
A26: ='1_6_請求書兼領収書 サンディスク 最新 '!B37 -> メーカー : SanDisk 商品コード : 0619659161927 商品モデル番号 : SDSQUNS-064G-GN3MN | G26: ='1_6_請求書兼領収書 サンディスク 最新 '!H37 -> 200
... A41: ='1_6_請求書兼領収書 サンディスク 最新 '!B52 -> メーカー : SanDisk 商品コード : 0619659185091, 4607117451167 商品モデル番号 : SDSQUNS-128G-GN6MN | G41: ='1_6_請求書兼領収書 サンディスク 最新 '!H52 -> 200
F42: 合計： | G42: =SUM(G15:I41) -> 4810
A44: この度はサンディスクストアにて商品をお買い上げいただき誠にありがとうございます。
A45: 商品を送付させていただきます。今後ともご愛顧賜りますよう何卒よろしくお願い申し上げます。

Sheet 1_7_請求書兼領収書 図形バージョン 
F2: =VLOOKUP(管理!$C$1,管理!A4:S53,2,0) -> サンディスク合同会社 | M2: 請求書 兼 領収書
F3: ="〒"&VLOOKUP(管理!$C$1,管理!A4:S53,3,0)&" "&VLOOKUP(管理!$C$1,管理!A4:T53,4,0) -> 〒108-0075 東京都港区港南1丁目6番31号
F4: =IFERROR( IF(OR(VLOOKUP(管理!$C$1,管理!$A$4:$V$100,5,0)=0, VLOOKUP(管理!$C$1,管理!$A$4:$V$100,5,0)=""), "", VLOOKUP(管理!$C$1,管理!A5:T54,5,0) ), "") -> 品川東急ビル3階
I6: 発送番号 | L6: 発送日 | O6: ページ
I7: 87482297 | L7: =H12 -> 46097 | O7: 1の1
F8: ="登録番号："&VLOOKUP(管理!$C$1,管理!A4:T53,11,0) -> 登録番号：T2010401090562 | I8: 発送業者 | M8: B/L
I9: 佐川急便
F11: 請求番号 | H11: 請求日 | L11: 注文番号
F12: =VLOOKUP(管理!$C$2,管理!A4:S50,17,0) -> 0 | H12: =管理!F1 -> 46097
F13: 受注番号 | H13: 配送条件 | L13: 貿易取引条件
F14: S0022047564
F15: ="出荷先:"&VLOOKUP(管理!C2,管理!A4:T100,14,0) -> 出荷先:245141 | K15: ="請求先:"&VLOOKUP(管理!C2,管理!A4:T100,14,0) -> 請求先:245141
F16: =VLOOKUP(管理!$C2,管理!A4:$AA$103,2,0) -> 柏尾奏利（KASIOshop） | K16: =VLOOKUP(管理!$C2,管理!A4:$AA$103,2,0) -> 柏尾奏利（KASIOshop）
F17: ="〒"&VLOOKUP(管理!$C$2,管理!A4:$AA$103,3,0) -> 〒174-0072 | K17: ="〒"&VLOOKUP(管理!$C$2,管理!A4:$AA$103,3,0) -> 〒174-0072
F18: =VLOOKUP(管理!$C$2,管理!A4:$AA$103,4,0) -> 東京都板橋区南常盤台1丁目11番6号 | K18: =VLOOKUP(管理!$C$2,管理!A4:$AA$103,4,0) -> 東京都板橋区南常盤台1丁目11番6号
F19: =VLOOKUP(管理!$C$2,管理!A4:$AA$103,5,0) -> ウエアーハウス303号室 | K19: =VLOOKUP(管理!$C$2,管理!A4:$AA$103,5,0) -> ウエアーハウス303号室
F20: 日本国 | K20: 日本国
B24: №
B26: 1 | C26: 商品モデル番号 : | D26: =[1]SD新基準!$AR$2 -> 7545783945 | H26: =[1]SD新基準!$L$2 -> 0 | J26: EA | K26: 円 | M26: =[1]SD新基準!$AF$2 -> 714 | O26: =M26*H26 -> 0
C27: 商品コード : | D27: =[1]SD新基準!$AP$2 -> 9349220005022
B29: 2 | C29: 商品モデル番号 : | D29: =[1]SD新基準!$AR$3 -> 9349220005039 | H29: =[1]SD新基準!$L$3 -> 0 | J29: EA | K29: 円 | M29: =[1]SD新基準!$AF$3 -> 976 | O29: =M29*H29 -> 0
C30: 商品コード : | D30: =[1]SD新基準!$AP$3 -> 9349220005039
B32: 3 | C32: 商品モデル番号 : | D32: =[1]SD新基準!$AR$4 -> SDSQUNS-032G-GN3MN | H32: =[1]SD新基準!$L$4 -> 200 | J32: EA | K32: 円 | M32: =[1]SD新基準!$AF$4 -> 6308 | O32: =M32*H32 -> 1261600
C33: 商品コード : | D33: =[1]SD新基準!$AP$4 -> 0619659161651
B35: 4 | C35: 商品モデル番号 : | D35: =[1]SD新基準!$AR$5 -> SDSQUNS-032G-GN3MN | H35: =[1]SD新基準!$L$5 -> 200 | J35: EA | K35: 円 | M35: =[1]SD新基準!$AF$5 -> 3714 | O35: =M35*H35 -> 742800
C36: 商品コード : | D36: =[1]SD新基準!$AP$5 -> 0619659184384
B38: 5 | C38: 商品モデル番号 : | D38: =[1]SD新基準!$AR$6 -> SDSQUNS-032G-GN3MA | H38: =[1]SD新基準!$L$6 -> 200 | J38: EA | K38: 円 | M38: =[1]SD新基準!$AF$6 -> 6686 | O38: =M38*H38 -> 1337200
C39: 商品コード : | D39: =[1]SD新基準!$AP$6 -> 0619659161644, 6195765406328, 7840000001712
B41: 6 | C41: 商品モデル番号 : | D41: =[1]SD新基準!$AR$7 -> SDSQUNB-032G-GN3MN | H41: =[1]SD新基準!$L$7 -> 200 | J41: EA | K41: 円 | M41: =[1]SD新基準!$AF$7 -> 6127 | O41: =M41*H41 -> 1225400
C42: 商品コード : | D42: =[1]SD新基準!$AP$7 -> 0619659134044
B44: 7 | C44: 商品モデル番号 : | D44: =[1]SD新基準!$AR$8 -> SDSDQUA-032G-U46A | H44: =[1]SD新基準!$L$8 -> 200 | J44: EA | K44: 円 | M44: =[1]SD新基準!$AF$8 -> 6870 | O44: =M44*H44 -> 1374000
C45: 商品コード : | D45: =[1]SD新基準!$AP$8 -> 0619659078645, 5053460346961, 5554442365203, 6196590786456, 7044447834692, 7123290469845, 7987987901489
B47: 8 | C47: 商品モデル番号 : | D47: =[1]SD新基準!$AR$9 -> 43237-2 | H47: =[1]SD新基準!$L$9 -> 200 | J47: EA | K47: 円 | M47: =[1]SD新基準!$AF$9 -> 8893 | O47: =M47*H47 -> 1778600
C48: 商品コード : | D48: =[1]SD新基準!$AP$9 -> 0068888807494, 0619659246518
B50: 9 | C50: 商品モデル番号 : | D50: =[1]SD新基準!$AR$10 -> SDSQUNC-032G-GN6MA | H50: =[1]SD新基準!$L$10 -> 10 | J50: EA | K50: 円 | M50: =[1]SD新基準!$AF$10 -> 26210 | O50: =M50*H50 -> 262100
C51: 商品コード : | D51: =[1]SD新基準!$AP$10 -> 0619659134747
B53: 10 | C53: 商品モデル番号 : | D53: =[1]SD新基準!$AR$11 -> SDSQUNS-064G-GHEMA | H53: =[1]SD新基準!$L$11 -> 200 | J53: EA | K53: 円 | M53: =[1]SD新基準!$AF$11 -> 4316 | O53: =M53*H53 -> 863200
C54: 商品コード : | D54: =[1]SD新基準!$AP$11 -> 0619659172916
B56: 11 | C56: 商品モデル番号 : | D56: =[1]SD新基準!$AR$12 -> SDSQUNR-064G-GN3MN | H56: =[1]SD新基準!$L$12 -> 200 | J56: EA | K56: 円 | M56: =[1]SD新基準!$AF$12 -> 4253 | O56: =M56*H56 -> 850600
C57: 商品コード : | D57: =[1]SD新基準!$AP$12 -> 0619659185077, 0799833000614
B59: 12 | C59: 商品モデル番号 : | D59: =[1]SD新基準!$AR$13 -> SDSQUNS-064G-GN3MN | H59: =[1]SD新基準!$L$13 -> 200 | J59: EA | K59: 円 | M59: =[1]SD新基準!$AF$13 -> 6803 | O59: =M59*H59 -> 1360600
C60: 商品コード : | D60: =[1]SD新基準!$AP$13 -> 0619659161927
B62: 13 | C62: 商品モデル番号 : | D62: =[1]SD新基準!$AR$14 -> SDSQUNC-064G-GN6MA | H62: =[1]SD新基準!$L$14 -> 200 | J62: EA | K62: 円 | M62: =[1]SD新基準!$AF$14 -> 6567 | O62: =M62*H62 -> 1313400
C63: 商品コード : | D63: =[1]SD新基準!$AP$14 -> 0619659134846, 4056572752683
B65: 14 | C65: 商品モデル番号 : | D65: =[1]SD新基準!$AR$15 -> 0 | H65: =[1]SD新基準!$L$15 -> 200 | J65: EA | K65: 円 | M65: =[1]SD新基準!$AF$15 -> 4317 | O65: =M65*H65 -> 863400
C66: 商品コード : | D66: =[1]SD新基準!$AP$15 -> 0
B68: 15 | C68: 商品モデル番号 : | D68: =[1]SD新基準!$AR$16 -> 0 | H68: =[1]SD新基準!$L$16 -> 200 | J68: EA | K68: 円 | M68: =[1]SD新基準!$AF$16 -> 4317 | O68: =M68*H68 -> 863400
C69: 商品コード : | D69: =[1]SD新基準!$AP$16 -> 0
B71: 16 | C71: 商品モデル番号 : | D71: =[1]SD新基準!$AR$17 -> SDSQUNB-064G-GN3MN | H71: =[1]SD新基準!$L$17 -> 200 | J71: EA | K71: 円 | M71: =[1]SD新基準!$AF$17 -> 7131 | O71: =M71*H71 -> 1426200
C72: 商品コード : | D72: =[1]SD新基準!$AP$17 -> 0619659134068, 4031039880642, 4893433124148, 5054629833599, 8944129953071
C74: 支払い方法 | D74: 銀行振込
C75: お支払期日 | D75: =管理!O1 -> 46105
C76: お振込口座 | D76: =VLOOKUP(管理!C1,管理!A4:U100,12,0) -> みずほ銀行 品川支店 普通7759780
D77: =VLOOKUP(管理!C1,管理!A4:U100,13,0) -> サンディスク（ド
J78: 税率（％） | K78: : 10 | L78: 円 | M78: 小計: | O78: =SUM(O26:O72) -> 15522500
M79: 割引額: | O79: 0
M80: 配送料: | O80: 0
J81: 税率（％） | K81: : 10 | M81: 消費税額: | O81: =O78*10% -> 1552250
L82: 円 | M82: 合計: | O82: =O78+O81 -> 17074750

Sheet 1_7_納品書　図形バージョン 
G2: Page | H2: 1 of 1
C3: 納品書 | I3: =VLOOKUP(管理!$C$1,管理!A4:S53,2,0) -> サンディスク合同会社
I4: =VLOOKUP(管理!$C$1,管理!A4:T53,4,0) -> 東京都港区港南1丁目6番31号
I5: =IFERROR( IF(OR(VLOOKUP(管理!$C$1,管理!$A$4:$V$100,5,0)=0, VLOOKUP(管理!$C$1,管理!$A$4:$V$100,5,0)=""), "", VLOOKUP(管理!$C$1,管理!A5:T54,5,0) ), "") -> 品川東急ビル3階
I6: =VLOOKUP(管理!$C$1,管理!$A$4:$V$100,6,0) -> 0120-893-009
A7: 注文番号 | C7: 配送番号 | D7: =#REF! -> #REF!
A8: お名前 | B8: =VLOOKUP(管理!$C2,管理!A4:$AA$103,2,0) -> 柏尾奏利（KASIOshop） | E8: 日付 | F8: =管理!I1 -> 46097
A9: 住所 | B9: =VLOOKUP(管理!$C$2,管理!A4:S50,4,0) -> 東京都板橋区南常盤台1丁目11番6号 | E9: 連絡先 | F9: =VLOOKUP(管理!$C2,管理!A4:$AA$103,6,0) -> 03-3600-3333
B10: =VLOOKUP(管理!$C$2,管理!A5:S51,5,0) -> ウエアーハウス303号室
B11: ="〒"&VLOOKUP(管理!$C$2,管理!A3:S49,3,0) -> 〒174-0072
B12: JAPAN
A14: 製品名 | G14: 数量
A15: ="商品モデル番号："&[1]SD新基準!$AR2&" 商品コード："&[1]SD新基準!$AP2 -> 商品モデル番号：7545783945 商品コード：9349220005022 | G15: =[1]SD新基準!$L2 -> 0
A16: ="商品モデル番号："&[1]SD新基準!$AR3&" 商品コード："&[1]SD新基準!$AP3 -> 商品モデル番号：9349220005039 商品コード：9349220005039 | G16: =[1]SD新基準!$L3 -> 0
A17: ="商品モデル番号："&[1]SD新基準!$AR4&" 商品コード："&[1]SD新基準!$AP4 -> 商品モデル番号：SDSQUNS-032G-GN3MN 商品コード：0619659161651 | G17: =[1]SD新基準!$L4 -> 200
A18: ="商品モデル番号："&[1]SD新基準!$AR5&" 商品コード："&[1]SD新基準!$AP5 -> 商品モデル番号：SDSQUNS-032G-GN3MN 商品コード：0619659184384 | G18: =[1]SD新基準!$L5 -> 200
A19: ="商品モデル番号："&[1]SD新基準!$AR6&" 商品コード："&[1]SD新基準!$AP6 -> 商品モデル番号：SDSQUNS-032G-GN3MA 商品コード：0619659161644, 6195765406328, 7840000001712 | G19: =[1]SD新基準!$L6 -> 200
A20: ="商品モデル番号："&[1]SD新基準!$AR7&" 商品コード："&[1]SD新基準!$AP7 -> 商品モデル番号：SDSQUNB-032G-GN3MN 商品コード：0619659134044 | G20: =[1]SD新基準!$L7 -> 200
A21: ="商品モデル番号："&[1]SD新基準!$AR8&" 商品コード："&[1]SD新基準!$AP8 -> 商品モデル番号：SDSDQUA-032G-U46A 商品コード：0619659078645, 5053460346961, 5554442365203, 6196590786456, 7044447834692, 7123290469845, 7987987901489 | G21: =[1]SD新基準!$L8 -> 200
A22: ="商品モデル番号："&[1]SD新基準!$AR9&" 商品コード："&[1]SD新基準!$AP9 -> 商品モデル番号：43237-2 商品コード：0068888807494, 0619659246518 | G22: =[1]SD新基準!$L9 -> 200
A23: ="商品モデル番号："&[1]SD新基準!$AR10&" 商品コード："&[1]SD新基準!$AP10 -> 商品モデル番号：SDSQUNC-032G-GN6MA 商品コード：0619659134747 | G23: =[1]SD新基準!$L10 -> 10
A24: ="商品モデル番号："&[1]SD新基準!$AR11&" 商品コード："&[1]SD新基準!$AP11 -> 商品モデル番号：SDSQUNS-064G-GHEMA 商品コード：0619659172916 | G24: =[1]SD新基準!$L11 -> 200
A25: ="商品モデル番号："&[1]SD新基準!$AR12&" 商品コード："&[1]SD新基準!$AP12 -> 商品モデル番号：SDSQUNR-064G-GN3MN 商品コード：0619659185077, 0799833000614 | G25: =[1]SD新基準!$L12 -> 200
A26: ="商品モデル番号："&[1]SD新基準!$AR13&" 商品コード："&[1]SD新基準!$AP13 -> 商品モデル番号：SDSQUNS-064G-GN3MN 商品コード：0619659161927 | G26: =[1]SD新基準!$L13 -> 200
... A30: ="商品モデル番号："&[1]SD新基準!$AR17&" 商品コード："&[1]SD新基準!$AP17 -> 商品モデル番号：SDSQUNB-064G-GN3MN 商品コード：0619659134068, 4031039880642, 4893433124148, 5054629833599, 8944129953071 | G30: =[1]SD新基準!$L17 -> 200
F31: 合計： | G31: =SUM(G15:I30) -> 2610
A33: この度はサンディスクストアにて商品をお買い上げいただき誠にありがとうございます。
A34: 商品を送付させていただきます。今後ともご愛顧賜りますよう何卒よろしくお願い申し上げます。

Sheet 1_8_請求書兼領収書 図形バージョン  (2)
F2: =VLOOKUP(管理!$C$1,管理!A4:S53,2,0) -> サンディスク合同会社 | M2: 請求書 兼 領収書
F3: ="〒"&VLOOKUP(管理!$C$1,管理!A4:S53,3,0)&" "&VLOOKUP(管理!$C$1,管理!A4:T53,4,0) -> 〒108-0075 東京都港区港南1丁目6番31号
F4: =IFERROR( IF(OR(VLOOKUP(管理!$C$1,管理!$A$4:$V$100,5,0)=0, VLOOKUP(管理!$C$1,管理!$A$4:$V$100,5,0)=""), "", VLOOKUP(管理!$C$1,管理!A5:T54,5,0) ), "") -> 品川東急ビル3階
I6: 発送番号 | L6: 発送日 | O6: ページ
I7: 87482297 | L7: =H12 -> 46097 | O7: 1の1
F8: ="登録番号："&VLOOKUP(管理!$C$1,管理!A4:T53,11,0) -> 登録番号：T2010401090562 | I8: 発送業者 | M8: B/L
I9: 佐川急便
F11: 請求番号 | H11: 請求日 | L11: 注文番号
F12: =VLOOKUP(管理!$C$2,管理!A4:S50,17,0) -> 0 | H12: =管理!F1 -> 46097
F13: 受注番号 | H13: 配送条件 | L13: 貿易取引条件
F14: S0022047564
F15: ="出荷先:"&VLOOKUP(管理!C2,管理!A4:T100,14,0) -> 出荷先:245141 | K15: ="請求先:"&VLOOKUP(管理!C2,管理!A4:T100,14,0) -> 請求先:245141
F16: =VLOOKUP(管理!$C2,管理!A4:$AA$103,2,0) -> 柏尾奏利（KASIOshop） | K16: =VLOOKUP(管理!$C2,管理!A4:$AA$103,2,0) -> 柏尾奏利（KASIOshop）
F17: ="〒"&VLOOKUP(管理!$C$2,管理!A4:$AA$103,3,0) -> 〒174-0072 | K17: ="〒"&VLOOKUP(管理!$C$2,管理!A4:$AA$103,3,0) -> 〒174-0072
F18: =VLOOKUP(管理!$C$2,管理!A4:$AA$103,4,0) -> 東京都板橋区南常盤台1丁目11番6号 | K18: =VLOOKUP(管理!$C$2,管理!A4:$AA$103,4,0) -> 東京都板橋区南常盤台1丁目11番6号
F19: =VLOOKUP(管理!$C$2,管理!A4:$AA$103,5,0) -> ウエアーハウス303号室 | K19: =VLOOKUP(管理!$C$2,管理!A4:$AA$103,5,0) -> ウエアーハウス303号室
F20: 日本国 | K20: 日本国
B24: №
B26: 1 | C26: 商品モデル番号 : | D26: =[1]SD新基準!$AR$2 -> 7545783945 | H26: =[1]SD新基準!$L$2 -> 0 | J26: EA | K26: 円 | M26: =[1]SD新基準!$AF$2 -> 714 | O26: =M26*H26 -> 0
C27: 商品コード : | D27: =[1]SD新基準!$AP$2 -> 9349220005022
B29: 2 | C29: 商品モデル番号 : | D29: =[1]SD新基準!$AR$3 -> 9349220005039 | H29: =[1]SD新基準!$L$3 -> 0 | J29: EA | K29: 円 | M29: =[1]SD新基準!$AF$3 -> 976 | O29: =M29*H29 -> 0
C30: 商品コード : | D30: =[1]SD新基準!$AP$3 -> 9349220005039
B32: 3 | C32: 商品モデル番号 : | D32: =[1]SD新基準!$AR$4 -> SDSQUNS-032G-GN3MN | H32: =[1]SD新基準!$L$4 -> 200 | J32: EA | K32: 円 | M32: =[1]SD新基準!$AF$4 -> 6308 | O32: =M32*H32 -> 1261600
C33: 商品コード : | D33: =[1]SD新基準!$AP$4 -> 0619659161651
B35: 4 | C35: 商品モデル番号 : | D35: =[1]SD新基準!$AR$5 -> SDSQUNS-032G-GN3MN | H35: =[1]SD新基準!$L$5 -> 200 | J35: EA | K35: 円 | M35: =[1]SD新基準!$AF$5 -> 3714 | O35: =M35*H35 -> 742800
C36: 商品コード : | D36: =[1]SD新基準!$AP$5 -> 0619659184384
B38: 5 | C38: 商品モデル番号 : | D38: =[1]SD新基準!$AR$6 -> SDSQUNS-032G-GN3MA | H38: =[1]SD新基準!$L$6 -> 200 | J38: EA | K38: 円 | M38: =[1]SD新基準!$AF$6 -> 6686 | O38: =M38*H38 -> 1337200
C39: 商品コード : | D39: =[1]SD新基準!$AP$6 -> 0619659161644, 6195765406328, 7840000001712
B41: 6 | C41: 商品モデル番号 : | D41: =[1]SD新基準!$AR$7 -> SDSQUNB-032G-GN3MN | H41: =[1]SD新基準!$L$7 -> 200 | J41: EA | K41: 円 | M41: =[1]SD新基準!$AF$7 -> 6127 | O41: =M41*H41 -> 1225400
C42: 商品コード : | D42: =[1]SD新基準!$AP$7 -> 0619659134044
B44: 7 | C44: 商品モデル番号 : | D44: =[1]SD新基準!$AR$8 -> SDSDQUA-032G-U46A | H44: =[1]SD新基準!$L$8 -> 200 | J44: EA | K44: 円 | M44: =[1]SD新基準!$AF$8 -> 6870 | O44: =M44*H44 -> 1374000
C45: 商品コード : | D45: =[1]SD新基準!$AP$8 -> 0619659078645, 5053460346961, 5554442365203, 6196590786456, 7044447834692, 7123290469845, 7987987901489
B47: 8 | C47: 商品モデル番号 : | D47: =[1]SD新基準!$AR$9 -> 43237-2 | H47: =[1]SD新基準!$L$9 -> 200 | J47: EA | K47: 円 | M47: =[1]SD新基準!$AF$9 -> 8893 | O47: =M47*H47 -> 1778600
C48: 商品コード : | D48: =[1]SD新基準!$AP$9 -> 0068888807494, 0619659246518
B50: 9 | C50: 商品モデル番号 : | D50: =[1]SD新基準!$AR$10 -> SDSQUNC-032G-GN6MA | H50: =[1]SD新基準!$L$10 -> 10 | J50: EA | K50: 円 | M50: =[1]SD新基準!$AF$10 -> 26210 | O50: =M50*H50 -> 262100
C51: 商品コード : | D51: =[1]SD新基準!$AP$10 -> 0619659134747
B53: 10 | C53: 商品モデル番号 : | D53: =[1]SD新基準!$AR$11 -> SDSQUNS-064G-GHEMA | H53: =[1]SD新基準!$L$11 -> 200 | J53: EA | K53: 円 | M53: =[1]SD新基準!$AF$11 -> 4316 | O53: =M53*H53 -> 863200
C54: 商品コード : | D54: =[1]SD新基準!$AP$11 -> 0619659172916
B56: 11 | C56: 商品モデル番号 : | D56: =[1]SD新基準!$AR$12 -> SDSQUNR-064G-GN3MN | H56: =[1]SD新基準!$L$12 -> 200 | J56: EA | K56: 円 | M56: =[1]SD新基準!$AF$12 -> 4253 | O56: =M56*H56 -> 850600
C57: 商品コード : | D57: =[1]SD新基準!$AP$12 -> 0619659185077, 0799833000614
B59: 12 | C59: 商品モデル番号 : | D59: =[1]SD新基準!$AR$13 -> SDSQUNS-064G-GN3MN | H59: =[1]SD新基準!$L$13 -> 200 | J59: EA | K59: 円 | M59: =[1]SD新基準!$AF$13 -> 6803 | O59: =M59*H59 -> 1360600
C60: 商品コード : | D60: =[1]SD新基準!$AP$13 -> 0619659161927
B62: 13 | C62: 商品モデル番号 : | D62: =[1]SD新基準!$AR$14 -> SDSQUNC-064G-GN6MA | H62: =[1]SD新基準!$L$14 -> 200 | J62: EA | K62: 円 | M62: =[1]SD新基準!$AF$14 -> 6567 | O62: =M62*H62 -> 1313400
C63: 商品コード : | D63: =[1]SD新基準!$AP$14 -> 0619659134846, 4056572752683
B65: 14 | C65: 商品モデル番号 : | D65: =[1]SD新基準!$AR$15 -> 0 | H65: =[1]SD新基準!$L$15 -> 200 | J65: EA | K65: 円 | M65: =[1]SD新基準!$AF$15 -> 4317 | O65: =M65*H65 -> 863400
C66: 商品コード : | D66: =[1]SD新基準!$AP$15 -> 0
B68: 15 | C68: 商品モデル番号 : | D68: =[1]SD新基準!$AR$16 -> 0 | H68: =[1]SD新基準!$L$16 -> 200 | J68: EA | K68: 円 | M68: =[1]SD新基準!$AF$16 -> 4317 | O68: =M68*H68 -> 863400
C69: 商品コード : | D69: =[1]SD新基準!$AP$16 -> 0
B71: 16 | C71: 商品モデル番号 : | D71: =[1]SD新基準!$AR$17 -> SDSQUNB-064G-GN3MN | H71: =[1]SD新基準!$L$17 -> 200 | J71: EA | K71: 円 | M71: =[1]SD新基準!$AF$17 -> 7131 | O71: =M71*H71 -> 1426200
C72: 商品コード : | D72: =[1]SD新基準!$AP$17 -> 0619659134068, 4031039880642, 4893433124148, 5054629833599, 8944129953071
C74: 支払い方法 | D74: 銀行振込
C75: お支払期日 | D75: =管理!O1 -> 46105
C76: お振込口座 | D76: =VLOOKUP(管理!C1,管理!A4:U100,12,0) -> みずほ銀行 品川支店 普通7759780
D77: =VLOOKUP(管理!C1,管理!A4:U100,13,0) -> サンディスク（ド
J78: 税率（％） | K78: : 10 | L78: 円 | M78: 小計: | O78: =SUM(O26:O72) -> 15522500
M79: 割引額: | O79: 0
M80: 配送料: | O80: 0
J81: 税率（％） | K81: : 10 | M81: 消費税額: | O81: =O78*10% -> 1552250
L82: 円 | M82: 合計: | O82: =O78+O81 -> 17074750

Sheet 1_8_納品書　図形バージョン  (2)
G2: Page | H2: 1 of 1
C3: 納品書 | I3: =VLOOKUP(管理!$C$1,管理!A4:S53,2,0) -> サンディスク合同会社
I4: =VLOOKUP(管理!$C$1,管理!A4:T53,4,0) -> 東京都港区港南1丁目6番31号
I5: =IFERROR( IF(OR(VLOOKUP(管理!$C$1,管理!$A$4:$V$100,5,0)=0, VLOOKUP(管理!$C$1,管理!$A$4:$V$100,5,0)=""), "", VLOOKUP(管理!$C$1,管理!A5:T54,5,0) ), "") -> 品川東急ビル3階
I6: =VLOOKUP(管理!$C$1,管理!$A$4:$V$100,6,0) -> 0120-893-009
A7: 注文番号 | C7: 配送番号 | D7: =#REF! -> #REF!
A8: お名前 | B8: =VLOOKUP(管理!$C2,管理!A4:$AA$103,2,0) -> 柏尾奏利（KASIOshop） | E8: 日付 | F8: =管理!I1 -> 46097
A9: 住所 | B9: =VLOOKUP(管理!$C$2,管理!A4:S50,4,0) -> 東京都板橋区南常盤台1丁目11番6号 | E9: 連絡先 | F9: =VLOOKUP(管理!$C2,管理!A4:$AA$103,6,0) -> 03-3600-3333
B10: =VLOOKUP(管理!$C$2,管理!A5:S51,5,0) -> ウエアーハウス303号室
B11: ="〒"&VLOOKUP(管理!$C$2,管理!A3:S49,3,0) -> 〒174-0072
B12: JAPAN
A14: 製品名 | G14: 数量
A15: ="商品モデル番号："&[1]SD新基準!$AR2&" 商品コード："&[1]SD新基準!$AP2 -> 商品モデル番号：7545783945 商品コード：9349220005022 | G15: =[1]SD新基準!$L2 -> 0
A16: ="商品モデル番号："&[1]SD新基準!$AR3&" 商品コード："&[1]SD新基準!$AP3 -> 商品モデル番号：9349220005039 商品コード：9349220005039 | G16: =[1]SD新基準!$L3 -> 0
A17: ="商品モデル番号："&[1]SD新基準!$AR4&" 商品コード："&[1]SD新基準!$AP4 -> 商品モデル番号：SDSQUNS-032G-GN3MN 商品コード：0619659161651 | G17: =[1]SD新基準!$L4 -> 200
A18: ="商品モデル番号："&[1]SD新基準!$AR5&" 商品コード："&[1]SD新基準!$AP5 -> 商品モデル番号：SDSQUNS-032G-GN3MN 商品コード：0619659184384 | G18: =[1]SD新基準!$L5 -> 200
A19: ="商品モデル番号："&[1]SD新基準!$AR6&" 商品コード："&[1]SD新基準!$AP6 -> 商品モデル番号：SDSQUNS-032G-GN3MA 商品コード：0619659161644, 6195765406328, 7840000001712 | G19: =[1]SD新基準!$L6 -> 200
A20: ="商品モデル番号："&[1]SD新基準!$AR7&" 商品コード："&[1]SD新基準!$AP7 -> 商品モデル番号：SDSQUNB-032G-GN3MN 商品コード：0619659134044 | G20: =[1]SD新基準!$L7 -> 200
A21: ="商品モデル番号："&[1]SD新基準!$AR8&" 商品コード："&[1]SD新基準!$AP8 -> 商品モデル番号：SDSDQUA-032G-U46A 商品コード：0619659078645, 5053460346961, 5554442365203, 6196590786456, 7044447834692, 7123290469845, 7987987901489 | G21: =[1]SD新基準!$L8 -> 200
A22: ="商品モデル番号："&[1]SD新基準!$AR9&" 商品コード："&[1]SD新基準!$AP9 -> 商品モデル番号：43237-2 商品コード：0068888807494, 0619659246518 | G22: =[1]SD新基準!$L9 -> 200
A23: ="商品モデル番号："&[1]SD新基準!$AR10&" 商品コード："&[1]SD新基準!$AP10 -> 商品モデル番号：SDSQUNC-032G-GN6MA 商品コード：0619659134747 | G23: =[1]SD新基準!$L10 -> 10
A24: ="商品モデル番号："&[1]SD新基準!$AR11&" 商品コード："&[1]SD新基準!$AP11 -> 商品モデル番号：SDSQUNS-064G-GHEMA 商品コード：0619659172916 | G24: =[1]SD新基準!$L11 -> 200
A25: ="商品モデル番号："&[1]SD新基準!$AR12&" 商品コード："&[1]SD新基準!$AP12 -> 商品モデル番号：SDSQUNR-064G-GN3MN 商品コード：0619659185077, 0799833000614 | G25: =[1]SD新基準!$L12 -> 200
A26: ="商品モデル番号："&[1]SD新基準!$AR13&" 商品コード："&[1]SD新基準!$AP13 -> 商品モデル番号：SDSQUNS-064G-GN3MN 商品コード：0619659161927 | G26: =[1]SD新基準!$L13 -> 200
... A30: ="商品モデル番号："&[1]SD新基準!$AR17&" 商品コード："&[1]SD新基準!$AP17 -> 商品モデル番号：SDSQUNB-064G-GN3MN 商品コード：0619659134068, 4031039880642, 4893433124148, 5054629833599, 8944129953071 | G30: =[1]SD新基準!$L17 -> 200
F31: 合計： | G31: =SUM(G15:I30) -> 2610
A33: この度はサンディスクストアにて商品をお買い上げいただき誠にありがとうございます。
A34: 商品を送付させていただきます。今後ともご愛顧賜りますよう何卒よろしくお願い申し上げます。

Sheet 2_請求書
A1: 請求書
T2: 登録番号 | U2: ： | V2: T5010401008297
V3: 46020
A7: 113-0033 | Q7: キャノンマーケティングジャパン株式会社
A8: 東京都文京区本郷２丁目２５番１４
A9: 第一ライトビル509号室
A10: 株式会社レイディスク | G10: 御中
R11: 108-8011
R12: 東京都港区南２丁目１６番６号
R13: キャノンマーケティングジャパン株式会社
R14: Tel | T14: ：050-1808-7960
B15: 00000-0000-0000
B18: 株式会社レイディスク | H18: 御中
B20: いつも格別のお引立てを賜り誠に有難うございます。
B21: 下記の通りご請求申し上げます。
O23: お支払方法 | P23: ： | Q23: 下記の口座にお振込願います。
B24: お客様番号 | F24: ： | G24: 00000-0000-0000 | O24: お支払期日 | P24: ： | Q24: 46021
B25: 請求書No. | F25: ： | G25: 123456789 | O25: お振込口座 | P25: ： | Q25: 住信SBIネット銀行
B26: 締日 | F26: ： | G26: 46002 | Q26: キウイ支店
B27: ご請求金額（税込） | F27: ： | G27: =V63 -> 1218.8 | H27: ー | Q27: 当座 6827254
Q28: キャノンマーケティングジャパン（カ
B30: ー商品代金明細ー
B31: 取引日 | E31: 46003 | M31: 受注No. | O31: 123465
B32: 伝票No. | E32: 123456786 | M32: 発注No. | T32: 専用伝票No.
C33: 品名 | M33: 型番【アイテム発注No.】 | Q33: 数量 | T33: 単価 | V33: 金額
C34: SanDisk (サンディスク) Ultra SDXC メモリーカード | M34: SDSDUNC-128G-GZFIN | Q34: 1 | R34: 個 | T34: 1018 | V34: 1018
B36: 取引日 | E36: 46003 | M36: 受注No. | O36: 123465
B37: 伝票No. | E37: 123456786 | M37: 発注No. | T37: 専用伝票No.
C38: 品名 | M38: 型番【アイテム発注No.】 | Q38: 数量 | T38: 単価 | V38: 金額
C39: SanDisk (サンディスク) Ultra SDXC メモリーカード | M39: SDSDUNC-128G-GZFIN | Q39: 1 | R39: 個 | T39: 45 | V39: 45
C40: SanDisk (サンディスク) Ultra SDXC メモリーカード | M40: SDSDUNC-128G-GZFIN | Q40: 1 | R40: 個 | T40: 45 | V40: 45
C51: 売上先CD | G51: 23564323
C52: 売上先名 | G52: 株式会社レイディスク
K55: ＜商品代金合計＞ | O55: お買上総額（税抜） | V55: 1108
O58: ご請求金額（税抜） | V58: =V55 -> 1108
O59: （10％対象 | V59: =V58 -> 1108
P60: 消費税等 | V60: =V58*10% -> 110.8 | W60: ）
O61: （軽減税率 8％対象
P62: 消費税等 | W62: ）
O63: ご請求金額（税込） | V63: =V58+V60 -> 1218.8
B67: #…非課税または免税／＊…軽減税率対象品目／!…8％税率対象品目
B68: X…全額ご入金済／レ…一部ご入金済

Sheet 2_納品書
A1: 納品書
O2: 1/ | P2: 1
P5: キャノンマーケティングジャパン株式会社
A7: 113-0033 | C7: 東京都文京区
A8: 本郷２丁目２５－１４ 第一ライトビル５階９号室
A9: 山之内 雄一 | D9: 様
K10: ■お問い合わせ先
K11: キャノンオンラインショップ コールセンター
K12: TEL：０５７０ー０８ー００５８
K13: ↑↑↑
K14: ※局番０５７０のお掛け間違いにご注意ください
K15: 受付時間：平日９：００～１７：００
K16: （土日祝、年末年始、弊社休業日を除く）
A22: 伝票番号 | C22: ： | D22: OM1859261574 | I22: 見積番号 | J22: ：
A23: 受注番号 | C23: ： | D23: 229637321 | I23: 注文番号 | J23: ： | K23: CA03015237
A24: 出荷日 | C24: ： | D24: 46028 | I24: 専用伝票番号 | J24: ：
A25: 到着予定日 | C25: ： | D25: 46029
A27: いつも格別のお引き立てを賜り誠に有難うございます。
A28: 下記商品を納品いたします。
A30: ー商品明細ー
A31: 品名
A32: 注文番号 | C32: 商品コード | F32: 型番 | I32: JAN／UPCコード | L32: 数量 | N32: 単価 | P32: 金額
A33: SanDisk ウルトラ プラス SDHC UHSーⅠ 32G SDSUW3-032G-JNJIN
A34: 1 | C34: SDSUW3-032G-JNJIN | F34: SDSUW3-032G-JNJIN | I34: 4523052022814 | L34: 1 | M34: 個
A35: EC配送料
A36: 1 | C36: 010ZZ480
A60: 免税または非課税商品は明細右隅に「＃」、軽減税率商品は「＊」を表示しております。
A62: ■ご発注元 | J62: ■お届け先
A63: 山之内 雄一 | D63: 様

Sheet 2_1_請求書
A1: ご請求書
T2: 登録番号 | U2: ： | V2: T5010401008297
V3: 45718
A7: 103-0023 | Q7: キャノンマーケティングジャパン株式会社
A8: 東京都中央区日本橋本町3-9-4
A9: 浜田電機株式会社 御中
A10: TEL：03-5651-7351 FAX：03-5651-7353
A11: E-mail：m-hukuhara@hamada-dk.co.jp | R11: 108-8011
A12: 登録番号：T6010001026302 | R12: 東京都港区南２丁目１６番６号
R13: キャノンマーケティングジャパン株式会社
R14: Tel. ：050-1808-7960
B15: =G24 -> 95468-8756-3221
B18: =A9 -> 浜田電機株式会社 御中
B20: いつも格別のお引立てを賜り誠に有難うございます。
B21: 下記の通りご請求申し上げます。
O23: お支払方法 | P23: ： | Q23: 下記の口座にお振込願います。
B24: お客様番号 | F24: ： | G24: 95468-8756-3221 | O24: お支払期日 | P24: ： | Q24: 45726
B25: 請求書No. | F25: ： | G25: CA03015237 | O25: お振込口座 | P25: ： | Q25: 住信SBIネット銀行
B26: 締日 | F26: ： | G26: 45726 | Q26: キウイ支店
B27: ご請求金額（税込） | F27: ： | G27: =V63 -> 5642010 | H27: ー | Q27: 当座 6827254
Q28: キャノンマーケティングジャパン（カ
B30: ー商品代金明細ー
B31: 取引日 | E31: =V3 -> 45718 | M31: 受注No. | O31: 123465
B32: 伝票No. | E32: OM1859261574 | M32: 発注No. | T32: 専用伝票No.
C33: 品名 | M33: 型番【アイテム発注No.】 | Q33: 数量 | T33: 単価 | V33: 金額
C34: SanDisk microSDカード 128GB エクストリーム microSDXC UHS-I | M34: SDSQXA1-128G-GN6MN | Q34: 450 | R34: 個 | T34: 1700 | V34: =T34*Q34 -> 765000
C35: SanDisk microSDカード 256GB エクストリーム microSDXC UHS-I | M35: SDSQXA1-256G-GN6MN | Q35: 260 | R35: 個 | T35: 3050 | V35: =T35*Q35 -> 793000
C36: SanDisk microSDカード 512GB エクストリーム microSDXC UHS-I | M36: SDSQXA1-512G-GN6MN | Q36: 55 | R36: 個 | T36: 5990 | V36: =T36*Q36 -> 329450
C37: SanDisk microSDカード 64GB エクストリーム microSDXC UHS-I | M37: SDSQXAH-064G-GN6MN | Q37: 540 | R37: 個 | T37: 1050 | V37: =T37*Q37 -> 567000
C38: SanDisk microSDカード 128GB エクストリーム microSDXC UHS-I | M38: SDSQXAA-128G-GN6MN | Q38: 520 | R38: 個 | T38: 1650 | V38: =T38*Q38 -> 858000
C39: SanDisk microSDカード 256GB エクストリーム microSDXC UHS-I | M39: SDSQXAV-256G-GN6MN | Q39: 250 | R39: 個 | T39: 2750 | V39: =T39*Q39 -> 687500
C40: SanDisk microSDカード 64GB High Endurance microSDXC UHS-I | M40: SDSQQNR-064G-GH3IA | Q40: 50 | R40: 個 | T40: 990 | V40: =T40*Q40 -> 49500
C41: SanDisk microSDカード 128GB High Endurance microSDXC UHS-I | M41: SDSQQNR-128G-GH3IA | Q41: 25 | R41: 個 | T41: 1710 | V41: =T41*Q41 -> 42750
C42: SanDisk microSDカード 256GB High Endurance microSDXC UHS-I | M42: SDSQQNR-256G-GH3IA | Q42: 35 | R42: 個 | T42: 2940 | V42: =T42*Q42 -> 102900
C43: SanDisk SDカード 64GB エクストリーム SDXC UHS-I | M43: SDSDXV2-064G-GHJIN | Q43: 50 | R43: 個 | T43: 1750 | V43: =T43*Q43 -> 87500
C44: SanDisk SDカード 128GB エクストリーム SDXC UHS-I | M44: SDSDXVA-128G-GHJIN | Q44: 75 | R44: 個 | T44: 2940 | V44: =T44*Q44 -> 220500
C45: SanDisk SDカード 256GB エクストリーム SDXC UHS-I | M45: SDSDXVV-256G-GHJIN | Q45: 30 | R45: 個 | T45: 4600 | V45: =T45*Q45 -> 138000
... C48: SanDisk SDカード 256GB エクストリーム プロ SDXC UHS-I | M48: SDSDXXD-256G-GHJIN | Q48: 35 | R48: 個 | T48: 6500 | V48: =T48*Q48 -> 227500
C51: 売上先CD | G51: 235643-2354
C52: 売上先名 | G52: =A9 -> 浜田電機株式会社 御中
K55: ＜商品代金合計＞ | O55: お買上総額（税抜） | V55: =SUM(V34:V52) -> 5129100
O58: ご請求金額（税抜） | V58: =V55 -> 5129100
O59: （10％対象 | V59: =V58 -> 5129100
P60: 消費税等 | V60: =V58*10% -> 512910 | W60: ）
O61: （軽減税率 8％対象
P62: 消費税等 | W62: ）
O63: ご請求金額（税込） | V63: =V58+V60 -> 5642010
B67: #…非課税または免税／＊…軽減税率対象品目／!…8％税率対象品目 | M67: 0001/0001
B68: X…全額ご入金済／レ…一部ご入金済

Sheet 2_1_納品書
A1: 納品書
M2: 登録番号： | P2: T5010401008297
O3: 45718
P5: キャノンマーケティングジャパン株式会社
A6: 103-0023
A7: 東京都中央区日本橋本町3-9-4
A8: 浜田電機株式会社 御中
A9: TEL：03-5651-7351 FAX：03-5651-7353
A10: E-mail：m-hukuhara@hamada-dk.co.jp | L10: 108-8011
A11: 登録番号：T6010001026302 | L11: 東京都港区港南２丁目１６番６号
L12: キャノンマーケティングジャパン株式会社
L13: Tel. ：050-1808-7960
A18: 伝票番号 | C18: ： | D18: OM1859261574 | I18: 見積番号 | J18: ：
A19: 受注番号 | C19: ： | D19: 229637321 | I19: 注文番号 | J19: ： | K19: CA03015237
A20: 出荷日 | C20: ： | D20: 46028 | I20: 専用伝票番号 | J20: ：
A21: 到着予定日 | C21: ： | D21: 46029
A23: いつも格別のお引き立てを賜り誠に有難うございます。
A24: 下記商品を納品いたします。
A26: ー商品明細ー
A27: 品名
A28: 注文番号 | C28: 商品コード | F28: 型番 | I28: JAN／UPCコード | L28: 数量 | N28: 単価 | P28: 金額
A29: SanDisk microSDカード 128GB エクストリーム microSDXC UHS-I
A30: 1 | C30: =F30 -> SDSQXA1-128G-GN6MN | F30: SDSQXA1-128G-GN6MN | I30: 0619659180034 | L30: 450 | M30: 個 | N30: 1700 | O30: 765000
A31: SanDisk microSDカード 256GB エクストリーム microSDXC UHS-I
A32: 1 | C32: =F32 -> SDSQXA1-256G-GN6MN | F32: SDSQXA1-256G-GN6MN | I32: 0619659180041 | L32: 260 | M32: 個 | N32: 3050 | O32: 793000
A33: SanDisk microSDカード 512GB エクストリーム microSDXC UHS-I
A34: 1 | C34: =F34 -> SDSQXA1-512G-GN6MN | F34: SDSQXA1-512G-GN6MN | I34: 0619659189655 | L34: 55 | M34: 個 | N34: 5990 | O34: 329450
A35: SanDisk microSDカード 64GB エクストリーム microSDXC UHS-I
A36: 1 | C36: =F36 -> SDSQXAH-064G-GN6MN | F36: SDSQXAH-064G-GN6MN | I36: 0619659193416 | L36: 540 | M36: 個 | N36: 1050 | O36: 567000
A37: SanDisk microSDカード 128GB エクストリーム microSDXC UHS-I
A38: 1 | C38: =F38 -> SDSQXAA-128G-GN6MN | F38: SDSQXAA-128G-GN6MN | I38: 0619659188467 | L38: 520 | M38: 個 | N38: 1650 | O38: 858000
A39: SanDisk microSDカード 256GB エクストリーム microSDXC UHS-I
A40: 1 | C40: =F40 -> SDSQXAV-256G-GN6MN | F40: SDSQXAV-256G-GN6MN | I40: 0619659188511 | L40: 250 | M40: 個 | N40: 2750 | O40: 687500
A41: SanDisk microSDカード 64GB High Endurance microSDXC UHS-I
A42: 1 | C42: =F42 -> SDSQQNR-064G-GH3IA | F42: SDSQQNR-064G-GH3IA | I42: 0619659197711 | L42: 50 | M42: 個 | N42: 990 | O42: 49500
A43: SanDisk microSDカード 128GB High Endurance microSDXC UHS-I
A44: 1 | C44: =F44 -> SDSQQNR-128G-GH3IA | F44: SDSQQNR-128G-GH3IA | I44: 0619659198923 | L44: 25 | M44: 個 | N44: 1710 | O44: 42750
A45: SanDisk microSDカード 256GB High Endurance microSDXC UHS-I
A46: 1 | C46: =F46 -> SDSQQNR-256G-GH3IA | F46: SDSQQNR-256G-GH3IA | I46: 0619659198930 | L46: 35 | M46: 個 | N46: 2940 | O46: 102900
A47: SanDisk SDカード 64GB エクストリーム SDXC UHS-I
A48: 1 | C48: =F48 -> SDSDXV2-064G-GHJIN | F48: SDSDXV2-064G-GHJIN | I48: 0619659197834 | L48: 50 | M48: 個 | N48: 1750 | O48: 87500
A49: SanDisk SDカード 128GB エクストリーム SDXC UHS-I
A50: 1 | C50: =F50 -> SDSDXVA-128G-GHJIN | F50: SDSDXVA-128G-GHJIN | I50: 0619659197841 | L50: 75 | M50: 個 | N50: 2940 | O50: 220500
A51: SanDisk SDカード 256GB エクストリーム SDXC UHS-I
A52: 1 | C52: =F52 -> SDSDXVV-256G-GHJIN | F52: SDSDXVV-256G-GHJIN | I52: 0619659197858 | L52: 30 | M52: 個 | N52: 4600 | O52: 138000
A53: SanDisk SDカード 64GB エクストリーム プロ SDXC UHS-I
A54: 1 | C54: =F54 -> SDSDXXU-064G-GHJIN | F54: SDSDXXU-064G-GHJIN | I54: 0619659197872 | L54: 50 | M54: 個 | N54: 2200 | O54: 110000
A55: SanDisk SDカード 128GB エクストリーム プロ SDXC UHS-I
A56: 1 | C56: =F56 -> SDSDXXD-128G-GHJIN | F56: SDSDXXD-128G-GHJIN | I56: 0619659197889 | L56: 35 | M56: 個 | N56: 4300 | O56: 150500
A57: SanDisk SDカード 64GB エクストリーム プロ SDXC UHS-I
A58: 1 | C58: =F58 -> SDSDXXU-064G-GHJIN | F58: SDSDXXU-064G-GHJIN | I58: 0619659197872 | L58: 50 | M58: 個 | N58: 2200 | O58: 110000
A64: 免税または非課税商品は明細右隅に「＃」、軽減税率商品は「＊」を表示しております。
A66: ■ご発注元 | J66: ■お届け先
A67: =A8 -> 浜田電機株式会社 御中

Sheet 2_2_請求書
A1: ご請求書
T2: 登録番号 | U2: ： | V2: T5010401008297
V3: 45718
B7: 174-0072 | Q7: キヤノンマーケティングジャパン株式会社
B8: 東京都板橋区南常盤台1丁目１１番６号
B9: ウエアーハウス303号室
B10: 柏尾奏利（KASIOshop）様
R11: 108-8011
R12: 東京都港区港南２丁目１６番６号
R13: キヤノンマーケティングジャパン株式会社
R14: Tel. ：050-1808-7960
B15: =G24 -> 95468-8756-3221
B18: =B10 -> 柏尾奏利（KASIOshop）様
B20: いつも格別のお引立てを賜り誠に有難うございます。
B21: 下記の通りご請求申し上げます。
O23: お支払方法 | P23: ： | Q23: 下記の口座にお振込願います。
B24: お客様番号 | F24: ： | G24: 95468-8756-3221 | O24: お支払期日 | P24: ： | Q24: =G26 -> 45726
B25: 請求書No. | F25: ： | G25: CA03015237 | O25: お振込口座 | P25: ： | Q25: 三菱UFJ銀行
B26: 締日 | F26: ： | G26: 45726 | Q26: 品川駅前支店
B27: ご請求金額（税込） | F27: ： | G27: =V63 -> 5642010 | Q27: 普通口座 7412859
Q28: キヤノンマーケティングジャパン（カ
B30: ー商品代金明細ー
B31: 取引日 | E31: =V3 -> 45718
B32: 伝票No. | E32: OM1859261574
C33: 品名 | M33: 型番【アイテム発注No.】 | Q33: 数量 | T33: 単価 | V33: 金額
C34: SanDisk microSDカード 128GB エクストリーム microSDXC UHS-I | M34: SDSQXA1-128G-GN6MN | Q34: 450 | R34: 個 | T34: 1700 | V34: =T34*Q34 -> 765000
C35: SanDisk microSDカード 256GB エクストリーム microSDXC UHS-I | M35: SDSQXA1-256G-GN6MN | Q35: 260 | R35: 個 | T35: 3050 | V35: =T35*Q35 -> 793000
C36: SanDisk microSDカード 512GB エクストリーム microSDXC UHS-I | M36: SDSQXA1-512G-GN6MN | Q36: 55 | R36: 個 | T36: 5990 | V36: =T36*Q36 -> 329450
C37: SanDisk microSDカード 64GB エクストリーム microSDXC UHS-I | M37: SDSQXAH-064G-GN6MN | Q37: 540 | R37: 個 | T37: 1050 | V37: =T37*Q37 -> 567000
C38: SanDisk microSDカード 128GB エクストリーム microSDXC UHS-I | M38: SDSQXAA-128G-GN6MN | Q38: 520 | R38: 個 | T38: 1650 | V38: =T38*Q38 -> 858000
C39: SanDisk microSDカード 256GB エクストリーム microSDXC UHS-I | M39: SDSQXAV-256G-GN6MN | Q39: 250 | R39: 個 | T39: 2750 | V39: =T39*Q39 -> 687500
C40: SanDisk microSDカード 64GB High Endurance microSDXC UHS-I | M40: SDSQQNR-064G-GH3IA | Q40: 50 | R40: 個 | T40: 990 | V40: =T40*Q40 -> 49500
C41: SanDisk microSDカード 128GB High Endurance microSDXC UHS-I | M41: SDSQQNR-128G-GH3IA | Q41: 25 | R41: 個 | T41: 1710 | V41: =T41*Q41 -> 42750
C42: SanDisk microSDカード 256GB High Endurance microSDXC UHS-I | M42: SDSQQNR-256G-GH3IA | Q42: 35 | R42: 個 | T42: 2940 | V42: =T42*Q42 -> 102900
C43: SanDisk SDカード 64GB エクストリーム SDXC UHS-I | M43: SDSDXV2-064G-GHJIN | Q43: 50 | R43: 個 | T43: 1750 | V43: =T43*Q43 -> 87500
C44: SanDisk SDカード 128GB エクストリーム SDXC UHS-I | M44: SDSDXVA-128G-GHJIN | Q44: 75 | R44: 個 | T44: 2940 | V44: =T44*Q44 -> 220500
C45: SanDisk SDカード 256GB エクストリーム SDXC UHS-I | M45: SDSDXVV-256G-GHJIN | Q45: 30 | R45: 個 | T45: 4600 | V45: =T45*Q45 -> 138000
... C48: SanDisk SDカード 256GB エクストリーム プロ SDXC UHS-I | M48: SDSDXXD-256G-GHJIN | Q48: 35 | R48: 個 | T48: 6500 | V48: =T48*Q48 -> 227500
C51: 売上先CD | G51: 235643-2354
C52: 売上先名 | G52: =B10 -> 柏尾奏利（KASIOshop）様
K55: ＜商品代金合計＞ | O55: お買上総額（税抜） | V55: =SUM(V34:V52) -> 5129100
O58: ご請求金額（税抜） | V58: =V55 -> 5129100
O59: （10％対象 | V59: =V58 -> 5129100
P60: 消費税等 | V60: =V58*10% -> 512910 | W60: ）
O61: （軽減税率 8％対象
P62: 消費税等 | W62: ）
O63: ご請求金額（税込） | V63: =V58+V60 -> 5642010
B67: #…非課税または免税／＊…軽減税率対象品目／!…8％税率対象品目 | M67: 0001/0001
B68: X…全額ご入金済／レ…一部ご入金済

Sheet 2_2_納品書
A1: 納品書
M2: 登録番号： | P2: T5010401008297
O3: 45718
P5: キヤノンマーケティングジャパン株式会社
B6: 174-0072
B7: 東京都板橋区南常盤台1丁目１１番６号
B8: ウエアーハウス303号室
B9: 柏尾奏利（KASIOshop）様
L10: 108-8011
L11: 東京都港区港南２丁目１６番６号
L12: キヤノンマーケティングジャパン株式会社
L13: Tel. ：050-1808-7960
A18: 伝票番号 | C18: ： | D18: OM1859261574 | I18: 見積番号 | J18: ：
A19: 受注番号 | C19: ： | D19: 229637321 | I19: 注文番号 | J19: ： | K19: CA03015237
A20: 出荷日 | C20: ： | D20: =O3 -> 45718 | I20: 専用伝票番号 | J20: ：
A21: 到着予定日 | C21: ： | D21: =D20+2 -> 45720
A23: いつも格別のお引き立てを賜り誠に有難うございます。
A24: 下記商品を納品いたします。
A26: ー商品明細ー
A27: 品名
A28: 注文番号 | C28: 商品コード | F28: 型番 | I28: JAN／UPCコード | L28: 数量 | N28: 単価 | P28: 金額
A29: SanDisk microSDカード 128GB エクストリーム microSDXC UHS-I
F30: SDSQXA1-128G-GN6MN | I30: 0619659180034 | L30: 450 | M30: 個 | N30: 1700 | O30: 765000
A31: SanDisk microSDカード 256GB エクストリーム microSDXC UHS-I
F32: SDSQXA1-256G-GN6MN | I32: 0619659180041 | L32: 260 | M32: 個 | N32: 3050 | O32: 793000
A33: SanDisk microSDカード 512GB エクストリーム microSDXC UHS-I
F34: SDSQXA1-512G-GN6MN | I34: 0619659180065 | L34: 55 | M34: 個 | N34: 5990 | O34: 329450
A35: SanDisk microSDカード 64GB エクストリーム microSDXC UHS-I
F36: SDSQXAH-064G-GN6MN | I36: 0619659193416 | L36: 540 | M36: 個 | N36: 1050 | O36: 567000
A37: SanDisk microSDカード 128GB エクストリーム microSDXC UHS-I
F38: SDSQXAA-128G-GN6MN | I38: 0619659188467 | L38: 520 | M38: 個 | N38: 1650 | O38: 858000
A39: SanDisk microSDカード 256GB エクストリーム microSDXC UHS-I
F40: SDSQXAV-256G-GN6MN | I40: 0619659188511 | L40: 250 | M40: 個 | N40: 2750 | O40: 687500
A41: SanDisk microSDカード 64GB High Endurance microSDXC UHS-I
F42: SDSQQNR-064G-GH3IA | I42: 0619659197711 | L42: 50 | M42: 個 | N42: 990 | O42: 49500
A43: SanDisk microSDカード 128GB High Endurance microSDXC UHS-I
F44: SDSQQNR-128G-GH3IA | I44: 0619659198923 | L44: 25 | M44: 個 | N44: 1710 | O44: 42750
A45: SanDisk microSDカード 256GB High Endurance microSDXC UHS-I
F46: SDSQQNR-256G-GH3IA | I46: 0619659198930 | L46: 35 | M46: 個 | N46: 2940 | O46: 102900
A47: SanDisk SDカード 64GB エクストリーム SDXC UHS-I
F48: SDSDXV2-064G-GHJIN | I48: 0619659197834 | L48: 50 | M48: 個 | N48: 1750 | O48: 87500
A49: SanDisk SDカード 128GB エクストリーム SDXC UHS-I
F50: SDSDXVA-128G-GHJIN | I50: 0619659197841 | L50: 75 | M50: 個 | N50: 2940 | O50: 220500
A51: SanDisk SDカード 256GB エクストリーム SDXC UHS-I
F52: SDSDXVV-256G-GHJIN | I52: 0619659197858 | L52: 30 | M52: 個 | N52: 4600 | O52: 138000
A53: SanDisk SDカード 64GB エクストリーム プロ SDXC UHS-I
F54: SDSDXXU-064G-GHJIN | I54: 0619659197872 | L54: 50 | M54: 個 | N54: 2200 | O54: 110000
A55: SanDisk SDカード 128GB エクストリーム プロ SDXC UHS-I
F56: SDSDXXD-128G-GHJIN | I56: 0619659197889 | L56: 35 | M56: 個 | N56: 4300 | O56: 150500
A57: SanDisk SDカード 256GB エクストリーム プロ SDXC UHS-I
F58: SDSDXXD-256G-GHJIN | I58: 0619659197896 | L58: 35 | M58: 個 | N58: 6500 | O58: 227500
A64: 免税または非課税商品は明細右隅に「＃」、軽減税率商品は「＊」を表示しております。
A66: ■ご発注元 | J66: ■お届け先
A67: =B9 -> 柏尾奏利（KASIOshop）様

Sheet 2_3_請求書JANあり
A1: ご請求書
U2: 登録番号 | V2: ： | W2: T5010401008297
W3: 45718
B7: 174-0072 | R7: キヤノンマーケティングジャパン株式会社
B8: 東京都板橋区南常盤台1丁目１１番６号
B9: ウエアーハウス303号室
B10: 柏尾奏利（KASIOshop）様
S11: 108-8011
S12: 東京都港区港南2丁目16番6号
S13: キヤノンマーケティングジャパン株式会社
S14: Tel. ：050-1808-7960
B15: =G24 -> 95468-8756-3221
B18: =B10 -> 柏尾奏利（KASIOshop）様
B20: いつも格別のお引立てを賜り誠に有難うございます。
B21: 下記の通りご請求申し上げます。
Q23: お支払方法： | R23: 下記の口座にお振込願います。
B24: お客様番号 | F24: ： | G24: 95468-8756-3221 | Q24: お支払期日： | R24: =G26 -> 45726
B25: 請求書No. | F25: ： | G25: CA03015237 | Q25: お振込口座： | R25: 三菱UFJ銀行
B26: 締日 | F26: ： | G26: 45726 | R26: 品川駅前支店
B27: ご請求金額（税込） | F27: ： | G27: =W78 -> 5642010 | R27: 普通口座 7412859
R28: キヤノンマーケティングジャパン（カ
B30: ー商品代金明細ー
B31: 取引日 | E31: =W3 -> 45718
B32: 伝票No. | E32: OM1859261574
C33: 品名 | M33: 型番【アイテム発注No.】 | Q33: JAN／UPCコード | R33: 数量 | U33: 単価 | W33: 金額
C34: SanDisk microSDカード 128GB エクストリーム microSDXC UHS-I | M34: SDSQXA1-128G-GN6MN | Q34: 0619659180034 | R34: 450 | S34: 個 | U34: 1700 | W34: =U34*R34 -> 765000
C35: SanDisk microSDカード 256GB エクストリーム microSDXC UHS-I | M35: SDSQXA1-256G-GN6MN | Q35: 0619659180041 | R35: 260 | S35: 個 | U35: 3050 | W35: =U35*R35 -> 793000
C36: SanDisk microSDカード 512GB エクストリーム microSDXC UHS-I | M36: SDSQXA1-512G-GN6MN | Q36: 0619659180065 | R36: 55 | S36: 個 | U36: 5990 | W36: =U36*R36 -> 329450
C37: SanDisk microSDカード 64GB エクストリーム microSDXC UHS-I | M37: SDSQXAH-064G-GN6MN | Q37: 0619659193416 | R37: 540 | S37: 個 | U37: 1050 | W37: =U37*R37 -> 567000
C38: SanDisk microSDカード 128GB エクストリーム microSDXC UHS-I | M38: SDSQXAA-128G-GN6MN | Q38: 0619659188467 | R38: 520 | S38: 個 | U38: 1650 | W38: =U38*R38 -> 858000
C39: SanDisk microSDカード 256GB エクストリーム microSDXC UHS-I | M39: SDSQXAV-256G-GN6MN | Q39: 0619659188511 | R39: 250 | S39: 個 | U39: 2750 | W39: =U39*R39 -> 687500
C40: SanDisk microSDカード 64GB High Endurance microSDXC UHS-I | M40: SDSQQNR-064G-GH3IA | Q40: 0619659197711 | R40: 50 | S40: 個 | U40: 990 | W40: =U40*R40 -> 49500
C41: SanDisk microSDカード 128GB High Endurance microSDXC UHS-I | M41: SDSQQNR-128G-GH3IA | Q41: 0619659198923 | R41: 25 | S41: 個 | U41: 1710 | W41: =U41*R41 -> 42750
C42: SanDisk microSDカード 256GB High Endurance microSDXC UHS-I | M42: SDSQQNR-256G-GH3IA | Q42: 0619659198930 | R42: 35 | S42: 個 | U42: 2940 | W42: =U42*R42 -> 102900
C43: SanDisk SDカード 64GB エクストリーム SDXC UHS-I | M43: SDSDXV2-064G-GHJIN | Q43: 0619659197834 | R43: 50 | S43: 個 | U43: 1750 | W43: =U43*R43 -> 87500
C44: SanDisk SDカード 128GB エクストリーム SDXC UHS-I | M44: SDSDXVA-128G-GHJIN | Q44: 0619659197841 | R44: 75 | S44: 個 | U44: 2940 | W44: =U44*R44 -> 220500
C45: SanDisk SDカード 256GB エクストリーム SDXC UHS-I | M45: SDSDXVV-256G-GHJIN | Q45: 0619659197858 | R45: 30 | S45: 個 | U45: 4600 | W45: =U45*R45 -> 138000
... C48: SanDisk SDカード 256GB エクストリーム プロ SDXC UHS-I | M48: SDSDXXD-256G-GHJIN | Q48: 0619659197896 | R48: 35 | S48: 個 | U48: 6500 | W48: =U48*R48 -> 227500
C66: 売上先CD | G66: 235643-2354
C67: 売上先名 | G67: =B10 -> 柏尾奏利（KASIOshop）様
K70: ＜商品代金合計＞ | O70: お買上総額（税抜） | W70: =SUM(W34:W67) -> 5129100
O73: ご請求金額（税抜） | W73: =W70 -> 5129100
O74: （10％対象 | W74: =W73 -> 5129100
P75: 消費税等 | W75: =W73*10% -> 512910 | X75: ）
O76: （軽減税率 8％対象
P77: 消費税等 | X77: ）
O78: ご請求金額（税込） | W78: =W73+W75 -> 5642010
B82: #…非課税または免税／＊…軽減税率対象品目／!…8％税率対象品目 | M82: 0001/0001
B83: X…全額ご入金済／レ…一部ご入金済

Sheet 2_3_納品書JANあり
A1: 納品書
M2: 登録番号： | P2: T5010401008297
O3: 45718
P5: キヤノンマーケティングジャパン株式会社
B6: 174-0072
B7: 東京都板橋区南常盤台1丁目１１番６号
B8: ウエアーハウス303号室
B9: 柏尾奏利（KASIOshop）様
L10: 108-8011
L11: 東京都港区港南2丁目16番6号
L12: キヤノンマーケティングジャパン株式会社
L13: Tel. ：050-1808-7960
A18: 伝票番号 | C18: ： | D18: OM1859261574 | I18: 見積番号 | J18: ：
A19: 受注番号 | C19: ： | D19: 229637321 | I19: 注文番号 | J19: ： | K19: CA03015237
A20: 出荷日 | C20: ： | D20: =O3 -> 45718 | I20: 専用伝票番号 | J20: ：
A21: 到着予定日 | C21: ： | D21: =D20+2 -> 45720
A23: いつも格別のお引き立てを賜り誠に有難うございます。
A24: 下記商品を納品いたします。
A26: ー商品明細ー
A27: 品名
A28: 注文番号 | C28: 商品コード | F28: 型番 | I28: JAN／UPCコード | L28: 数量 | N28: 単価 | P28: 金額
A29: SanDisk microSDカード 128GB エクストリーム microSDXC UHS-I
F30: SDSQXA1-128G-GN6MN | I30: 0619659180034 | L30: 450 | M30: 個 | N30: 1700 | O30: 765000
A31: SanDisk microSDカード 256GB エクストリーム microSDXC UHS-I
F32: SDSQXA1-256G-GN6MN | I32: 0619659180041 | L32: 260 | M32: 個 | N32: 3050 | O32: 793000
A33: SanDisk microSDカード 512GB エクストリーム microSDXC UHS-I
F34: SDSQXA1-512G-GN6MN | I34: 0619659180065 | L34: 55 | M34: 個 | N34: 5990 | O34: 329450
A35: SanDisk microSDカード 64GB エクストリーム microSDXC UHS-I
F36: SDSQXAH-064G-GN6MN | I36: 0619659193416 | L36: 540 | M36: 個 | N36: 1050 | O36: 567000
A37: SanDisk microSDカード 128GB エクストリーム microSDXC UHS-I
F38: SDSQXAA-128G-GN6MN | I38: 0619659188467 | L38: 520 | M38: 個 | N38: 1650 | O38: 858000
A39: SanDisk microSDカード 256GB エクストリーム microSDXC UHS-I
F40: SDSQXAV-256G-GN6MN | I40: 0619659188511 | L40: 250 | M40: 個 | N40: 2750 | O40: 687500
A41: SanDisk microSDカード 64GB High Endurance microSDXC UHS-I
F42: SDSQQNR-064G-GH3IA | I42: 0619659197711 | L42: 50 | M42: 個 | N42: 990 | O42: 49500
A43: SanDisk microSDカード 128GB High Endurance microSDXC UHS-I
F44: SDSQQNR-128G-GH3IA | I44: 0619659198923 | L44: 25 | M44: 個 | N44: 1710 | O44: 42750
A45: SanDisk microSDカード 256GB High Endurance microSDXC UHS-I
F46: SDSQQNR-256G-GH3IA | I46: 0619659198930 | L46: 35 | M46: 個 | N46: 2940 | O46: 102900
A47: SanDisk SDカード 64GB エクストリーム SDXC UHS-I
F48: SDSDXV2-064G-GHJIN | I48: 0619659197834 | L48: 50 | M48: 個 | N48: 1750 | O48: 87500
A49: SanDisk SDカード 128GB エクストリーム SDXC UHS-I
F50: SDSDXVA-128G-GHJIN | I50: 0619659197841 | L50: 75 | M50: 個 | N50: 2940 | O50: 220500
A51: SanDisk SDカード 256GB エクストリーム SDXC UHS-I
F52: SDSDXVV-256G-GHJIN | I52: 0619659197858 | L52: 30 | M52: 個 | N52: 4600 | O52: 138000
A53: SanDisk SDカード 64GB エクストリーム プロ SDXC UHS-I
F54: SDSDXXU-064G-GHJIN | I54: 0619659197872 | L54: 50 | M54: 個 | N54: 2200 | O54: 110000
A55: SanDisk SDカード 128GB エクストリーム プロ SDXC UHS-I
F56: SDSDXXD-128G-GHJIN | I56: 0619659197889 | L56: 35 | M56: 個 | N56: 4300 | O56: 150500
A57: SanDisk SDカード 256GB エクストリーム プロ SDXC UHS-I
F58: SDSDXXD-256G-GHJIN | I58: 0619659197896 | L58: 35 | M58: 個 | N58: 6500 | O58: 227500
A59: SanDisk SDカード 128GB エクストリーム プロ SDXC UHS-I
F60: SDSDXXD-128G-GHJIN | I60: 0619659197889 | L60: 35 | M60: 個 | N60: 4300 | O60: 150500
A61: SanDisk SDカード 256GB エクストリーム プロ SDXC UHS-I
F62: SDSDXXD-256G-GHJIN | I62: 0619659197896 | L62: 35 | M62: 個 | N62: 6500 | O62: 227500
A63: SanDisk SDカード 128GB エクストリーム プロ SDXC UHS-I
F64: SDSDXXD-128G-GHJIN | I64: 0619659197889 | L64: 35 | M64: 個 | N64: 4300 | O64: 150500
A65: SanDisk SDカード 256GB エクストリーム プロ SDXC UHS-I
F66: SDSDXXD-256G-GHJIN | I66: 0619659197896 | L66: 35 | M66: 個 | N66: 6500 | O66: 227500
A78: 免税または非課税商品は明細右隅に「＃」、軽減税率商品は「＊」を表示しております。
A80: ■ご発注元 | J80: ■お届け先
A81: =B9 -> 柏尾奏利（KASIOshop）様

Sheet 2_4_請求書JANあり
A1: ご請求書
T2: 登録番号 | U2: ： | V2: T5010401008297
V3: 45718
B7: 〒101-0021 | Q7: キヤノンマーケティングジャパン株式会社 | AD7: №
B8: 東京都千代田区外神田１丁目１０番１１号 | AD8: 1 | AE8: 63
B9: 東京ラジオデパート | AD9: 2 | AE9: 90
B10: 東映無線株式会社 | F10: 御中 | AD10: 3 | AE10: 115
B11: 登録番号 T1010001023790 | R11: 〒108-8011 | AD11: 4 | AE11: 138
B12: 代表電話番号：03-3253-5660 担当部署：03-3527-1006 | R12: 東京都港区港南2丁目16番6号 | AD12: 5 | AE12: 168
B13: E-mail：info@asubic.com | R13: キヤノンマーケティングジャパン株式会社 | AD13: 6 | AE13: 180
B14: http://www.toeimusen.co.jp | R14: Tel. ：050-1808-7960 | AD14: 7 | AE14: 199
AD15: 8 | AE15: 214
AD16: 9 | AE16: 195
B17: =G26 -> 95468-8756-3221 | AD17: 10 | AE17: 198
AD18: 11 | AE18: 213
AD19: 12 | AE19: 230
B20: =B10 -> 東映無線株式会社 | AD20: 13 | AE20: 330
AD21: 14 | AE21: 340
B22: いつも格別のお引立てを賜り誠に有難うございます。 | AD22: 15 | AE22: 350
B23: 下記の通りご請求申し上げます。 | AD23: 16 | AE23: 390
AD24: 17 | AE24: 399
P25: お支払方法： | Q25: 下記の口座にお振込願います。 | AD25: 18 | AE25: 407
B26: お客様番号 | F26: ： | G26: 95468-8756-3221 | P26: お支払期日： | Q26: =G28 -> 45726 | AD26: 19 | AE26: 419
B27: 請求書No. | F27: ： | G27: CA03015237 | P27: お振込口座： | Q27: 三菱UFJ銀行 | AD27: 20
B28: 締日 | F28: ： | G28: 45726 | Q28: 品川駅前支店 | AD28: 21
B29: ご請求金額（税込） | F29: ： | G29: =V78 -> 36532650 | Q29: 普通口座 7412859 | AD29: 22
Q30: キヤノンマーケティングジャパン（カ | AD30: 23
AD31: 24
B32: ー商品代金明細ー | AD32: 25
B33: 取引日 | E33: =V3 -> 45718 | AD33: 26
B34: 伝票No. | E34: OM1859261574 | AD34: 27
C35: 品名 | J35: 型番【アイテム発注No.】 | P35: JAN／UPCコード | Q35: 数量 | T35: 単価 | V35: 金額 | AD35: 28
C36: SanDisk microSD Ultra 64GB | J36: SDSQUAB-064G-GN6MN | P36: 619659200473 | Q36: 500 | R36: 個 | T36: 1715 | V36: =T36*Q36 -> 857500 | AD36: 29
C37: SanDisk microSDXC Ultra 128GB UHS-I / U1 / A1 / C10 / | J37: SDSQUAB-128G-GN6MN | P37: 619659200480 | Q37: 500 | R37: 個 | T37: 2555 | V37: =T37*Q37 -> 1277500 | AD37: 30
C38: SanDisk microSD Ultra 256GB | J38: SDSQUAC-256G-GN6MN | P38: 619659200497 | Q38: 500 | R38: 個 | T38: 4445 | V38: =T38*Q38 -> 2222500 | AD38: 31
C39: SanDisk SD 512GB UHS-I / Nintendo Switch / | J39: SDSQUAC-512G-GN6MN | P39: 619659200503 | Q39: 500 | R39: 個 | T39: 8050 | V39: =T39*Q39 -> 4025000 | AD39: 32
C40: SanDisk SD 32GB U3 / Class10 / | J40: SDSQXAF-032G-GN6MN | P40: 619659177416 | Q40: 500 | R40: 個 | T40: 1785 | V40: =T40*Q40 -> 892500
C41: SanDisk microSDXC Extreme 64GB | J41: SDSQXA2-064G-GN6MA | P41: 619659169770 | Q41: 500 | R41: 個 | T41: 2093 | V41: =T41*Q41 -> 1046500
C42: SanDisk microSDXC Extreme 128GB U3 / V30 / 4K / | J42: SDSQXA1-128G-GN6MN | P42: 619659180034 | Q42: 500 | R42: 個 | T42: 2926 | V42: =T42*Q42 -> 1463000
C43: SanDisk microSD Ultra 256GB U3 / V30 / A1 / 4K / | J43: SDSQXA1-256G-GN6MN | P43: 619659180041 | Q43: 500 | R43: 個 | T43: 5530 | V43: =T43*Q43 -> 2765000
C44: SanDisk microSD Extreme 64GB 4K / | J44: SDSQXAH-064G-GN6MN | P44: 619659193416 | Q44: 500 | R44: 個 | T44: 2093 | V44: =T44*Q44 -> 1046500
C45: SanDisk microSD Extreme 128GB UHS-I / U3 / V30 / 4K / | J45: SDSQXAA-128G-GN6MN | P45: 619659188467 | Q45: 500 | R45: 個 | T45: 2926 | V45: =T45*Q45 -> 1463000
C46: SanDisk SD 256GB Nintendo Switch / | J46: SDSQXAV-256G-GN6MN | P46: 619659188511 | Q46: 500 | R46: 個 | T46: 5530 | V46: =T46*Q46 -> 2765000
C47: SanDisk microSDXC Extreme 512GB UHS-I / | J47: SDSQXAV-512G-GN6MN | P47: 619659189655 | Q47: 500 | R47: 個 | T47: 8820 | V47: =T47*Q47 -> 4410000
C48: SanDisk SDXC Ultra 64GB UHS-I / Class10 / | J48: SDSDUNB-064G-GH3NN | P48: 619659200671 | Q48: 500 | R48: 個 | T48: 1876 | V48: =T48*Q48 -> 938000
C49: SanDisk SDXC Ultra 128GB UHS-I / Class10 / | J49: SDSDUNB-128G-GH3NN | P49: 619659200107 | Q49: 500 | R49: 個 | T49: 2590 | V49: =T49*Q49 -> 1295000
C50: SanDisk SDXC Ultra 256GB UHS-I / Class10 / | J50: SDSDUNC-256G-GH3NN | P50: 619659200701 | Q50: 500 | R50: 個 | T50: 4193 | V50: =T50*Q50 -> 2096500
C51: SanDisk SDHC Extreme PRO 32GB UHS-I / U3 / V30 / C10 / 4K / | J51: SDSDXXO-032G-GN4IN | P51: 619659188689 | Q51: 500 | R51: 個 | T51: 2310 | V51: =T51*Q51 -> 1155000
... C54: SanDisk SDXC Extreme PRO 256GB UHS-I / V30 / Class10 / | J54: SDSDXXD-256G-GHJIN | P54: 619659197896 | Q54: 500 | R54: 個 | T54: 0 | V54: =T54*Q54 -> 0
C66: 売上先CD | G66: 235643-2354
C67: 売上先名 | G67: =B10 -> 東映無線株式会社
J70: ＜商品代金合計＞ | N70: お買上総額（税抜） | V70: =SUM(V36:V67) -> 33211500
N73: ご請求金額（税抜） | V73: =V70 -> 33211500
N74: （10％対象 | V74: =V73 -> 33211500
O75: 消費税等 | V75: =V73*10% -> 3321150 | W75: ）
N76: （軽減税率 8％対象
O77: 消費税等 | W77: ）
N78: ご請求金額（税込） | V78: =V73+V75 -> 36532650
B82: #…非課税または免税／＊…軽減税率対象品目／!…8％税率対象品目
B83: X…全額ご入金済／レ…一部ご入金済

Sheet 2_4_納品書JANあり 
A1: 納品書
W2: 登録番号 | X2: ： | Y2: ='2_4_請求書JANあり'!V2 -> T5010401008297
Y3: ='2_4_請求書JANあり'!V3 -> 45718
B7: ='2_4_請求書JANあり'!B7 -> 〒101-0021 | T7: キヤノンマーケティングジャパン株式会社
B8: ='2_4_請求書JANあり'!B8 -> 東京都千代田区外神田１丁目１０番１１号
B9: ='2_4_請求書JANあり'!B9 -> 東京ラジオデパート
B10: ='2_4_請求書JANあり'!B10 -> 東映無線株式会社 | I10: 御中
B11: ='2_4_請求書JANあり'!B11 -> 登録番号 T1010001023790 | U11: 108-8011
B12: ='2_4_請求書JANあり'!B12 -> 代表電話番号：03-3253-5660 担当部署：03-3527-1006 | U12: 東京都港区港南2丁目16番6号
B13: ='2_4_請求書JANあり'!B13 -> E-mail：info@asubic.com | U13: キヤノンマーケティングジャパン株式会社
B14: ='2_4_請求書JANあり'!B14 -> http://www.toeimusen.co.jp | U14: Tel. ：050-1808-7960
B19: 伝票番号 ： | F19: ： | G19: ='2_4_請求書JANあり'!E34 -> OM1859261574 | R19: 見積番号 | S19: ：
B20: 受注番号 ： | F20: ： | G20: 229637321 | R20: 注文番号 | S20: ： | T20: ='2_4_請求書JANあり'!G27 -> CA03015237
B21: 出荷日 ： | F21: ： | G21: =Y3 -> 45718 | R21: 専用伝票番号 | S21: ：
B22: 到着予定日 ： | F22: ： | G22: =G21+2 -> 45720
B24: いつも格別のお引き立てを賜り誠に有難うございます。
B25: 下記商品を納品いたします。
B27: ー商品代金明細ー
C28: 品名 | L28: 型番【アイテム発注No.】 | R28: JAN／UPCコード | T28: 数量 | W28: 単価 | Y28: 金額
C29: ='2_4_請求書JANあり'!C36 -> SanDisk microSD Ultra 64GB | L29: ='2_4_請求書JANあり'!J36 -> SDSQUAB-064G-GN6MN | R29: ='2_4_請求書JANあり'!P36 -> 619659200473 | T29: ='2_4_請求書JANあり'!Q36 -> 500 | U29: 個 | W29: ='2_4_請求書JANあり'!T36 -> 1715 | Y29: =W29*T29 -> 857500
C30: ='2_4_請求書JANあり'!C37 -> SanDisk microSDXC Ultra 128GB UHS-I / U1 / A1 / C10 / | L30: ='2_4_請求書JANあり'!J37 -> SDSQUAB-128G-GN6MN | R30: ='2_4_請求書JANあり'!P37 -> 619659200480 | T30: ='2_4_請求書JANあり'!Q37 -> 500 | U30: 個 | W30: ='2_4_請求書JANあり'!T37 -> 2555 | Y30: =W30*T30 -> 1277500
C31: ='2_4_請求書JANあり'!C38 -> SanDisk microSD Ultra 256GB | L31: ='2_4_請求書JANあり'!J38 -> SDSQUAC-256G-GN6MN | R31: ='2_4_請求書JANあり'!P38 -> 619659200497 | T31: ='2_4_請求書JANあり'!Q38 -> 500 | U31: 個 | W31: ='2_4_請求書JANあり'!T38 -> 4445 | Y31: =W31*T31 -> 2222500
C32: ='2_4_請求書JANあり'!C39 -> SanDisk SD 512GB UHS-I / Nintendo Switch / | L32: ='2_4_請求書JANあり'!J39 -> SDSQUAC-512G-GN6MN | R32: ='2_4_請求書JANあり'!P39 -> 619659200503 | T32: ='2_4_請求書JANあり'!Q39 -> 500 | U32: 個 | W32: ='2_4_請求書JANあり'!T39 -> 8050 | Y32: =W32*T32 -> 4025000
C33: ='2_4_請求書JANあり'!C40 -> SanDisk SD 32GB U3 / Class10 / | L33: ='2_4_請求書JANあり'!J40 -> SDSQXAF-032G-GN6MN | R33: ='2_4_請求書JANあり'!P40 -> 619659177416 | T33: ='2_4_請求書JANあり'!Q40 -> 500 | U33: 個 | W33: ='2_4_請求書JANあり'!T40 -> 1785 | Y33: =W33*T33 -> 892500
C34: ='2_4_請求書JANあり'!C41 -> SanDisk microSDXC Extreme 64GB | L34: ='2_4_請求書JANあり'!J41 -> SDSQXA2-064G-GN6MA | R34: ='2_4_請求書JANあり'!P41 -> 619659169770 | T34: ='2_4_請求書JANあり'!Q41 -> 500 | U34: 個 | W34: ='2_4_請求書JANあり'!T41 -> 2093 | Y34: =W34*T34 -> 1046500
C35: ='2_4_請求書JANあり'!C42 -> SanDisk microSDXC Extreme 128GB U3 / V30 / 4K / | L35: ='2_4_請求書JANあり'!J42 -> SDSQXA1-128G-GN6MN | R35: ='2_4_請求書JANあり'!P42 -> 619659180034 | T35: ='2_4_請求書JANあり'!Q42 -> 500 | U35: 個 | W35: ='2_4_請求書JANあり'!T42 -> 2926 | Y35: =W35*T35 -> 1463000
C36: ='2_4_請求書JANあり'!C43 -> SanDisk microSD Ultra 256GB U3 / V30 / A1 / 4K / | L36: ='2_4_請求書JANあり'!J43 -> SDSQXA1-256G-GN6MN | R36: ='2_4_請求書JANあり'!P43 -> 619659180041 | T36: ='2_4_請求書JANあり'!Q43 -> 500 | U36: 個 | W36: ='2_4_請求書JANあり'!T43 -> 5530 | Y36: =W36*T36 -> 2765000
C37: ='2_4_請求書JANあり'!C44 -> SanDisk microSD Extreme 64GB 4K / | L37: ='2_4_請求書JANあり'!J44 -> SDSQXAH-064G-GN6MN | R37: ='2_4_請求書JANあり'!P44 -> 619659193416 | T37: ='2_4_請求書JANあり'!Q44 -> 500 | U37: 個 | W37: ='2_4_請求書JANあり'!T44 -> 2093 | Y37: =W37*T37 -> 1046500
C38: ='2_4_請求書JANあり'!C45 -> SanDisk microSD Extreme 128GB UHS-I / U3 / V30 / 4K / | L38: ='2_4_請求書JANあり'!J45 -> SDSQXAA-128G-GN6MN | R38: ='2_4_請求書JANあり'!P45 -> 619659188467 | T38: ='2_4_請求書JANあり'!Q45 -> 500 | U38: 個 | W38: ='2_4_請求書JANあり'!T45 -> 2926 | Y38: =W38*T38 -> 1463000
C39: ='2_4_請求書JANあり'!C46 -> SanDisk SD 256GB Nintendo Switch / | L39: ='2_4_請求書JANあり'!J46 -> SDSQXAV-256G-GN6MN | R39: ='2_4_請求書JANあり'!P46 -> 619659188511 | T39: ='2_4_請求書JANあり'!Q46 -> 500 | U39: 個 | W39: ='2_4_請求書JANあり'!T46 -> 5530 | Y39: =W39*T39 -> 2765000
C40: ='2_4_請求書JANあり'!C47 -> SanDisk microSDXC Extreme 512GB UHS-I / | L40: ='2_4_請求書JANあり'!J47 -> SDSQXAV-512G-GN6MN | R40: ='2_4_請求書JANあり'!P47 -> 619659189655 | T40: ='2_4_請求書JANあり'!Q47 -> 500 | U40: 個 | W40: ='2_4_請求書JANあり'!T47 -> 8820 | Y40: =W40*T40 -> 4410000
... C47: ='2_4_請求書JANあり'!C54 -> SanDisk SDXC Extreme PRO 256GB UHS-I / V30 / Class10 / | L47: ='2_4_請求書JANあり'!J54 -> SDSDXXD-256G-GHJIN | R47: ='2_4_請求書JANあり'!P54 -> 619659197896 | T47: ='2_4_請求書JANあり'!Q54 -> 500 | U47: 個 | W47: ='2_4_請求書JANあり'!T54 -> 0 | Y47: =W47*T47 -> 0
B57: 免税または非課税商品は明細右隅に「＃」、軽減税率商品は「＊」を表示しております。
B59: ■ご発注元 | R59: ■お届け先
B60: =B10 -> 東映無線株式会社

Sheet 2_4_領収書
B2: № | C2: E0019052 | D2: 領収書 | I2: ='2_4_請求書JANあり'!G27 -> CA03015237
J3: （229637321）
H4: 注文日： | I4: ='2_4_請求書JANあり'!V3 -> 45718
B5: ='2_4_請求書JANあり'!B10 -> 東映無線株式会社 | F5: 御中 | H5: 出荷日： | I5: ='2_4_納品書JANあり '!G21 -> 45718
C8: 金額 | D8: ='2_4_請求書JANあり'!G29 -> 36532650 | G8: - | H8: (税込）
D9: 消費税率10％対象 | E9: ='2_4_請求書JANあり'!V74 -> 33211500 | G9: 消費税 | H9: ='2_4_請求書JANあり'!V75 -> 3321150
D12: 但し、キヤノンオンラインショップでのご購入代金として
D14: 上記金額領収致しました。
D15: 支払い方法：銀行振込
G16: キヤノンマーケテイングジャパン株式会社
G17: 登録番号 ： T5010401008297

Sheet 2_5_請求書JANあり 
A1: ご請求書
T2: 登録番号 | U2: ： | V2: T5010401008297
V3: 45691 | AE3: アカウント
AE4: 105
B7: 〒124-0014 | Q7: キヤノンマーケティングジャパン株式会社 | AD7: №
B8: 東京都葛飾区東四つ木4－44－1 | AD8: 1 | AE8: 63
B9: 17階1号室 | AD9: 2 | AE9: 90
B10: 東葛電子販売 | G10: 御中 | AD10: 3 | AE10: 115
R11: 〒108-8011 | AD11: 4 | AE11: 138
B12: 050-1792-1508 | R12: 東京都港区港南2丁目16番6号 | AD12: 5 | AE12: 168
B13: amazonseven1982@gmail.com | R13: キヤノンマーケティングジャパン株式会社 | AD13: 6 | AE13: 180
R14: Tel. ：050-1808-7960 | AD14: 7 | AE14: 199
AD15: 8 | AE15: 214
AD16: 9 | AE16: 195
B17: =G26 -> 95698-8646-2881 | AD17: 10 | AE17: 198
AD18: 11 | AE18: 213
AD19: 12 | AE19: 230
B20: =B10 -> 東葛電子販売 | F20: =G10 -> 御中 | AD20: 13 | AE20: 330
AD21: 14 | AE21: 340
B22: いつも格別のお引立てを賜り誠に有難うございます。 | AD22: 15 | AE22: 350
B23: 下記の通りご請求申し上げます。 | AD23: 16 | AE23: 390
AD24: 17 | AE24: 399
P25: お支払方法： | Q25: 下記の口座にお振込願います。 | AD25: 18 | AE25: 407
B26: お客様番号 | F26: ： | G26: 95698-8646-2881 | P26: お支払期日： | Q26: =G28 -> 45695 | AD26: 19 | AE26: 419
B27: 請求書No. | F27: ： | G27: CA0203634 | P27: お振込口座： | Q27: 三菱UFJ銀行 | AD27: 20
B28: 締日 | F28: ： | G28: 45695 | Q28: 品川駅前支店 | AD28: 21
B29: ご請求金額（税込） | F29: ： | G29: =V75 -> 36532650 | Q29: 普通口座 7412859 | AD29: 22
Q30: キヤノンマーケティングジャパン（カ | AD30: 23
AD31: 24
B32: ー商品代金明細ー | AD32: 25
B33: 取引日 | E33: =V3 -> 45691 | AD33: 26
B34: 伝票No. | E34: OM1859266346 | AD34: 27
C35: 品名 | K35: 型番【アイテム発注No.】 | P35: JAN／UPCコード | Q35: 数量 | T35: 単価 | V35: 金額 | AD35: 28
C36: SanDisk microSD Ultra 64GB | K36: SDSQUAB-064G-GN6MN | P36: 619659200473 | Q36: 500 | R36: 個 | T36: 1715 | V36: =T36*Q36 -> 857500 | AD36: 29
C37: SanDisk microSDXC Ultra 128GB UHS-I / U1 / A1 / C10 / | K37: SDSQUAB-128G-GN6MN | P37: 619659200480 | Q37: 500 | R37: 個 | T37: 2555 | V37: =T37*Q37 -> 1277500 | AD37: 30
C38: SanDisk microSD Ultra 256GB | K38: SDSQUAC-256G-GN6MN | P38: 619659200497 | Q38: 500 | R38: 個 | T38: 4445 | V38: =T38*Q38 -> 2222500 | AD38: 31
C39: SanDisk SD 512GB UHS-I / Nintendo Switch / | K39: SDSQUAC-512G-GN6MN | P39: 619659200503 | Q39: 500 | R39: 個 | T39: 8050 | V39: =T39*Q39 -> 4025000 | AD39: 32
C40: SanDisk SD 32GB U3 / Class10 / | K40: SDSQXAF-032G-GN6MN | P40: 619659177416 | Q40: 500 | R40: 個 | T40: 1785 | V40: =T40*Q40 -> 892500
C41: SanDisk microSDXC Extreme 64GB | K41: SDSQXA2-064G-GN6MA | P41: 619659169770 | Q41: 500 | R41: 個 | T41: 2093 | V41: =T41*Q41 -> 1046500
C42: SanDisk microSDXC Extreme 128GB U3 / V30 / 4K / | K42: SDSQXA1-128G-GN6MN | P42: 619659180034 | Q42: 500 | R42: 個 | T42: 2926 | V42: =T42*Q42 -> 1463000
C43: SanDisk microSD Ultra 256GB U3 / V30 / A1 / 4K / | K43: SDSQXA1-256G-GN6MN | P43: 619659180041 | Q43: 500 | R43: 個 | T43: 5530 | V43: =T43*Q43 -> 2765000
C44: SanDisk microSD Extreme 64GB 4K / | K44: SDSQXAH-064G-GN6MN | P44: 619659193416 | Q44: 500 | R44: 個 | T44: 2093 | V44: =T44*Q44 -> 1046500
C45: SanDisk microSD Extreme 128GB UHS-I / U3 / V30 / 4K / | K45: SDSQXAA-128G-GN6MN | P45: 619659188467 | Q45: 500 | R45: 個 | T45: 2926 | V45: =T45*Q45 -> 1463000
C46: SanDisk SD 256GB Nintendo Switch / | K46: SDSQXAV-256G-GN6MN | P46: 619659188511 | Q46: 500 | R46: 個 | T46: 5530 | V46: =T46*Q46 -> 2765000
C47: SanDisk microSDXC Extreme 512GB UHS-I / | K47: SDSQXAV-512G-GN6MN | P47: 619659189655 | Q47: 500 | R47: 個 | T47: 8820 | V47: =T47*Q47 -> 4410000
C48: SanDisk SDXC Ultra 64GB UHS-I / Class10 / | K48: SDSDUNB-064G-GH3NN | P48: 619659200671 | Q48: 500 | R48: 個 | T48: 1876 | V48: =T48*Q48 -> 938000
C49: SanDisk SDXC Ultra 128GB UHS-I / Class10 / | K49: SDSDUNB-128G-GH3NN | P49: 619659200107 | Q49: 500 | R49: 個 | T49: 2590 | V49: =T49*Q49 -> 1295000
C50: SanDisk SDXC Ultra 256GB UHS-I / Class10 / | K50: SDSDUNC-256G-GH3NN | P50: 619659200701 | Q50: 500 | R50: 個 | T50: 4193 | V50: =T50*Q50 -> 2096500
C51: SanDisk SDHC Extreme PRO 32GB UHS-I / U3 / V30 / C10 / 4K / | K51: SDSDXXO-032G-GN4IN | P51: 619659188689 | Q51: 500 | R51: 個 | T51: 2310 | V51: =T51*Q51 -> 1155000
... C54: SanDisk SDXC Extreme PRO 256GB UHS-I / V30 / Class10 / | K54: SDSDXXD-256G-GHJIN | P54: 619659197896 | Q54: 500 | R54: 個 | T54: 0 | V54: =T54*Q54 -> 0
C63: 売上先CD | G63: 236943-1548
C64: 売上先名 | G64: =B10 -> 東葛電子販売
M67: ＜商品代金合計＞ | N67: お買上総額（税抜） | V67: =SUM(V36:V64) -> 33211500
N70: ご請求金額（税抜） | V70: =V67 -> 33211500
N71: （10％対象 | V71: =V70 -> 33211500
O72: 消費税等 | V72: =V70*10% -> 3321150 | W72: ）
N73: （軽減税率 8％対象
O74: 消費税等 | W74: ）
N75: ご請求金額（税込） | V75: =V70+V72 -> 36532650
B79: #…非課税または免税／＊…軽減税率対象品目／!…8％税率対象品目
B80: X…全額ご入金済／レ…一部ご入金済

Sheet 2_5_納品書JANあり 
A1: 納品書
W2: 登録番号 | X2: ： | Y2: ='2_5_請求書JANあり '!V2 -> T5010401008297
Y3: ='2_5_請求書JANあり '!V3 -> 45691
B7: ='2_5_請求書JANあり '!B7 -> 〒124-0014 | T7: キヤノンマーケティングジャパン株式会社
B8: ='2_5_請求書JANあり '!B8 -> 東京都葛飾区東四つ木4－44－1
B9: ='2_5_請求書JANあり '!B9 -> 17階1号室
B10: ='2_5_請求書JANあり '!B10 -> 東葛電子販売 | I10: 御中
B11: ='2_5_請求書JANあり '!B11 | U11: 108-8011
B12: ='2_5_請求書JANあり '!B12 -> 050-1792-1508 | U12: 東京都港区港南2丁目16番6号
B13: ='2_5_請求書JANあり '!B13 -> amazonseven1982@gmail.com | U13: キヤノンマーケティングジャパン株式会社
B14: ='2_5_請求書JANあり '!B14 | U14: Tel. ：050-1808-7960
B19: 伝票番号 ： | F19: ： | G19: ='2_5_請求書JANあり '!E34 -> OM1859266346 | R19: 見積番号 | S19: ：
B20: 受注番号 ： | F20: ： | G20: 229637321 | R20: 注文番号 | S20: ： | T20: ='2_5_請求書JANあり '!G27 -> CA0203634
B21: 出荷日 ： | F21: ： | G21: =Y3 -> 45691 | R21: 専用伝票番号 | S21: ：
B22: 到着予定日 ： | F22: ： | G22: =G21+2 -> 45693
B24: いつも格別のお引き立てを賜り誠に有難うございます。
B25: 下記商品を納品いたします。
B27: ー商品代金明細ー
C28: 品名 | L28: 型番【アイテム発注No.】 | R28: JAN／UPCコード | T28: 数量 | W28: 単価 | Y28: 金額
C29: ='2_5_請求書JANあり '!C36 -> SanDisk microSD Ultra 64GB | L29: ='2_4_請求書JANあり'!J36 -> SDSQUAB-064G-GN6MN | R29: ='2_5_請求書JANあり '!P36 -> 619659200473 | T29: ='2_5_請求書JANあり '!Q36 -> 500 | U29: 個 | W29: ='2_5_請求書JANあり '!T36 -> 1715 | Y29: =W29*T29 -> 857500
C30: ='2_5_請求書JANあり '!C37 -> SanDisk microSDXC Ultra 128GB UHS-I / U1 / A1 / C10 / | L30: ='2_4_請求書JANあり'!J37 -> SDSQUAB-128G-GN6MN | R30: ='2_5_請求書JANあり '!P37 -> 619659200480 | T30: ='2_5_請求書JANあり '!Q37 -> 500 | U30: 個 | W30: ='2_5_請求書JANあり '!T37 -> 2555 | Y30: =W30*T30 -> 1277500
C31: ='2_5_請求書JANあり '!C38 -> SanDisk microSD Ultra 256GB | L31: ='2_4_請求書JANあり'!J38 -> SDSQUAC-256G-GN6MN | R31: ='2_5_請求書JANあり '!P38 -> 619659200497 | T31: ='2_5_請求書JANあり '!Q38 -> 500 | U31: 個 | W31: ='2_5_請求書JANあり '!T38 -> 4445 | Y31: =W31*T31 -> 2222500
C32: ='2_5_請求書JANあり '!C39 -> SanDisk SD 512GB UHS-I / Nintendo Switch / | L32: ='2_4_請求書JANあり'!J39 -> SDSQUAC-512G-GN6MN | R32: ='2_5_請求書JANあり '!P39 -> 619659200503 | T32: ='2_5_請求書JANあり '!Q39 -> 500 | U32: 個 | W32: ='2_5_請求書JANあり '!T39 -> 8050 | Y32: =W32*T32 -> 4025000
C33: ='2_5_請求書JANあり '!C40 -> SanDisk SD 32GB U3 / Class10 / | L33: ='2_4_請求書JANあり'!J40 -> SDSQXAF-032G-GN6MN | R33: ='2_5_請求書JANあり '!P40 -> 619659177416 | T33: ='2_5_請求書JANあり '!Q40 -> 500 | U33: 個 | W33: ='2_5_請求書JANあり '!T40 -> 1785 | Y33: =W33*T33 -> 892500
C34: ='2_5_請求書JANあり '!C41 -> SanDisk microSDXC Extreme 64GB | L34: ='2_4_請求書JANあり'!J41 -> SDSQXA2-064G-GN6MA | R34: ='2_5_請求書JANあり '!P41 -> 619659169770 | T34: ='2_5_請求書JANあり '!Q41 -> 500 | U34: 個 | W34: ='2_5_請求書JANあり '!T41 -> 2093 | Y34: =W34*T34 -> 1046500
C35: ='2_5_請求書JANあり '!C42 -> SanDisk microSDXC Extreme 128GB U3 / V30 / 4K / | L35: ='2_4_請求書JANあり'!J42 -> SDSQXA1-128G-GN6MN | R35: ='2_5_請求書JANあり '!P42 -> 619659180034 | T35: ='2_5_請求書JANあり '!Q42 -> 500 | U35: 個 | W35: ='2_5_請求書JANあり '!T42 -> 2926 | Y35: =W35*T35 -> 1463000
C36: ='2_5_請求書JANあり '!C43 -> SanDisk microSD Ultra 256GB U3 / V30 / A1 / 4K / | L36: ='2_4_請求書JANあり'!J43 -> SDSQXA1-256G-GN6MN | R36: ='2_5_請求書JANあり '!P43 -> 619659180041 | T36: ='2_5_請求書JANあり '!Q43 -> 500 | U36: 個 | W36: ='2_5_請求書JANあり '!T43 -> 5530 | Y36: =W36*T36 -> 2765000
C37: ='2_5_請求書JANあり '!C44 -> SanDisk microSD Extreme 64GB 4K / | L37: ='2_4_請求書JANあり'!J44 -> SDSQXAH-064G-GN6MN | R37: ='2_5_請求書JANあり '!P44 -> 619659193416 | T37: ='2_5_請求書JANあり '!Q44 -> 500 | U37: 個 | W37: ='2_5_請求書JANあり '!T44 -> 2093 | Y37: =W37*T37 -> 1046500
C38: ='2_5_請求書JANあり '!C45 -> SanDisk microSD Extreme 128GB UHS-I / U3 / V30 / 4K / | L38: ='2_4_請求書JANあり'!J45 -> SDSQXAA-128G-GN6MN | R38: ='2_5_請求書JANあり '!P45 -> 619659188467 | T38: ='2_5_請求書JANあり '!Q45 -> 500 | U38: 個 | W38: ='2_5_請求書JANあり '!T45 -> 2926 | Y38: =W38*T38 -> 1463000
C39: ='2_5_請求書JANあり '!C46 -> SanDisk SD 256GB Nintendo Switch / | L39: ='2_4_請求書JANあり'!J46 -> SDSQXAV-256G-GN6MN | R39: ='2_5_請求書JANあり '!P46 -> 619659188511 | T39: ='2_5_請求書JANあり '!Q46 -> 500 | U39: 個 | W39: ='2_5_請求書JANあり '!T46 -> 5530 | Y39: =W39*T39 -> 2765000
C40: ='2_5_請求書JANあり '!C47 -> SanDisk microSDXC Extreme 512GB UHS-I / | L40: ='2_4_請求書JANあり'!J47 -> SDSQXAV-512G-GN6MN | R40: ='2_5_請求書JANあり '!P47 -> 619659189655 | T40: ='2_5_請求書JANあり '!Q47 -> 500 | U40: 個 | W40: ='2_5_請求書JANあり '!T47 -> 8820 | Y40: =W40*T40 -> 4410000
... C47: ='2_5_請求書JANあり '!C54 -> SanDisk SDXC Extreme PRO 256GB UHS-I / V30 / Class10 / | L47: ='2_4_請求書JANあり'!J54 -> SDSDXXD-256G-GHJIN | R47: ='2_5_請求書JANあり '!P54 -> 619659197896 | T47: ='2_5_請求書JANあり '!Q54 -> 500 | U47: 個 | W47: ='2_5_請求書JANあり '!T54 -> 0 | Y47: =W47*T47 -> 0
B57: 免税または非課税商品は明細右隅に「＃」、軽減税率商品は「＊」を表示しております。
B59: ■ご発注元 | R59: ■お届け先
B60: =B10 -> 東葛電子販売

Sheet 2_5_領収書 
B2: № | C2: E0019052 | D2: 領収書 | I2: ='2_5_請求書JANあり '!G27 -> CA0203634
J3: （229637321）
H4: 注文日： | I4: ='2_5_請求書JANあり '!V3 -> 45691
B5: ='2_5_請求書JANあり '!B10 -> 東葛電子販売 | F5: 御中 | H5: 出荷日： | I5: ='2_5_納品書JANあり '!G21 -> 45691
C8: 金額 | D8: ='2_5_請求書JANあり '!G29 -> 36532650 | G8: - | H8: (税込）
D9: 消費税率10％対象 | E9: ='2_5_請求書JANあり '!V71 -> 33211500 | G9: 消費税 | H9: ='2_5_請求書JANあり '!V72 -> 3321150
D12: 但し、キヤノンオンラインショップでのご購入代金として
D14: 上記金額領収致しました。
D15: 支払い方法：銀行振込
G16: キヤノンマーケテイングジャパン株式会社
G17: 登録番号 ： T5010401008297

Sheet 2_6_請求書JANあり 手直し
A1: ご請求書
P2: 登録番号：T5010401008297
P3: 発行日 | R3: =管理!F1 -> 46097 | AA3: アカウント番号
AA4: 105
B5: 東葛電子販売 | E5: 御中
B7: 〒124-0014 | M7: キヤノンマーケティングジャパン株式会社 | Z7: №
B8: 東京都葛飾区東四つ木4－44－1 | M8: 〒108-8011 | Z8: 1 | AA8: 36 | AC8: 34
B9: 17階1号室 | M9: 東京都港区港南2丁目16番6号 | Z9: 2 | AA9: 62 | AC9: 36
Z10: 3 | AA10: 167 | AC10: 62
B11: 050-1792-1508 | Z11: 4 | AA11: 179 | AC11: 167
B12: E-mail：amazonseven1982@gmail.com | Z12: 5 | AA12: 197 | AC12: 179
Z13: 6 | AA13: 297 | AC13: 180
M14: ビジネスオンラインサポート | Z14: 7 | AA14: 302 | AC14: 195
M15: TEL：0570-08-0000 | Z15: 8 | AA15: 340 | AC15: 197
M16: （受付時間：平日9:00～17:00） ※土日祝日・年末年始は除きます。 | Z16: 9 | AA16: 373 | AC16: 198
B17: =F26 -> 95468-8756-3221 | M17: https://canon.jp | Z17: 10 | AA17: 199 | AC17: 199
Z18: 11 | AA18: 180 | AC18: 213
Z19: 12 | AA19: 214 | AC19: 214
B20: =B5 -> 東葛電子販売 | E20: 御中 | Z20: 13 | AA20: 34 | AC20: 257
Z21: 14 | AA21: 195 | AC21: 276
B22: いつも格別のお引立てを賜り誠に有難うございます。 | Z22: 15 | AA22: 257 | AC22: 297
B23: 下記の通りご請求申し上げます。 | Z23: 16 | AA23: 276 | AC23: 302
Z24: 17 | AA24: 399 | AC24: 340
L25: お支払方法： | M25: 下記の口座にお振込願います。 | Z25: 18 | AA25: 342 | AC25: 342
B26: お客様番号 | E26: ： | F26: 95468-8756-3221 | L26: お支払期日： | M26: =F28+11 -> 45747 | Z26: 19 | AA26: 374 | AC26: 373
B27: 請求書No. | E27: ： | F27: CA03015237 | L27: お振込口座： | M27: 三菱UFJ銀行 | Z27: 20 | AA27: 390 | AC27: 374
B28: 締日 | E28: ： | F28: 45736 | M28: 品川駅前支店 | Z28: 21 | AA28: 198 | AC28: 390
B29: ご請求金額（税込） | E29: ： | F29: =R70 -> 1671978 | M29: 普通口座 7412859 | Z29: 22 | AA29: 213 | AC29: 399
M30: キヤノンマーケティングジャパン（カ | Z30: 23
Z31: 24
B32: ー商品代金明細ー | Z32: 25
B33: 取引日 | D33: =管理!I1 -> 46097 | Z33: 26
B34: 伝票No. | D34: OM1859261574 | Z34: 27
C35: 品名 | I35: 型番【アイテム発注No.】 | L35: JAN／UPCコード | M35: 数量 | P35: 単価 | R35: 金額 | Z35: 28
B36: SanDisk microSD Ultra 32GB UHS-I / U1 / Class10 / Nintendo Switch / | I36: SDSQUA4-032G-GH3MA | L36: 619659201593 | M36: 0 | N36: 個 | P36: 1463 | R36: =P36*M36 -> 0 | Z36: 29
B37: SanDisk microSD Ultra 64GB UHS-I / U1 / Class10 / Nintendo Switch / | I37: SDSQUAB-064G-GH3MA | L37: 619659201586 | M37: 0 | N37: 個 | P37: 1715 | R37: =P37*M37 -> 0 | Z37: 30
B38: SanDisk microSD Extreme 32GB UHS-I / U3 / V30 / 4K / | I38: SDSQXAT-032G-GH3MA | L38: 619659197940 | M38: 0 | N38: 個 | P38: 1785 | R38: =P38*M38 -> 0 | Z38: 31
B39: SanDisk microSD Extreme 64GB UHS-I / U3 / V30 / 4K / | I39: SDSQXAH-064G-GH3MA | L39: 619659197933 | M39: 60 | N39: 個 | P39: 2093 | R39: =P39*M39 -> 125580 | Z39: 32
B40: SanDisk microSD Extreme 128GB UHS-I / U3 / V30 / 4K / | I40: SDSQXAA-128G-GH3MA | L40: 619659197926 | M40: 150 | N40: 個 | P40: 2926 | R40: =P40*M40 -> 438900
B41: SanDisk microSD High Endurance 128GB UHS-I / U3 / V30 / Class10 / ドラレコ / 監視カメラ / | I41: SDSQQNR-128G-GH3IA | L41: 619659198923 | M41: 0 | N41: 個 | P41: 3080 | R41: =P41*M41 -> 0
B42: SanDisk microSD High Endurance 256GB UHS-I / U3 / V30 / Class10 / ドラレコ / 監視カメラ / | I42: SDSQQNR-256G-GH3IA | L42: 619659198930 | M42: 0 | N42: 個 | P42: 5810 | R42: =P42*M42 -> 0
B43: SanDisk SDXC Ultra 128GB UHS-I / Class10 / | I43: SDSDUNB-128G-GH3NN | L43: 619659200107 | M43: 0 | N43: 個 | P43: 2590 | R43: =P43*M43 -> 0
B44: SanDisk SDXC Extreme 128GB UHS-I / U3 / V30 / Class10 / | I44: SDSDXVA-128G-GHJIN | L44: 619659197841 | M44: 50 | N44: 個 | P44: 3185 | R44: =P44*M44 -> 159250
B45: SanDisk microSDXC Extreme 128GB U3 / V30 / 4K / | I45: SDSQXA1-128G-GN6MN | L45: 619659180034 | M45: 0 | N45: 個 | P45: 2926 | R45: =P45*M45 -> 0
B46: SanDisk microSDXC Extreme 64GB | I46: SDSQXA2-064G-GN6MA | L46: 619659169770 | M46: 0 | N46: 個 | P46: 2093 | R46: =P46*M46 -> 0
B47: SanDisk microSD Ultra 256GB U3 / V30 / A1 / 4K / | I47: SDSQXA1-256G-GN6MN | L47: 619659180041 | M47: 0 | N47: 個 | P47: 5530 | R47: =P47*M47 -> 0
B48: SanDisk SDXC 256GB UHS-I / Class10 / | I48: SDSQUNR-256G-GN3MN | L48: 619659196516 | M48: 0 | N48: 個 | P48: 3332 | R48: =P48*M48 -> 0
B49: SanDisk microSD Extreme 64GB 4K / | I49: SDSQXAH-064G-GN6MN | L49: 619659193416 | M49: 100 | N49: 個 | P49: 2093 | R49: =P49*M49 -> 209300
B50: SanDisk microSD Extreme PRO 32GB | I50: SDSQXCG-032G-GN6MA | L50: 619659155414 | M50: 0 | N50: 個 | P50: 1750 | R50: =P50*M50 -> 0
B51: SanDisk microSDXC Extreme PRO 256GB UHS-I / U3 / V30 / 4K / | I51: SDSQXCD-256G-GN6MA | L51: 619659188542 | M51: 0 | N51: 個 | P51: 6986 | R51: =P51*M51 -> 0
... B57: SanDisk SD 256GB Nintendo Switch / | I57: SDSQXAV-256G-GN6MN | L57: 619659188511 | M57: 40 | N57: 個 | P57: 5530 | R57: =P57*M57 -> 221200
C58: 売上先CD | F58: 235643-2354
C59: 売上先名 | F59: =B5 -> 東葛電子販売
I62: ＜商品代金合計＞ | J62: お買上総額（税抜） | R62: =SUM(R36:R59) -> 1519980
J65: ご請求金額（税抜） | R65: =R62 -> 1519980
J66: （10％対象 | R66: =R65 -> 1519980
K67: 消費税等 | R67: =R65*10% -> 151998 | S67: ）
J68: （軽減税率 8％対象
K69: 消費税等 | S69: ）
J70: ご請求金額（税込） | R70: =R65+R67 -> 1671978
B74: #…非課税または免税／＊…軽減税率対象品目／!…8％税率対象品目
B75: X…全額ご入金済／レ…一部ご入金済

Sheet 2_6_納品書JANあり  手直し
A1: 納品書
W2: ='2_6_請求書JANあり 手直し'!P2 -> 登録番号：T5010401008297
W3: ='2_6_請求書JANあり 手直し'!P3 -> 発行日 | X3: ='2_6_請求書JANあり 手直し'!R3 -> 46097
B5: ='2_6_請求書JANあり 手直し'!B5 -> 東葛電子販売 | I5: 御中 | T5: キヤノンマーケティングジャパン株式会社
B7: ='2_6_請求書JANあり 手直し'!B7 -> 〒124-0014
B8: ='2_6_請求書JANあり 手直し'!B8 -> 東京都葛飾区東四つ木4－44－1
B9: ='2_6_請求書JANあり 手直し'!B9 -> 17階1号室 | T9: ='2_6_請求書JANあり 手直し'!M8 -> 〒108-8011
B10: ='2_6_請求書JANあり 手直し'!B10 | T10: ='2_6_請求書JANあり 手直し'!M9 -> 東京都港区港南2丁目16番6号
B11: ='2_6_請求書JANあり 手直し'!B11 -> 050-1792-1508
B12: ='2_6_請求書JANあり 手直し'!B12 -> E-mail：amazonseven1982@gmail.com
B13: ='2_6_請求書JANあり 手直し'!B13 | T13: ='2_6_請求書JANあり 手直し'!M14 -> ビジネスオンラインサポート
T14: ='2_6_請求書JANあり 手直し'!M15 -> TEL：0570-08-0000
T15: ='2_6_請求書JANあり 手直し'!M16 -> （受付時間：平日9:00～17:00） ※土日祝日・年末年始は除きます。
T16: ='2_6_請求書JANあり 手直し'!M17 -> https://canon.jp
B20: 伝票番号 ： | F20: ： | G20: ='2_6_請求書JANあり 手直し'!D34 -> OM1859261574 | R20: 見積番号 | S20: ：
B21: 受注番号 ： | F21: ： | G21: 229637321 | R21: 注文番号 | S21: ： | T21: ='2_6_請求書JANあり 手直し'!F27 -> CA03015237
B22: 出荷日 ： | F22: ： | G22: =X3+2 -> 46099 | R22: 専用伝票番号 | S22: ：
B23: 到着予定日 ： | F23: ： | G23: =G22+2 -> 46101
B25: いつも格別のお引き立てを賜り誠に有難うございます。
B26: 下記商品を納品いたします。
B28: ー商品代金明細ー
C29: 品名 | L29: 型番【アイテム発注No.】 | R29: JAN／UPCコード | T29: 数量 | W29: 単価 | X29: 金額
C30: ='2_6_請求書JANあり 手直し'!B36 -> SanDisk microSD Ultra 32GB UHS-I / U1 / Class10 / Nintendo Switch / | L30: ='2_6_請求書JANあり 手直し'!I36 -> SDSQUA4-032G-GH3MA | R30: ='2_6_請求書JANあり 手直し'!L36 -> 619659201593 | T30: ='2_6_請求書JANあり 手直し'!M36 -> 0 | U30: 個 | W30: ='2_6_請求書JANあり 手直し'!P36 -> 1463 | X30: ='2_6_請求書JANあり 手直し'!R36 -> 0
C31: ='2_6_請求書JANあり 手直し'!B37 -> SanDisk microSD Ultra 64GB UHS-I / U1 / Class10 / Nintendo Switch / | L31: ='2_6_請求書JANあり 手直し'!I37 -> SDSQUAB-064G-GH3MA | R31: ='2_6_請求書JANあり 手直し'!L37 -> 619659201586 | T31: ='2_6_請求書JANあり 手直し'!M37 -> 0 | U31: 個 | W31: ='2_6_請求書JANあり 手直し'!P37 -> 1715 | X31: ='2_6_請求書JANあり 手直し'!R37 -> 0
C32: ='2_6_請求書JANあり 手直し'!B38 -> SanDisk microSD Extreme 32GB UHS-I / U3 / V30 / 4K / | L32: ='2_6_請求書JANあり 手直し'!I38 -> SDSQXAT-032G-GH3MA | R32: ='2_6_請求書JANあり 手直し'!L38 -> 619659197940 | T32: ='2_6_請求書JANあり 手直し'!M38 -> 0 | U32: 個 | W32: ='2_6_請求書JANあり 手直し'!P38 -> 1785 | X32: ='2_6_請求書JANあり 手直し'!R38 -> 0
C33: ='2_6_請求書JANあり 手直し'!B39 -> SanDisk microSD Extreme 64GB UHS-I / U3 / V30 / 4K / | L33: ='2_6_請求書JANあり 手直し'!I39 -> SDSQXAH-064G-GH3MA | R33: ='2_6_請求書JANあり 手直し'!L39 -> 619659197933 | T33: ='2_6_請求書JANあり 手直し'!M39 -> 60 | U33: 個 | W33: ='2_6_請求書JANあり 手直し'!P39 -> 2093 | X33: ='2_6_請求書JANあり 手直し'!R39 -> 125580
C34: ='2_6_請求書JANあり 手直し'!B40 -> SanDisk microSD Extreme 128GB UHS-I / U3 / V30 / 4K / | L34: ='2_6_請求書JANあり 手直し'!I40 -> SDSQXAA-128G-GH3MA | R34: ='2_6_請求書JANあり 手直し'!L40 -> 619659197926 | T34: ='2_6_請求書JANあり 手直し'!M40 -> 150 | U34: 個 | W34: ='2_6_請求書JANあり 手直し'!P40 -> 2926 | X34: ='2_6_請求書JANあり 手直し'!R40 -> 438900
C35: ='2_6_請求書JANあり 手直し'!B41 -> SanDisk microSD High Endurance 128GB UHS-I / U3 / V30 / Class10 / ドラレコ / 監視カメラ / | L35: ='2_6_請求書JANあり 手直し'!I41 -> SDSQQNR-128G-GH3IA | R35: ='2_6_請求書JANあり 手直し'!L41 -> 619659198923 | T35: ='2_6_請求書JANあり 手直し'!M41 -> 0 | U35: 個 | W35: ='2_6_請求書JANあり 手直し'!P41 -> 3080 | X35: ='2_6_請求書JANあり 手直し'!R41 -> 0
C36: ='2_6_請求書JANあり 手直し'!B42 -> SanDisk microSD High Endurance 256GB UHS-I / U3 / V30 / Class10 / ドラレコ / 監視カメラ / | L36: ='2_6_請求書JANあり 手直し'!I42 -> SDSQQNR-256G-GH3IA | R36: ='2_6_請求書JANあり 手直し'!L42 -> 619659198930 | T36: ='2_6_請求書JANあり 手直し'!M42 -> 0 | U36: 個 | W36: ='2_6_請求書JANあり 手直し'!P42 -> 5810 | X36: ='2_6_請求書JANあり 手直し'!R42 -> 0
C37: ='2_6_請求書JANあり 手直し'!B43 -> SanDisk SDXC Ultra 128GB UHS-I / Class10 / | L37: ='2_6_請求書JANあり 手直し'!I43 -> SDSDUNB-128G-GH3NN | R37: ='2_6_請求書JANあり 手直し'!L43 -> 619659200107 | T37: ='2_6_請求書JANあり 手直し'!M43 -> 0 | U37: 個 | W37: ='2_6_請求書JANあり 手直し'!P43 -> 2590 | X37: ='2_6_請求書JANあり 手直し'!R43 -> 0
C38: ='2_6_請求書JANあり 手直し'!B44 -> SanDisk SDXC Extreme 128GB UHS-I / U3 / V30 / Class10 / | L38: ='2_6_請求書JANあり 手直し'!I44 -> SDSDXVA-128G-GHJIN | R38: ='2_6_請求書JANあり 手直し'!L44 -> 619659197841 | T38: ='2_6_請求書JANあり 手直し'!M44 -> 50 | U38: 個 | W38: ='2_6_請求書JANあり 手直し'!P44 -> 3185 | X38: ='2_6_請求書JANあり 手直し'!R44 -> 159250
C39: ='2_6_請求書JANあり 手直し'!B45 -> SanDisk microSDXC Extreme 128GB U3 / V30 / 4K / | L39: ='2_6_請求書JANあり 手直し'!I45 -> SDSQXA1-128G-GN6MN | R39: ='2_6_請求書JANあり 手直し'!L45 -> 619659180034 | T39: ='2_6_請求書JANあり 手直し'!M45 -> 0 | U39: 個 | W39: ='2_6_請求書JANあり 手直し'!P45 -> 2926 | X39: ='2_6_請求書JANあり 手直し'!R45 -> 0
C40: ='2_6_請求書JANあり 手直し'!B46 -> SanDisk microSDXC Extreme 64GB | L40: ='2_6_請求書JANあり 手直し'!I46 -> SDSQXA2-064G-GN6MA | R40: ='2_6_請求書JANあり 手直し'!L46 -> 619659169770 | T40: ='2_6_請求書JANあり 手直し'!M46 -> 0 | U40: 個 | W40: ='2_6_請求書JANあり 手直し'!P46 -> 2093 | X40: ='2_6_請求書JANあり 手直し'!R46 -> 0
C41: ='2_6_請求書JANあり 手直し'!B47 -> SanDisk microSD Ultra 256GB U3 / V30 / A1 / 4K / | L41: ='2_6_請求書JANあり 手直し'!I47 -> SDSQXA1-256G-GN6MN | R41: ='2_6_請求書JANあり 手直し'!L47 -> 619659180041 | T41: ='2_6_請求書JANあり 手直し'!M47 -> 0 | U41: 個 | W41: ='2_6_請求書JANあり 手直し'!P47 -> 5530 | X41: ='2_6_請求書JANあり 手直し'!R47 -> 0
... C51: ='2_6_請求書JANあり 手直し'!B57 -> SanDisk SD 256GB Nintendo Switch / | L51: ='2_6_請求書JANあり 手直し'!I57 -> SDSQXAV-256G-GN6MN | R51: ='2_6_請求書JANあり 手直し'!L57 -> 619659188511 | T51: ='2_6_請求書JANあり 手直し'!M57 -> 40 | U51: 個 | W51: ='2_6_請求書JANあり 手直し'!P57 -> 5530 | X51: ='2_6_請求書JANあり 手直し'!R57 -> 221200
B54: 免税または非課税商品は明細右隅に「＃」、軽減税率商品は「＊」を表示しております。
B56: ■ご発注元 | R56: ■お届け先
B57: =B5 -> 東葛電子販売

Sheet 2_6_領収書 手直し
B2: № | C2: E03015237 | D2: 領収書 | I2: ='2_6_請求書JANあり 手直し'!F27 -> CA03015237
J3: （653584351）
H4: 注文日： | I4: ='2_6_請求書JANあり 手直し'!R3 -> 46097
B5: 東映無線株式会社 | F5: 御中 | H5: 出荷日： | I5: ='2_6_納品書JANあり 手直し'!G22 -> 46099
C8: 金額 | D8: ='2_6_請求書JANあり 手直し'!F29 -> 1671978 | G8: - | H8: (税込）
D9: 消費税率10％対象 | E9: ='2_6_請求書JANあり 手直し'!R66 -> 1519980 | G9: 消費税 | H9: ='2_6_請求書JANあり 手直し'!R67 -> 151998
D12: 但し、ビジネスオンラインサポートでのご購入代金として
D14: 上記金額領収致しました。
D15: 支払い方法：銀行振込
G16: キヤノンマーケテイングジャパン株式会社
G17: 登録番号 ： T5010401008297

Sheet 2_7_請求書JANあり 最新
A1: ご請求書
P2: 登録番号 | R2: =VLOOKUP(管理!$C$1,管理!A4:T53,11,0) -> T2010401090562
P3: 発行日 | R3: =管理!F1 -> 46097
B5: =VLOOKUP(管理!$C$2,管理!$A$4:$V$100,2,0) -> 柏尾奏利（KASIOshop）
B7: ="〒"&VLOOKUP(管理!$C$2,管理!$A$4:$V$100,3,0) -> 〒174-0072 | M7: =VLOOKUP(管理!$C$1,管理!$A$4:$V$100,2,0) -> サンディスク合同会社
B8: =VLOOKUP(管理!$C$2,管理!$A$4:$V$100,4,0) -> 東京都板橋区南常盤台1丁目11番6号 | M8: ="〒"&VLOOKUP(管理!$C$1,管理!$A$4:$V$100,3,0) -> 〒108-0075
B9: =VLOOKUP(管理!$C$2,管理!$A$4:$V$100,5,0) -> ウエアーハウス303号室 | M9: =VLOOKUP(管理!$C$1,管理!$A$4:$V$100,4,0) -> 東京都港区港南1丁目6番31号
B10: 担当者 | D10: ="："&VLOOKUP(管理!$C$2,管理!$A$4:$V$100,9,0)&" 様" -> ：柏尾奏利 様 | M10: =IFERROR( IF(OR(VLOOKUP(管理!$C$1,管理!$A$4:$V$100,5,0)=0, VLOOKUP(管理!$C$1,管理!$A$4:$V$100,5,0)=""), "", VLOOKUP(管理!$C$1,管理!A5:T54,5,0) ), "") -> 品川東急ビル3階
B11: TEL | D11: ="："&VLOOKUP(管理!$C$2,管理!$A$4:$V$100,6,0) -> ：03-3600-3333 | M11: 担当 | N11: ="："&VLOOKUP(管理!$C$1,管理!$A$4:$V$100,9,0) -> ：0
B12: MAIL | D12: ="："&VLOOKUP(管理!$C$2,管理!$A$4:$V$100,10,0) -> ：amazonthree1982@gmail.com | M12: TEL | N12: ="："&VLOOKUP(管理!$C$1,管理!$A$4:$V$100,6,0) -> ：0120-893-009
M13: MAIL | N13: ="："&VLOOKUP(管理!$C$1,管理!$A$4:$V$100,10,0) -> ：retail_support@sandisk.com
M14: WEB | N14: ="："&VLOOKUP(管理!$C$1,管理!$A$4:$V$100,8,0) -> ：https://www.sandisk.com
B17: =F26 -> 3176-119
B20: =B5 -> 柏尾奏利（KASIOshop）
B22: いつも格別のお引立てを賜り誠に有難うございます。
B23: 下記の通りご請求申し上げます。
L25: お支払方法 | M25: 下記の口座にお振込願います。
B26: お客様番号 | E26: ： | F26: =VLOOKUP(管理!C1,管理!A4:U100,14,0) -> 3176-119 | L26: お支払期日 | M26: =管理!O1 -> 46105
B27: 請求書No. | E27: ： | F27: =VLOOKUP(管理!C1,管理!A4:U100,17,0) -> INV-260316-109 | L27: お振込口座 | M27: =VLOOKUP(管理!C1,管理!A4:U100,12,0) -> みずほ銀行 品川支店 普通7759780
B28: 締日 | E28: ： | F28: =管理!O1 -> 46105 | M28: =VLOOKUP(管理!C1,管理!A5:U101,13,0) -> サンディスク（ド
B29: ご請求金額（税込） | E29: ： | F29: =R70 -> 0
B32: ー商品代金明細ー
B33: 取引日 | D33: =管理!I1 -> 46097
B34: 伝票No. | D34: OM1859261574
C35: 品名 | I35: 型番【アイテム発注No.】 | L35: JAN／UPCコード | M35: 数量 | P35: 単価 | R35: 金額
B36: =[1]コード!$AG2 -> 0 | I36: =[1]コード!$R2 -> 9349220005039 | L36: =[1]コード!$K2 -> 0 | M36: =[1]コード!$G2 -> 0 | N36: 個 | P36: =[1]コード!$F2 -> 210 | R36: =P36*M36 -> 0
B37: =[1]コード!$AG3 -> 0 | I37: =[1]コード!$R3 -> SDSQUNS-032G-GN3MN | L37: =[1]コード!$K3 -> 619659161651 | M37: =[1]コード!$G3 -> 0 | N37: 個 | P37: =[1]コード!$F3 -> 1190 | R37: =P37*M37 -> 0
B38: =[1]コード!$AG4 -> 0 | I38: =[1]コード!$R4 -> SDSQUNS-032G-GN3MN | L38: =[1]コード!$K4 -> 619659184384 | M38: =[1]コード!$G4 -> 0 | N38: 個 | P38: =[1]コード!$F4 -> 1190 | R38: =P38*M38 -> 0
B39: =[1]コード!$AG5 -> 0 | I39: =[1]コード!$R5 -> SDSQUNS-032G-GN3MA | L39: =[1]コード!$K5 -> 619659161644 | M39: =[1]コード!$G5 -> 0 | N39: 個 | P39: =[1]コード!$F5 -> 1190 | R39: =P39*M39 -> 0
B40: =[1]コード!$AG6 -> 0 | I40: =[1]コード!$R6 -> SDSQUNB-032G-GN3MN | L40: =[1]コード!$K6 -> 619659134044 | M40: =[1]コード!$G6 -> 0 | N40: 個 | P40: =[1]コード!$F6 -> 1190 | R40: =P40*M40 -> 0
B41: =[1]コード!$AG7 -> 0 | I41: =[1]コード!$R7 -> SDSDQUA-032G-U46A | L41: =[1]コード!$K7 -> 619659078645 | M41: =[1]コード!$G7 -> 0 | N41: 個 | P41: =[1]コード!$F7 -> 1190 | R41: =P41*M41 -> 0
B42: =[1]コード!$AG8 -> 0 | I42: =[1]コード!$R8 -> 43237-2 | L42: =[1]コード!$K8 -> 068888807494, 619659246518 | M42: =[1]コード!$G8 -> 0 | N42: 個 | P42: =[1]コード!$F8 -> 2380 | R42: =P42*M42 -> 0
B43: =[1]コード!$AG9 -> 0 | I43: =[1]コード!$R9 -> SDSQUNC-032G-GN6MA | L43: =[1]コード!$K9 -> 619659134747 | M43: =[1]コード!$G9 -> 0 | N43: 個 | P43: =[1]コード!$F9 -> 11900 | R43: =P43*M43 -> 0
B44: =[1]コード!$AG10 -> 0 | I44: =[1]コード!$R10 -> SDSQUNS-064G-GHEMA | L44: =[1]コード!$K10 -> 619659172916 | M44: =[1]コード!$G10 -> 0 | N44: 個 | P44: =[1]コード!$F10 -> 1596 | R44: =P44*M44 -> 0
B45: =[1]コード!$AG11 -> SanDisk Ultra microSDXC 64GB UHS-I Class10 | I45: =[1]コード!$R11 -> SDSQUNR-064G-GN3MN | L45: =[1]コード!$K11 -> 619659185077, 799833000614 | M45: =[1]コード!$G11 -> 0 | N45: 個 | P45: =[1]コード!$F11 -> 1596 | R45: =P45*M45 -> 0
B46: =[1]コード!$AG12 -> 0 | I46: =[1]コード!$R12 -> SDSQUNS-064G-GN3MN | L46: =[1]コード!$K12 -> 619659161927 | M46: =[1]コード!$G12 -> 0 | N46: 個 | P46: =[1]コード!$F12 -> 1596 | R46: =P46*M46 -> 0
B47: =[1]コード!$AG13 -> 0 | I47: =[1]コード!$R13 -> SDSQUNC-064G-GN6MA | L47: =[1]コード!$K13 -> 619659134846 | M47: =[1]コード!$G13 -> 0 | N47: 個 | P47: =[1]コード!$F13 -> 1596 | R47: =P47*M47 -> 0
... B57: =[1]コード!$AG23 -> 0 | I57: =[1]コード!$R23 -> FBA_64-GoPro Hero 3+ | L57: =[1]コード!$K23 -> 0 | M57: =[1]コード!$G23 -> 0 | N57: 個 | P57: =[1]コード!$F23 -> 1596 | R57: =P57*M57 -> 0
C58: 売上先CD | F58: 235643-2354
C59: 売上先名 | F59: =B5 -> 柏尾奏利（KASIOshop）
I62: ＜商品代金合計＞ | J62: お買上総額（税抜） | R62: =SUM(R36:R59) -> 0
J65: ご請求金額（税抜） | R65: =R62 -> 0
J66: （10％対象 | R66: =R65 -> 0
K67: 消費税等 | R67: =R65*10% -> 0 | S67: ）
J68: （軽減税率 8％対象
K69: 消費税等 | S69: ）
J70: ご請求金額（税込） | R70: =R65+R67 -> 0
B74: #…非課税または免税／＊…軽減税率対象品目／!…8％税率対象品目
B75: X…全額ご入金済／レ…一部ご入金済

Sheet 2_7_納品書JANあり 最新
A1: 納品書
P2: ="登録番号："&VLOOKUP(管理!$C$1,管理!A4:T53,11,0) -> 登録番号：T2010401090562
P3: 発行日 | R3: =管理!F1 -> 46097
B5: =VLOOKUP(管理!$C$2,管理!$A$4:$V$100,2,0) -> 柏尾奏利（KASIOshop）
B7: ="〒"&VLOOKUP(管理!$C$2,管理!$A$4:$V$100,3,0) -> 〒174-0072 | M7: =VLOOKUP(管理!$C$1,管理!$A$4:$V$100,2,0) -> サンディスク合同会社
B8: =VLOOKUP(管理!$C$2,管理!$A$4:$V$100,4,0) -> 東京都板橋区南常盤台1丁目11番6号 | M8: ="〒"&VLOOKUP(管理!$C$1,管理!$A$4:$V$100,3,0) -> 〒108-0075
B9: =VLOOKUP(管理!$C$2,管理!$A$4:$V$100,5,0) -> ウエアーハウス303号室 | M9: =VLOOKUP(管理!$C$1,管理!$A$4:$V$100,4,0) -> 東京都港区港南1丁目6番31号
B10: 担当者 | D10: ="："&VLOOKUP(管理!$C$2,管理!$A$4:$V$100,9,0)&" 様" -> ：柏尾奏利 様 | M10: =IFERROR( IF(OR(VLOOKUP(管理!$C$1,管理!$A$4:$V$100,5,0)=0, VLOOKUP(管理!$C$1,管理!$A$4:$V$100,5,0)=""), "", VLOOKUP(管理!$C$1,管理!A5:T54,5,0) ), "") -> 品川東急ビル3階
B11: TEL | D11: ="："&VLOOKUP(管理!$C$2,管理!$A$4:$V$100,6,0) -> ：03-3600-3333 | M11: 担当 | N11: ="："&VLOOKUP(管理!$C$1,管理!$A$4:$V$100,9,0) -> ：0
B12: MAIL | D12: ="："&VLOOKUP(管理!$C$2,管理!$A$4:$V$100,10,0) -> ：amazonthree1982@gmail.com | M12: TEL | N12: ="："&VLOOKUP(管理!$C$1,管理!$A$4:$V$100,6,0) -> ：0120-893-009
M13: MAIL | N13: ="："&VLOOKUP(管理!$C$1,管理!$A$4:$V$100,10,0) -> ：retail_support@sandisk.com
M14: WEB | N14: ="："&VLOOKUP(管理!$C$1,管理!$A$4:$V$100,8,0) -> ：https://www.sandisk.com
B18: 伝票番号 | E18: ="："&'2_7_請求書JANあり 最新'!D34 -> ：OM1859261574 | L18: 見積番号
B19: 受注番号 | E19: ="："&VLOOKUP(管理!$C$2,管理!$A$4:$V$100,16,0) -> ：0 | L19: 注文番号 | M19: ='2_7_請求書JANあり 最新'!F27 -> INV-260316-109
B20: 出荷日 | E20: =管理!I1+2 -> 46099 | L20: 専用伝票番号
B21: 到着予定日 | E21: =E20+2 -> 46101
B23: いつも格別のお引き立てを賜り誠に有難うございます。
B24: 下記商品を納品いたします。
B26: ー商品代金明細ー
B27: 取引日 | D27: =R3 -> 46097
B28: 伝票No. | D28: OM1859261574
C29: 品名 | I29: 型番【アイテム発注No.】 | L29: JAN／UPCコード | M29: 数量 | P29: 単価 | R29: 金額
B30: SanDisk microSD Ultra 32GB UHS-I / U1 / Class10 / Nintendo Switch / | I30: SDSQUA4-032G-GH3MA | L30: 619659201593 | M30: 0 | N30: 個 | P30: 1463 | R30: =P30*M30 -> 0
B31: SanDisk microSD Ultra 64GB UHS-I / U1 / Class10 / Nintendo Switch / | I31: SDSQUAB-064G-GH3MA | L31: 619659201586 | M31: 0 | N31: 個 | P31: 1715 | R31: =P31*M31 -> 0
B32: SanDisk microSD Ultra 128GB UHS-I / U1 / Class10 / Nintendo Switch / | I32: SDSQUAB-128G-GH3MA | L32: 619659201579 | M32: 70 | N32: 個 | P32: 2555 | R32: =P32*M32 -> 178850
B33: SanDisk microSDXC Ultra 128GB UHS-I / U1 / A1 / C10 / | I33: SDSQUAB-128G-GN6MN | L33: 619659200480 | M33: 55 | N33: 個 | P33: 2555 | R33: =P33*M33 -> 140525
B34: SanDisk microSD Ultra 256GB UHS-I / U1 / Class10 / Nintendo Switch / | I34: SDSQUAC-256G-GH3MA | L34: 619659201555 | M34: 0 | N34: 個 | P34: 4445 | R34: =P34*M34 -> 0
B35: SanDisk microSD Ultra 512GB UHS-I / U1 / Class10 / Nintendo Switch / | I35: SDSQUAC-512G-GH3MA | L35: 619659201562 | M35: 0 | N35: 個 | P35: 8050 | R35: =P35*M35 -> 0
B36: SanDisk microSD Ultra 1TB UHS-I / U1 / Class10 / Nintendo Switch / | I36: SDSQUAC-1T00-GH3MA | L36: 619659201609 | M36: 0 | N36: 個 | P36: 15470 | R36: =P36*M36 -> 0
B37: SanDisk microSD Ultra UHS-I / U1 / Class10 / Nintendo Switch / | I37: SDSQUAC-1T50-GH3MA | L37: 619659203566 | M37: 0 | N37: 個 | P37: 17220 | R37: =P37*M37 -> 0
B38: SanDisk microSD Extreme 32GB UHS-I / U3 / V30 / 4K / | I38: SDSQXAT-032G-GH3MA | L38: 619659197940 | M38: 0 | N38: 個 | P38: 1785 | R38: =P38*M38 -> 0
B39: SanDisk microSD Extreme 64GB UHS-I / U3 / V30 / 4K / | I39: SDSQXAH-064G-GH3MA | L39: 619659197933 | M39: 60 | N39: 個 | P39: 2093 | R39: =P39*M39 -> 125580
B40: SanDisk microSD Extreme 64GB 4K / | I40: SDSQXAH-064G-GN6MN | L40: 619659193416 | M40: 100 | N40: 個 | P40: 2093 | R40: =P40*M40 -> 209300
B41: SanDisk microSD Extreme 128GB UHS-I / U3 / V30 / 4K / | I41: SDSQXAA-128G-GH3MA | L41: 619659197926 | M41: 150 | N41: 個 | P41: 2926 | R41: =P41*M41 -> 438900
B42: SanDisk microSD Extreme 128GB UHS-I / U3 / V30 / 4K / | I42: SDSQXAA-128G-GN6MN | L42: 619659188467 | M42: 125 | N42: 個 | P42: 2926 | R42: =P42*M42 -> 365750
B43: SanDisk microSD Extreme 256GB UHS-I / U3 / V30 / 4K / | I43: SDSQXAV-256G-GH3MA | L43: 619659197964 | M43: 35 | N43: 個 | P43: 5530 | R43: =P43*M43 -> 193550
B44: SanDisk SD 256GB Nintendo Switch / | I44: SDSQXAV-256G-GN6MN | L44: 619659188511 | M44: 40 | N44: 個 | P44: 5530 | R44: =P44*M44 -> 221200
B45: SanDisk microSD Extreme 512GB UHS-I / U3 / V30 / 4K / | I45: SDSQXAV-512G-GH3MA | L45: 619659197971 | M45: 20 | N45: 個 | P45: 8820 | R45: =P45*M45 -> 176400
B46: SanDisk microSD Extreme 1TB UHS-I / U3 / V30 / 4K / | I46: SDSQXAV-1T00-GH3MA | L46: 619659197957 | M46: 0 | N46: 個 | P46: 16660 | R46: =P46*M46 -> 0
B47: SanDisk microSD Extreme 2TB UHS-I / U3 / V30 / 4K / | I47: SDSQXAV-2T00-GH3MA | L47: 619659208783 | M47: 0 | N47: 個 | P47: 32620 | R47: =P47*M47 -> 0
B48: SanDisk microSD High Endurance 32GB UHS-I / U3 / V30 / Class10 / ドラレコ / 監視カメラ / | I48: SDSQQNR-032G-GH3IA | L48: 619659197704 | M48: 0 | N48: 個 | P48: 2345 | R48: =P48*M48 -> 0
B49: SanDisk microSD High Endurance 64GB UHS-I / U3 / V30 / Class10 / ドラレコ / 監視カメラ / | I49: SDSQQNR-064G-GH3IA | L49: 619659197711 | M49: 0 | N49: 個 | P49: 2485 | R49: =P49*M49 -> 0
B50: SanDisk microSD High Endurance 128GB UHS-I / U3 / V30 / Class10 / ドラレコ / 監視カメラ / | I50: SDSQQNR-128G-GH3IA | L50: 619659198923 | M50: 0 | N50: 個 | P50: 3080 | R50: =P50*M50 -> 0
B51: SanDisk microSD High Endurance 256GB UHS-I / U3 / V30 / Class10 / ドラレコ / 監視カメラ / | I51: SDSQQNR-256G-GH3IA | L51: 619659198930 | M51: 0 | N51: 個 | P51: 5810 | R51: =P51*M51 -> 0
B54: 免税または非課税商品は明細右隅に「＃」、軽減税率商品は「＊」を表示しております。
B56: ■ご発注元 | L56: ■お届け先
B57: =B5 -> 柏尾奏利（KASIOshop）

Sheet 2_7_領収書 最新
B2: № | C2: =VLOOKUP(管理!$C$2,管理!$A$4:$V$100,17,0) -> 0 | I2: ='2_7_請求書JANあり 最新'!F27 -> INV-260316-109
A3: 領収書 | J3: （653584351）
H4: 注文日： | I4: =管理!I1 -> 46097
B5: =VLOOKUP(管理!$C$2,管理!$A$4:$V$100,2,0) -> 柏尾奏利（KASIOshop） | F5: 御中 | H5: 出荷日： | I5: ='2_7_納品書JANあり 最新'!E20 -> 46099
C8: 金額 | D8: ='2_7_請求書JANあり 最新'!R70 -> 0 | G8: - | H8: (税込）
D9: 消費税率10％対象 | E9: ='2_7_請求書JANあり 最新'!R64 -> 0 | G9: 消費税 | H9: ='2_7_請求書JANあり 最新'!R67 -> 0
D12: 但し、ビジネスオンラインサポートでのご購入代金として
D14: 上記金額領収致しました。
D15: 支払い方法：銀行振込
G16: =VLOOKUP(管理!$C$1,管理!$A$4:$V$100,2,0) -> サンディスク合同会社
G17: ="登録番号："&VLOOKUP(管理!$C$1,管理!A4:T53,11,0) -> 登録番号：T2010401090562

Sheet 3_納品書
A1: 納 品 書（兼 領収書）
AF4: 46029
A6: 〒 | B6: 113-0033
A7: 東京都 | Y7: 受注番号 | AD7: 7062636
A8: 文京区本郷2丁目25-14
A9: 第一ライトビル5階 | Y9: 〒105-7529
A10: TEL：0359909456 | Y10: 東京都港区海岸一丁目7番1号
Y11: SB C＆S 株式会社
A12: 山之内 雄一 | H12: 様
Y13: TEL | AA13: 0800-111-2247
A15: この度は『トレテク！ソフトバンクセレクション』をご利用頂き、誠にありがとうございます。
A16: 以下の通り、ご注文の商品をお届け致しますのでご確認ください。
A19: 受注日 | G19: 46026 | O19: 会員自由項目
A20: 受注時間 | G20: 0.090277778 | O20: 受注明細自由項目
A21: お支払方法 | G21: クレジットカード | O21: 受注ヘッダ自由項目
A25: お届け先
A26: 〒 | B26: 113-0033 | O26: 配送方法 | W26: 佐川急便
A27: 東京都 | O27: お届け希望日
A28: 文京区本郷2丁目25-14 | O28: お届け希望時間
A29: 第一ライトビル5階 | O29: 出荷日 | W29: 46028
A30: TEL：0359909456 | O30: 次回配送予定日
A31: 山之内 雄一
A35: 商品CD | G35: 品名 | T35: 単価 | X35: 会員割引額 | AC35: 個数 | AE35: 金額
A36: 4523546 | G36: SanDisk microSD カード 256GB UHS-I U3 V30 256G | S36: 7700 | X36: 770 | AC36: 1 | AE36: =S36*AC36 -> 7700
X47: 小計 | AC47: =SUM(AE36:AG46) -> 7700
A48: 備考: | X48: 送料 | AC48: 0
X49: 会員割引 | AC49: =SUM(X36:AB46) -> 770
X50: ポイント割引 | AC50: 0
X51: クーポン割引 | AC51: 0
X52: 決済手数料 | AC52: 0
X53: 消費税（10％） | AC53: =(AC47-AC49)/(1+10%)*10% -> 630
X54: TAX
X55: 税込合計 | AC55: =AC47 -> 7700
A57: 適格請求書発行事業者登録番号：T9010403011485
A60: またのご利用を心からお待ち申し上げます。

Sheet 3_1_納品書
A1: 納 品 書（兼 領収書）
AF4: 46029
A6: 〒102-0023
A7: 東京都 | Y7: 受注番号 | AD7: 7062636
A8: 中央区日本橋本町3-9-4
A9: TEL：03-5651-7351 FAX：03-5651-7353 | Y9: 〒105-7529
A10: E-mail：m-hukuhara@hamada-dk.co.jp | Y10: 東京都港区海岸一丁目7番1号
Y11: SB C＆S 株式会社
A12: 浜田電機株式会社 御中
Y13: TEL | AA13: 0800-111-2247
A15: この度は『トレテク！ソフトバンクセレクション』をご利用頂き、誠にありがとうございます。
A16: 以下の通り、ご注文の商品をお届け致しますのでご確認ください。
A19: 受注日 | G19: 46026 | O19: 会員自由項目
A20: 受注時間 | G20: 0.090277778 | O20: 受注明細自由項目
A21: お支払方法 | G21: クレジットカード | O21: 受注ヘッダ自由項目
A25: お届け先
A26: =A6 -> 〒102-0023 | O26: 配送方法 | W26: 佐川急便
A27: =A7 -> 東京都 | O27: お届け希望日
A28: =A8 -> 中央区日本橋本町3-9-4 | O28: お届け希望時間
A29: =A9 -> TEL：03-5651-7351 FAX：03-5651-7353 | O29: 出荷日 | W29: 46028
A30: =A10 -> E-mail：m-hukuhara@hamada-dk.co.jp | O30: 次回配送予定日
A31: =A12 -> 浜田電機株式会社 御中
A35: 商品CD | G35: 品名 | S35: 単価 | X35: 会員割引額 | AC35: 個数 | AE35: 金額
A36: 0619659180034 | G36: SanDisk SDSQXA1-128G-GN6MN | S36: 1700 | AC36: 50 | AE36: =S36*AC36 -> 85000
A37: 0619659180041 | G37: SanDisk SDSQXA1-256G-GN6MN | S37: 3050 | AC37: 50 | AE37: =S37*AC37 -> 152500
A38: 0619659189655 | G38: SanDisk SDSQXA1-512G-GN6MN | S38: 5990 | AC38: 50 | AE38: =S38*AC38 -> 299500
A39: 0619659193416 | G39: SanDisk SDSQXAH-064G-GN6MN | S39: 1050 | AC39: 50 | AE39: =S39*AC39 -> 52500
A40: 0619659188467 | G40: SanDisk SDSQXAA-128G-GN6MN | S40: 1650 | AC40: 50 | AE40: =S40*AC40 -> 82500
A41: 0619659188511 | G41: SanDisk SDSQXAV-256G-GN6MN | S41: 2750 | AC41: 50 | AE41: =S41*AC41 -> 137500
A42: 4523052026218 | G42: SanDisk SDSDXWT-032G-JNJIP | S42: 5500 | AC42: 50 | AE42: =S42*AC42 -> 275000
A43: 4523052025990 | G43: SanDisk SDSDXWH-064G-JNJIPP | S43: 8800 | AC43: 50 | AE43: =S43*AC43 -> 440000
A44: 4523052025969 | G44: SanDisk SDSDXWA-128G-JNJIP | S44: 14080 | AC44: 50 | AE44: =S44*AC44 -> 704000
A45: 4523052025976 | G45: SanDisk SDSDXWA-256G-JNJIP | S45: 21780 | AC45: 50 | AE45: =S45*AC45 -> 1089000
A46: 4523052026041 | G46: SanDisk SDSDXXD-1T00-JNJIP | S46: 131780 | AC46: 20 | AE46: =S46*AC46 -> 2635600
X51: 小計 | AC51: =SUM(AE36:AG50) -> 5953100
A52: 備考: | X52: 送料 | AC52: 0
X53: 会員割引 | AC53: =SUM(X36:AB50) -> 0
X54: ポイント割引 | AC54: 0
X55: クーポン割引 | AC55: 0
X56: 決済手数料 | AC56: 0
X57: 消費税（10％） | AC57: =ROUNDDOWN(AC51/(1+10%)*10%,0) -> 541190
X58: TAX
X59: 税込合計 | AC59: =AC51 -> 5953100
A61: 適格請求書発行事業者登録番号：T9010403011485
A64: またのご利用を心からお待ち申し上げます。

Sheet 4_1_請求書
I1: 請求書№ 386-2486 | L1: 発行日： | M1: 45346
Q3: №
K4: 浜 田 電 機 株 式 会 社 | Q4: 1 | R4: 34
K5: 情報販売部 PC USEFUL | Q5: 2 | R5: 57
B6: 東京都文京区本郷２丁目２５−１４ | K6: 登録番号T6010001026302 | Q6: 3 | R6: 80
B7: 第一ライトビル 5階 | Q7: 4 | R7: 102
K8: 〒101-0021 | Q8: 5 | R8: 122
B9: 電話03-5990-9456 | K9: 東京都千代田区外神田１－９－９ | Q9: 6 | R9: 135
B10: e-mail：amazonfast1982@gmail.com | K10: 電話 03-5298-6905㈹ FAX 03-3253-5264 | Q10: 7 | R10: 146
K11: e-mail：h-shioda@hamada-dk.co.jp | Q11: 8 | R11: 149
B12: 月島電気商会 御中 | K12: web：https://www.hamada-dk.com | Q12: 9 | R12: 160
K13: 発行者 塩田 | Q13: 10 | R13: 176
B14: 下記の金額、ご請求いたします。 | Q14: 11 | R14: 188
B15: 合計金額(税込) | D15: =J62+M62 -> 2256705000 | F15: 円 | Q15: 12 | R15: 201
Q16: 13 | R16: 213
Q17: 14 | R17: 251
B18: ＜ 領収明細 > | Q18: 15 | R18: 256
Q19: 16 | R19: 262
Q20: 17 | R20: 266
A21: №/ | B21: /日付 | C21: /メーカー | D21: / 商品コード | E21: / 型番 | F21: 税率 | G21: 数 量 | H21: 単位 | I21: 単 価 | K21: 金 額 | N21: 備 考 | Q21: 18 | R21: 283
A22: 1 | B22: 45347 | C22: サンディスク | D22: ［A］ | E22: ‎SDSQUA4-032G-GH3MA | F22: 0.1 | G22: 15000 | H22: 個 | J22: 640 | M22: =G22*J22 -> 9600000 | Q22: 19 | R22: 289
A23: 2 | B23: 45347 | C23: サンディスク | D23: 0619659201586 | E23: SDSQUAB-064G-GH3MA | F23: 0.1 | G23: 15000 | H23: 個 | J23: 780 | M23: =G23*J23 -> 11700000 | Q23: 20 | R23: 297
A24: 3 | B24: 45347 | C24: サンディスク | D24: 0619659201579 | E24: ‎SDSQUAB-128G-GH3MA | F24: 0.1 | G24: 15000 | H24: 個 | J24: 1240 | M24: =G24*J24 -> 18600000 | Q24: 21 | R24: 298
A25: 4 | B25: 45347 | C25: サンディスク | D25: 0619659201555 | E25: SDSQUAC-256G-GH3MA | F25: 0.1 | G25: 15000 | H25: 個 | J25: 2280 | M25: =G25*J25 -> 34200000 | Q25: 22 | R25: 307
A26: 5 | B26: 45347 | C26: サンディスク | D26: 0619659201562 | E26: ‎SDSQUAC-512G-GH3MA | F26: 0.1 | G26: 15000 | H26: 個 | J26: 4450 | M26: =G26*J26 -> 66750000 | Q26: 23 | R26: 311
A27: 6 | B27: 45347 | C27: サンディスク | D27: 0619659201609 | E27: SDSQUAC-1T00-GH3MA | F27: 0.1 | G27: 15000 | H27: 個 | J27: 11090 | M27: =G27*J27 -> 166350000 | Q27: 24 | R27: 312
A28: 7 | B28: 45347 | C28: サンディスク | D28: 0619659203566 | E28: SDSQUAC-1T50-GN6MN | F28: 0.1 | G28: 15000 | H28: 個 | J28: 19850 | M28: =G28*J28 -> 297750000 | Q28: 25 | R28: 314
A29: 8 | B29: 45347 | C29: サンディスク | D29: 0619659197940 | E29: SDSQXAT-032G-GH3MA | F29: 0.1 | G29: 15000 | H29: 個 | J29: 990 | M29: =G29*J29 -> 14850000 | Q29: 26 | R29: 315
A30: 9 | B30: 45347 | C30: サンディスク | D30: 0619659197933 | E30: ‎SDSQXAH-064G-GH3MA | F30: 0.1 | G30: 15000 | H30: 個 | J30: 990 | M30: =G30*J30 -> 14850000 | Q30: 27 | R30: 320
A31: 10 | B31: 45347 | C31: サンディスク | D31: 0619659197926 | E31: SDSQXAA-128G-GH3MA | F31: 0.1 | G31: 15000 | H31: 個 | J31: 1630 | M31: =G31*J31 -> 24450000 | Q31: 28 | R31: 328
A32: 11 | B32: 45347 | C32: サンディスク | D32: 0619659197964 | E32: ‎SDSQXAV-256G-GH3MA | F32: 0.1 | G32: 15000 | H32: 個 | J32: 2790 | M32: =G32*J32 -> 41850000 | Q32: 29 | R32: 335
A33: 12 | B33: 45347 | C33: サンディスク | D33: 0619659197971 | E33: SDSQXAV-512G-GH3MA | F33: 0.1 | G33: 15000 | H33: 個 | J33: 5580 | M33: =G33*J33 -> 83700000 | Q33: 30 | R33: 341
... A39: 18 | B39: 45347 | C39: サンディスク | D39: 0619659197247 | E39: ‎SDSDUN4-032G-GHJNN | F39: 0.1 | G39: 15000 | H39: 個 | J39: 790 | M39: =G39*J39 -> 11850000 | Q39: 35 | R39: 242
A40: 19 | B40: 45347 | C40: サンディスク | D40: 0619659200671 | E40: ‎SDSDUNB-064G-GH3NN | F40: 0.1 | G40: 15000 | H40: 個 | J40: 1050 | M40: =G40*J40 -> 15750000 | Q40: 35
A41: 20 | B41: 45347 | C41: サンディスク | D41: 0619659200671 | E41: ‎SDSDUNB-064G-GH3NN | F41: 0.1 | G41: 15000 | H41: 個 | J41: 1050 | M41: =G41*J41 -> 15750000 | Q41: 35
A42: 21 | B42: 45347 | C42: サンディスク | D42: 0619659200107 | E42: SDSDUN4-128G-GHJNN | F42: 0.1 | G42: 15000 | H42: 個 | J42: 1770 | M42: =G42*J42 -> 26550000 | Q42: 35
A43: 22 | B43: 45347 | C43: サンディスク | D43: 0619659200701 | E43: SDSDUNC-256G-GH3NN | F43: 0.1 | G43: 15000 | H43: 個 | J43: 4000 | M43: =G43*J43 -> 60000000 | Q43: 35
A44: 23 | B44: 45347 | C44: サンディスク | D44: 0619659200701 | E44: ‎SDSDUNC-256G-GH3NN | F44: 0.1 | G44: 15000 | H44: 個 | J44: 4000 | M44: =G44*J44 -> 60000000 | Q44: 35
A45: 24 | B45: 45347 | C45: サンディスク | D45: 0619659197285 | E45: ‎SDSDUN4-512G-GHJNN | F45: 0.1 | G45: 15000 | H45: 個 | J45: 7350 | M45: =G45*J45 -> 110250000 | Q45: 35
A46: 25 | B46: 45347 | C46: サンディスク | D46: 0619659200664 | E46: ‎SDSDUNC-512G-GH3NN | F46: 0.1 | G46: 15000 | H46: 個 | J46: 7350 | M46: =G46*J46 -> 110250000 | Q46: 35
A47: 26 | B47: 45347 | C47: サンディスク | D47: 0619659197827 | E47: SDSDXVT-032G-GHJIN | F47: 0.1 | G47: 15000 | H47: 個 | J47: 1100 | M47: =G47*J47 -> 16500000 | Q47: 35
A48: 27 | B48: 45347 | C48: サンディスク | D48: 0619659197834 | E48: ‎SDSDXV2-064G-GHJIN | F48: 0.1 | G48: 15000 | H48: 個 | J48: 1290 | M48: =G48*J48 -> 19350000 | Q48: 35
A49: 28 | B49: 45347 | C49: サンディスク | D49: 0619659197841 | E49: ‎SDSDXVA-128G-GHJIN | F49: 0.1 | G49: 15000 | H49: 個 | J49: 2150 | M49: =G49*J49 -> 32250000 | Q49: 35
A50: 29 | B50: 45347 | C50: サンディスク | D50: 0619659197858 | E50: ‎SDSDXVV-256G-GHJIN | F50: 0.1 | G50: 15000 | H50: 個 | J50: 4450 | M50: =G50*J50 -> 66750000 | Q50: 35
A51: 30 | B51: 45347 | C51: サンディスク | D51: 0619659198718 | E51: SDSDXVV-512G-GHJIN | F51: 0.1 | G51: 15000 | H51: 個 | J51: 8130 | M51: =G51*J51 -> 121950000
A52: 31 | B52: 45347 | C52: サンディスク | D52: 0619659197865 | E52: ‎SDSDXXO-032G-GHJIN | F52: 0.1 | G52: 15000 | H52: 個 | J52: 1310 | M52: =G52*J52 -> 19650000
A53: 32 | B53: 45347 | C53: サンディスク | D53: 0619659197872 | E53: SDSDXXU-064G-GHJIN | F53: 0.1 | G53: 15000 | H53: 個 | J53: 1650 | M53: =G53*J53 -> 24750000
A54: 33 | B54: 45347 | C54: サンディスク | D54: 0619659197889 | E54: SDSDXXD-128G-GHJIN | F54: 0.1 | G54: 15000 | H54: 個 | J54: 2690 | M54: =G54*J54 -> 40350000
A55: 34 | B55: 45347 | C55: サンディスク | D55: 0619659197896 | E55: SDSDXXD-256G-GHJIN | F55: 0.1 | G55: 15000 | H55: 個 | J55: 5350 | M55: =G55*J55 -> 80250000
A56: 35 | B56: 45347 | C56: サンディスク | D56: 0619659201494 | E56: ‎SDSDXXU-064G-GN4IN | F56: 0.1 | G56: 15000 | H56: 個 | J56: 5650 | M56: =G56*J56 -> 84750000
A57: 36 | B57: 45347 | C57: サンディスク | D57: 0619659188542 | E57: SDSQXCD-256G-GN6MA | F57: 0.1 | G57: 15000 | H57: 個 | J57: 3590 | M57: =G57*J57 -> 53850000
M58: =G58*J58 -> 0
M59: =G59*J59 -> 0
M60: =G60*J60 -> 0
K61: =G61*I61 -> 0 | M61: =G61*J61 -> 0
I62: 合計（税抜） | J62: =SUM(K22:M57) -> 2051550000 | K62: 円 | L62: 消費税合計 | M62: =J62*10% -> 205155000 | N62: 円
I63: １０％対象 | J63: =SUM(K22:M57) -> 2051550000 | K63: 円 | L63: 消費税 | M63: =J63*10% -> 205155000 | N63: 円
I64: ８％対象 | J64: 0 | K64: 円 | L64: 消費税 | M64: 0 | N64: 円
I65: ０％対象 | J65: 0 | K65: 円 | L65: 消費税 | M65: 0 | N65: 円
I66: ※軽減税率対象
B69: 備考欄：指定銀行口座に支払い

Sheet 4_1_領収書
I1: No： | J1: 150-93996 | L1: 発行日： | M1: 45347
Q3: №
K4: 浜 田 電 機 株 式 会 社 | Q4: 1 | R4: 34
K5: 情報販売部 PC USEFUL | Q5: 2 | R5: 57
B6: 東京都文京区本郷２丁目２５−１４ | K6: 登録番号T6010001026302 | Q6: 3 | R6: 80
B7: 第一ライトビル 5階 | Q7: 4 | R7: 102
K8: 〒101-0021 | Q8: 5 | R8: 122
B9: 電話03-5990-9456 | K9: 東京都千代田区外神田１－９－９ | Q9: 6 | R9: 135
B10: e-mail：amazonfast1982@gmail.com | K10: 電話 03-5298-6905㈹ FAX 03-3253-5264 | Q10: 7 | R10: 146
K11: e-mail：h-shioda@hamada-dk.co.jp | Q11: 8 | R11: 149
B12: 月島電気商会 御中 | K12: web：https://www.hamada-dk.com | Q12: 9 | R12: 160
K13: 発行者 塩田 | Q13: 10 | R13: 176
B14: 下記の金額、正に領収いたしました。 | Q14: 11 | R14: 188
B15: 合計金額(税込) | D15: =J62+M62 -> 2256705000 | F15: 円 | Q15: 12 | R15: 201
Q16: 13 | R16: 213
Q17: 14 | R17: 251
B18: ＜ 領収明細 > | Q18: 15 | R18: 256
Q19: 16 | R19: 262
Q20: 17 | R20: 266
A21: №/ | B21: /日付 | C21: /メーカー | D21: / 商品コード | E21: / 型番 | F21: 税率 | G21: 数 量 | H21: 単位 | I21: 単 価 | K21: 金 額 | N21: 備 考 | Q21: 18 | R21: 283
A22: 1 | B22: 45322 | C22: サンディスク | D22: ［A］ | E22: ‎SDSQUA4-032G-GH3MA | F22: 0.1 | G22: 15000 | H22: 個 | J22: 640 | M22: =G22*J22 -> 9600000 | Q22: 19 | R22: 289
A23: 2 | B23: 45322 | C23: サンディスク | D23: 0619659201586 | E23: SDSQUAB-064G-GH3MA | F23: 0.1 | G23: 15000 | H23: 個 | J23: 780 | M23: =G23*J23 -> 11700000 | Q23: 20 | R23: 297
A24: 3 | B24: 45322 | C24: サンディスク | D24: 0619659201579 | E24: ‎SDSQUAB-128G-GH3MA | F24: 0.1 | G24: 15000 | H24: 個 | J24: 1240 | M24: =G24*J24 -> 18600000 | Q24: 21 | R24: 298
A25: 4 | B25: 45322 | C25: サンディスク | D25: 0619659201555 | E25: SDSQUAC-256G-GH3MA | F25: 0.1 | G25: 15000 | H25: 個 | J25: 2280 | M25: =G25*J25 -> 34200000 | Q25: 22 | R25: 307
A26: 5 | B26: 45322 | C26: サンディスク | D26: 0619659201562 | E26: ‎SDSQUAC-512G-GH3MA | F26: 0.1 | G26: 15000 | H26: 個 | J26: 4450 | M26: =G26*J26 -> 66750000 | Q26: 23 | R26: 311
A27: 6 | B27: 45322 | C27: サンディスク | D27: 0619659201609 | E27: SDSQUAC-1T00-GH3MA | F27: 0.1 | G27: 15000 | H27: 個 | J27: 11090 | M27: =G27*J27 -> 166350000 | Q27: 24 | R27: 312
A28: 7 | B28: 45322 | C28: サンディスク | D28: 0619659203566 | E28: SDSQUAC-1T50-GN6MN | F28: 0.1 | G28: 15000 | H28: 個 | J28: 19850 | M28: =G28*J28 -> 297750000 | Q28: 25 | R28: 314
A29: 8 | B29: 45322 | C29: サンディスク | D29: 0619659197940 | E29: SDSQXAT-032G-GH3MA | F29: 0.1 | G29: 15000 | H29: 個 | J29: 990 | M29: =G29*J29 -> 14850000 | Q29: 26 | R29: 315
A30: 9 | B30: 45322 | C30: サンディスク | D30: 0619659197933 | E30: ‎SDSQXAH-064G-GH3MA | F30: 0.1 | G30: 15000 | H30: 個 | J30: 990 | M30: =G30*J30 -> 14850000 | Q30: 27 | R30: 320
A31: 10 | B31: 45322 | C31: サンディスク | D31: 0619659197926 | E31: SDSQXAA-128G-GH3MA | F31: 0.1 | G31: 15000 | H31: 個 | J31: 1630 | M31: =G31*J31 -> 24450000 | Q31: 28 | R31: 328
A32: 11 | B32: 45322 | C32: サンディスク | D32: 0619659197964 | E32: ‎SDSQXAV-256G-GH3MA | F32: 0.1 | G32: 15000 | H32: 個 | J32: 2790 | M32: =G32*J32 -> 41850000 | Q32: 29 | R32: 335
A33: 12 | B33: 45322 | C33: サンディスク | D33: 0619659197971 | E33: SDSQXAV-512G-GH3MA | F33: 0.1 | G33: 15000 | H33: 個 | J33: 5580 | M33: =G33*J33 -> 83700000 | Q33: 30 | R33: 341
... A39: 18 | B39: 45322 | C39: サンディスク | D39: 0619659197247 | E39: ‎SDSDUN4-032G-GHJNN | F39: 0.1 | G39: 15000 | H39: 個 | J39: 790 | M39: =G39*J39 -> 11850000 | Q39: 35 | R39: 242
A40: 19 | B40: 45322 | C40: サンディスク | D40: 0619659200671 | E40: ‎SDSDUNB-064G-GH3NN | F40: 0.1 | G40: 15000 | H40: 個 | J40: 1050 | M40: =G40*J40 -> 15750000 | Q40: 35
A41: 20 | B41: 45322 | C41: サンディスク | D41: 0619659200671 | E41: ‎SDSDUNB-064G-GH3NN | F41: 0.1 | G41: 15000 | H41: 個 | J41: 1050 | M41: =G41*J41 -> 15750000 | Q41: 35
A42: 21 | B42: 45322 | C42: サンディスク | D42: 0619659200107 | E42: SDSDUN4-128G-GHJNN | F42: 0.1 | G42: 15000 | H42: 個 | J42: 1770 | M42: =G42*J42 -> 26550000 | Q42: 35
A43: 22 | B43: 45322 | C43: サンディスク | D43: 0619659200701 | E43: SDSDUNC-256G-GH3NN | F43: 0.1 | G43: 15000 | H43: 個 | J43: 4000 | M43: =G43*J43 -> 60000000 | Q43: 35
A44: 23 | B44: 45322 | C44: サンディスク | D44: 0619659200701 | E44: ‎SDSDUNC-256G-GH3NN | F44: 0.1 | G44: 15000 | H44: 個 | J44: 4000 | M44: =G44*J44 -> 60000000 | Q44: 35
A45: 24 | B45: 45322 | C45: サンディスク | D45: 0619659197285 | E45: ‎SDSDUN4-512G-GHJNN | F45: 0.1 | G45: 15000 | H45: 個 | J45: 7350 | M45: =G45*J45 -> 110250000 | Q45: 35
A46: 25 | B46: 45322 | C46: サンディスク | D46: 0619659200664 | E46: ‎SDSDUNC-512G-GH3NN | F46: 0.1 | G46: 15000 | H46: 個 | J46: 7350 | M46: =G46*J46 -> 110250000 | Q46: 35
A47: 26 | B47: 45322 | C47: サンディスク | D47: 0619659197827 | E47: SDSDXVT-032G-GHJIN | F47: 0.1 | G47: 15000 | H47: 個 | J47: 1100 | M47: =G47*J47 -> 16500000 | Q47: 35
A48: 27 | B48: 45322 | C48: サンディスク | D48: 0619659197834 | E48: ‎SDSDXV2-064G-GHJIN | F48: 0.1 | G48: 15000 | H48: 個 | J48: 1290 | M48: =G48*J48 -> 19350000 | Q48: 35
A49: 28 | B49: 45322 | C49: サンディスク | D49: 0619659197841 | E49: ‎SDSDXVA-128G-GHJIN | F49: 0.1 | G49: 15000 | H49: 個 | J49: 2150 | M49: =G49*J49 -> 32250000 | Q49: 35
A50: 29 | B50: 45322 | C50: サンディスク | D50: 0619659197858 | E50: ‎SDSDXVV-256G-GHJIN | F50: 0.1 | G50: 15000 | H50: 個 | J50: 4450 | M50: =G50*J50 -> 66750000 | Q50: 35
A51: 30 | B51: 45322 | C51: サンディスク | D51: 0619659198718 | E51: SDSDXVV-512G-GHJIN | F51: 0.1 | G51: 15000 | H51: 個 | J51: 8130 | M51: =G51*J51 -> 121950000
A52: 31 | B52: 45322 | C52: サンディスク | D52: 0619659197865 | E52: ‎SDSDXXO-032G-GHJIN | F52: 0.1 | G52: 15000 | H52: 個 | J52: 1310 | M52: =G52*J52 -> 19650000
A53: 32 | B53: 45322 | C53: サンディスク | D53: 0619659197872 | E53: SDSDXXU-064G-GHJIN | F53: 0.1 | G53: 15000 | H53: 個 | J53: 1650 | M53: =G53*J53 -> 24750000
A54: 33 | B54: 45322 | C54: サンディスク | D54: 0619659197889 | E54: SDSDXXD-128G-GHJIN | F54: 0.1 | G54: 15000 | H54: 個 | J54: 2690 | M54: =G54*J54 -> 40350000
A55: 34 | B55: 45322 | C55: サンディスク | D55: 0619659197896 | E55: SDSDXXD-256G-GHJIN | F55: 0.1 | G55: 15000 | H55: 個 | J55: 5350 | M55: =G55*J55 -> 80250000
A56: 35 | B56: 45322 | C56: サンディスク | D56: 0619659201494 | E56: ‎SDSDXXU-064G-GN4IN | F56: 0.1 | G56: 15000 | H56: 個 | J56: 5650 | M56: =G56*J56 -> 84750000
A57: 36 | B57: 45322 | C57: サンディスク | D57: 0619659188542 | E57: SDSQXCD-256G-GN6MA | F57: 0.1 | G57: 15000 | H57: 個 | J57: 3590 | M57: =G57*J57 -> 53850000
M58: =G58*J58 -> 0
M59: =G59*J59 -> 0
M60: =G60*J60 -> 0
K61: =G61*I61 -> 0 | M61: =G61*J61 -> 0
I62: 合計（税抜） | J62: =SUM(K22:M57) -> 2051550000 | K62: 円 | L62: 消費税合計 | M62: =J62*10% -> 205155000 | N62: 円
I63: １０％対象 | J63: =SUM(K22:M57) -> 2051550000 | K63: 円 | L63: 消費税 | M63: =J63*10% -> 205155000 | N63: 円
I64: ８％対象 | J64: 0 | K64: 円 | L64: 消費税 | M64: 0 | N64: 円
I65: ０％対象 | J65: 0 | K65: 円 | L65: 消費税 | M65: 0 | N65: 円
I66: ※軽減税率対象
B69: 備考欄： | D69: 請求書№ 386-2486
B71: ※適格請求書

Sheet 4_2_請求書
D1: 請求書
B3: 東京電子販売 御中 | E3: 納品日 | G3: 45629 | N3: 業者№ | P3: 商品№
B4: 1130033 | E4: 納品書番号 | G4: DEL-0000000001 | M4: №1 | N4: 3 | O4: №1 | P4: 34
B5: 東京都文京区本郷2-25-14 | E5: 登録番号 | G5: T6010001026302 | M5: №2 | O5: №2 | P5: 57
B6: 第一ライトビル5階 | M6: №3 | O6: №3 | P6: 80
B7: 03-5990-9456 | M7: №4 | O7: №4 | P7: 102
E8: 浜田電機株式会社 | M8: №5 | O8: №5 | P8: 122
M9: №6 | O9: №6 | P9: 135
E10: 住所:〒101-0021 東京都千代田区外神田1-9-9 | M10: №7 | O10: №7 | P10: 146
E11: TEL:03-5298-6905 FAX:03-32535264 | M11: №8 | O11: №8 | P11: 150
B12: 下記の通り納品致します。 | E12: http://www.akibadirect.com | M12: №9 | O12: №9 | P12: 161
B13: 件名 | C13: 2023年11月発注分 | E13: h-shioda@hamada-dk.co.jp | M13: №10 | O13: №10 | P13: 177
B14: 小計 | C14: 消費税 | D14: 合計金額 | M14: №11 | O14: №11 | P14: 189
B15: 1,624,200円 | C15: 162,420円 | D15: 1,786,620円 | M15: №12 | O15: №12 | P15: 203
M16: №13 | O16: №13 | P16: 214
B17: 摘要 | E17: 数量 | F17: 単価 | G17: 明細金額 | M17: №14 | O17: №14 | P17: 253
B18: =M27&N27&O27&P27&Q27 -> SanDisk 商品型番：SDSQUA4-032G-GH3MA 商品コード：0619659184162 | E18: 500個 | F18: 1299 | G18: 649500 | M18: №15 | O18: №15 | P18: 258
B19: =M28&N28&O28&P28&Q28 -> SanDisk 商品型番：SDSQUAB-064G-GH3MA 商品コード：0619659200473 | E19: 250個 | F19: 2499 | G19: 624750 | M19: №16 | O19: №16 | P19: 263
B20: =M29&N29&O29&P29&Q29 -> SanDisk 商品型番：SDSQUAB-128G-GH3MA 商品コード：0619659200480 | E20: 50個 | F20: 6999 | G20: 349950
B21: =M30&N30&O30&P30&Q30 -> SanDisk 商品型番：SDSQUAC-256G-GH3MA 商品コード：0619659200497 | E21: 51個
B22: =M31&N31&O31&P31&Q31 -> SanDisk 商品型番：SDSQUAC-512G-GH3MA 商品コード：0619659200503 | E22: 52個
B23: =M32&N32&O32&P32&Q32 -> SanDisk 商品型番：SDSQUAC-1T00-GH3MA 商品コード：0619659200510 | E23: 53個
B24: =M33&N33&O33&P33&Q33 -> SanDisk 商品型番：SDSQUAC-1T50-GH3MA 商品コード：0619659208035 | E24: 54個
B25: =M34&N34&O34&P34&Q34 -> SanDisk 商品型番：SDSQXAT-032G-GH3MA 商品コード：0619659177416 | E25: 55個
B26: =M35&N35&O35&P35&Q35 -> SanDisk 商品型番：SDSQXAH-064G-GH3MA 商品コード：0619659193416 | E26: 56個
B27: =M36&N36&O36&P36&Q36 -> SanDisk 商品型番：SDSQXAA-128G-GH3MA 商品コード：0619659188467 | E27: 57個 | M27: SanDisk | N27: 商品型番： | O27: SDSQUA4-032G-GH3MA | P27: 商品コード： | Q27: 0619659184162
B28: =M37&N37&O37&P37&Q37 -> SanDisk 商品型番：SDSQXAV-256G-GH3MA 商品コード：0619659188511 | E28: 58個 | M28: SanDisk | N28: 商品型番： | O28: SDSQUAB-064G-GH3MA | P28: 商品コード： | Q28: 0619659200473
B29: =M38&N38&O38&P38&Q38 -> SanDisk 商品型番：SDSQXAV-512G-GH3MA 商品コード：0619659189655 | E29: 59個 | M29: SanDisk | N29: 商品型番： | O29: SDSQUAB-128G-GH3MA | P29: 商品コード： | Q29: 0619659200480
B30: =M39&N39&O39&P39&Q39 -> SanDisk 商品型番：SDSQXAV-1T00-GH3MA 商品コード：0619659188481 | E30: 60個 | M30: SanDisk | N30: 商品型番： | O30: SDSQUAC-256G-GH3MA | P30: 商品コード： | Q30: 0619659200497
B31: =M40&N40&O40&P40&Q40 -> SanDisk 商品型番：SDSQQNR-032G-GH3IA 商品コード：0619659173067 | E31: 61個 | M31: SanDisk | N31: 商品型番： | O31: SDSQUAC-512G-GH3MA | P31: 商品コード： | Q31: 0619659200503
B32: =M41&N41&O41&P41&Q41 -> SanDisk 商品型番：SDSQQNR-064G-GH3IA 商品コード：0619659173081 | E32: 62個 | M32: SanDisk | N32: 商品型番： | O32: SDSQUAC-1T00-GH3MA | P32: 商品コード： | Q32: 0619659200510
B33: =M42&N42&O42&P42&Q42 -> SanDisk 商品型番：SDSQQNR-128G-GH3IA 商品コード：0619659173104 | E33: 63個 | M33: SanDisk | N33: 商品型番： | O33: SDSQUAC-1T50-GH3MA | P33: 商品コード： | Q33: 0619659208035
M34: SanDisk | N34: 商品型番： | O34: SDSQXAT-032G-GH3MA | P34: 商品コード： | Q34: 0619659177416
E35: 内訳 10％対象（税抜） | G35: 1,624,200円 | M35: SanDisk | N35: 商品型番： | O35: SDSQXAH-064G-GH3MA | P35: 商品コード： | Q35: 0619659193416
E36: 10％消費税 | G36: 162,420円 | M36: SanDisk | N36: 商品型番： | O36: SDSQXAA-128G-GH3MA | P36: 商品コード： | Q36: 0619659188467
M37: SanDisk | N37: 商品型番： | O37: SDSQXAV-256G-GH3MA | P37: 商品コード： | Q37: 0619659188511
B38: 備考 | M38: SanDisk | N38: 商品型番： | O38: SDSQXAV-512G-GH3MA | P38: 商品コード： | Q38: 0619659189655
M39: SanDisk | N39: 商品型番： | O39: SDSQXAV-1T00-GH3MA | P39: 商品コード： | Q39: 0619659188481
M40: SanDisk | N40: 商品型番： | O40: SDSQQNR-032G-GH3IA | P40: 商品コード： | Q40: 0619659173067
M41: SanDisk | N41: 商品型番： | O41: SDSQQNR-064G-GH3IA | P41: 商品コード： | Q41: 0619659173081
M42: SanDisk | N42: 商品型番： | O42: SDSQQNR-128G-GH3IA | P42: 商品コード： | Q42: 0619659173104

Sheet 4_2_納品書
D1: 納品書
B3: 東京電子販売 御中 | E3: 納品日 | G3: 45629 | N3: 業者№ | P3: 商品№
B4: 1130033 | E4: 納品書番号 | G4: DEL-0000000001 | M4: №1 | N4: 3 | O4: №1 | P4: 34
B5: 東京都文京区本郷2-25-14 | E5: 登録番号 | G5: T6010001026302 | M5: №2 | O5: №2 | P5: 57
B6: 第一ライトビル5階 | M6: №3 | O6: №3 | P6: 80
B7: 03-5990-9456 | M7: №4 | O7: №4 | P7: 102
E8: 浜田電機株式会社 | M8: №5 | O8: №5 | P8: 122
M9: №6 | O9: №6 | P9: 135
E10: 住所:〒101-0021 東京都千代田区外神田1-9-9 | M10: №7 | O10: №7 | P10: 146
E11: TEL:03-5298-6905 FAX:03-32535264 | M11: №8 | O11: №8 | P11: 150
B12: 下記の通り納品致します。 | E12: http://www.akibadirect.com | M12: №9 | O12: №9 | P12: 161
B13: 件名 | C13: 2023年11月発注分 | E13: h-shioda@hamada-dk.co.jp | M13: №10 | O13: №10 | P13: 177
B14: 小計 | C14: 消費税 | D14: 合計金額 | M14: №11 | O14: №11 | P14: 189
B15: 1,624,200円 | C15: 162,420円 | D15: 1,786,620円 | M15: №12 | O15: №12 | P15: 203
M16: №13 | O16: №13 | P16: 214
B17: 摘要 | E17: 数量 | F17: 単価 | G17: 明細金額 | M17: №14 | O17: №14 | P17: 253
B18: =M27&N27&O27&P27&Q27 -> SanDisk 商品型番：SDSQUA4-032G-GH3MA 商品コード：0619659184162 | E18: 500個 | F18: 1299 | G18: 649500 | M18: №15 | O18: №15 | P18: 258
B19: =M28&N28&O28&P28&Q28 -> SanDisk 商品型番：SDSQUAB-064G-GH3MA 商品コード：0619659200473 | E19: 250個 | F19: 2499 | G19: 624750 | M19: №16 | O19: №16 | P19: 263
B20: =M29&N29&O29&P29&Q29 -> SanDisk 商品型番：SDSQUAB-128G-GH3MA 商品コード：0619659200480 | E20: 50個 | F20: 6999 | G20: 349950
B21: =M30&N30&O30&P30&Q30 -> SanDisk 商品型番：SDSQUAC-256G-GH3MA 商品コード：0619659200497 | E21: 51個
B22: =M31&N31&O31&P31&Q31 -> SanDisk 商品型番：SDSQUAC-512G-GH3MA 商品コード：0619659200503 | E22: 52個
B23: =M32&N32&O32&P32&Q32 -> SanDisk 商品型番：SDSQUAC-1T00-GH3MA 商品コード：0619659200510 | E23: 53個
B24: =M33&N33&O33&P33&Q33 -> SanDisk 商品型番：SDSQUAC-1T50-GH3MA 商品コード：0619659208035 | E24: 54個
B25: =M34&N34&O34&P34&Q34 -> SanDisk 商品型番：SDSQXAT-032G-GH3MA 商品コード：0619659177416 | E25: 55個
B26: =M35&N35&O35&P35&Q35 -> SanDisk 商品型番：SDSQXAH-064G-GH3MA 商品コード：0619659193416 | E26: 56個
B27: =M36&N36&O36&P36&Q36 -> SanDisk 商品型番：SDSQXAA-128G-GH3MA 商品コード：0619659188467 | E27: 57個 | M27: SanDisk | N27: 商品型番： | O27: SDSQUA4-032G-GH3MA | P27: 商品コード： | Q27: 0619659184162
B28: =M37&N37&O37&P37&Q37 -> SanDisk 商品型番：SDSQXAV-256G-GH3MA 商品コード：0619659188511 | E28: 58個 | M28: SanDisk | N28: 商品型番： | O28: SDSQUAB-064G-GH3MA | P28: 商品コード： | Q28: 0619659200473
B29: =M38&N38&O38&P38&Q38 -> SanDisk 商品型番：SDSQXAV-512G-GH3MA 商品コード：0619659189655 | E29: 59個 | M29: SanDisk | N29: 商品型番： | O29: SDSQUAB-128G-GH3MA | P29: 商品コード： | Q29: 0619659200480
B30: =M39&N39&O39&P39&Q39 -> SanDisk 商品型番：SDSQXAV-1T00-GH3MA 商品コード：0619659188481 | E30: 60個 | M30: SanDisk | N30: 商品型番： | O30: SDSQUAC-256G-GH3MA | P30: 商品コード： | Q30: 0619659200497
B31: =M40&N40&O40&P40&Q40 -> SanDisk 商品型番：SDSQQNR-032G-GH3IA 商品コード：0619659173067 | E31: 61個 | M31: SanDisk | N31: 商品型番： | O31: SDSQUAC-512G-GH3MA | P31: 商品コード： | Q31: 0619659200503
B32: =M41&N41&O41&P41&Q41 -> SanDisk 商品型番：SDSQQNR-064G-GH3IA 商品コード：0619659173081 | E32: 62個 | M32: SanDisk | N32: 商品型番： | O32: SDSQUAC-1T00-GH3MA | P32: 商品コード： | Q32: 0619659200510
B33: =M42&N42&O42&P42&Q42 -> SanDisk 商品型番：SDSQQNR-128G-GH3IA 商品コード：0619659173104 | E33: 63個 | M33: SanDisk | N33: 商品型番： | O33: SDSQUAC-1T50-GH3MA | P33: 商品コード： | Q33: 0619659208035
M34: SanDisk | N34: 商品型番： | O34: SDSQXAT-032G-GH3MA | P34: 商品コード： | Q34: 0619659177416
E35: 内訳 10％対象（税抜） | G35: 1,624,200円 | M35: SanDisk | N35: 商品型番： | O35: SDSQXAH-064G-GH3MA | P35: 商品コード： | Q35: 0619659193416
E36: 10％消費税 | G36: 162,420円 | M36: SanDisk | N36: 商品型番： | O36: SDSQXAA-128G-GH3MA | P36: 商品コード： | Q36: 0619659188467
M37: SanDisk | N37: 商品型番： | O37: SDSQXAV-256G-GH3MA | P37: 商品コード： | Q37: 0619659188511
B38: 備考 | M38: SanDisk | N38: 商品型番： | O38: SDSQXAV-512G-GH3MA | P38: 商品コード： | Q38: 0619659189655
M39: SanDisk | N39: 商品型番： | O39: SDSQXAV-1T00-GH3MA | P39: 商品コード： | Q39: 0619659188481
M40: SanDisk | N40: 商品型番： | O40: SDSQQNR-032G-GH3IA | P40: 商品コード： | Q40: 0619659173067
M41: SanDisk | N41: 商品型番： | O41: SDSQQNR-064G-GH3IA | P41: 商品コード： | Q41: 0619659173081
M42: SanDisk | N42: 商品型番： | O42: SDSQQNR-128G-GH3IA | P42: 商品コード： | Q42: 0619659173104

Sheet 4_3_請求書
A1: 請求書
A2: 東京電子販売 御中 | D2: 請求日 | F2: 2023-11-15
A3: 1130033 | D3: 請求書番号 | F3: INV-0000002023-967
A4: 東京都文京区本郷2-25-14 | D4: 登録番号 | F4: T6010001026302
A5: 第一ライトビル5階
A6: 03-5990-9456
A7: 営業部
D8: 浜田電機株式会社
D10: 住所：〒101-0021 東京都千代田区外神田1-9-9
D11: TEL：03-5298-6905 FAX：03-32535264
A12: 下記の通りご請求申し上げます。 | D12: http://www.akibadirect.com
A13: 件名 | B13: 2023年11月発注分 | D13: h-shioda@hamada-dk.co.jp
A14: 小計 | B14: 消費税 | C14: 請求金額
A15: 1,624,200円 | B15: 162,420円 | C15: 1,786,620円
A17: 入金期日 | B17: 振込先
A18: 45250 | B18: みずほ銀行 神田支店 普通7014121
B20: 摘要 | D20: 数量 | E20: 単価 | F20: 明細金額
A21: メーカーSanDisk 型番SDSQXAA-128G-GH3MA | D21: 500個 | E21: 1299 | F21: 649500
A22: メーカーSanDisk 型番SDSDXDK-032G-GHJIN | D22: 250個 | E22: 2499 | F22: 624750
A23: メーカーSanDisk 型番SDSQXCZ-1T00-GN6MA | D23: 50個 | E23: 6999 | F23: 349950
D38: 内訳 10％対象（税抜） | F38: 1,624,200円
D39: 10％消費税 | F39: 162,420円
A41: 備考

Sheet 4_3_納品書
C1: 納品書
A3: 東京電子販売 御中 | D3: 納品日 2024-12-03
A4: 営業部 | D4: 納品書番号 DEL-0000000001
A5: 水品 | D5: 登録番号 T6010001026302
A6: 1130033
A7: 東京都文京区本郷2-25-14
A8: 第一ライトビル5階 | D8: 浜田電機株式会社
A9: 03-5990-9456
D10: 住所:〒101-0021 東京都千代田区外神田1-9-9
D11: TEL:03-5298-6905 FAX:03-32535264
A12: 下記の通り納品致します。 | D12: http://www.akibadirect.com
A13: 件名 | B13: 2023年11月発注分 | D13: h-shioda@hamada-dk.co.jp
A14: 小計 | B14: 消費税 | C14: 合計金額
A15: 1,624,200円 | B15: 162,420円 | C15: 1,786,620円
A17: 摘要 | D17: 数量 | E17: 単価 | F17: 明細金額
A18: メーカーSanDisk 型番SDSQXAA-128G-GH3MA | D18: 500個 | E18: 1299 | F18: 649500
A19: メーカーSanDisk 型番SDSDXDK-032G-GHJIN | D19: 250個 | E19: 2499 | F19: 624750
A20: メーカーSanDisk 型番SDSQXCZ-1T00-GN6MA | D20: 50個 | E20: 6999 | F20: 349950
D35: 内訳 10％対象（税抜） | F35: 1,624,200円
D36: 10％消費税 | F36: 162,420円
A38: 備考

Sheet 4_3_領収書
C1: 領収書
A3: 東京電子販売 御中 | D3: 領収日 2024-12-01
A4: 1130033 | D4: 領収書番号 DEL-0000000001
A5: 東京都文京区本郷2-25-14 | D5: 登録番号 T6010001026302
A6: 第一ライトビル5階
A7: 03-5990-9456
A8: 営業部 | D8: 浜田電機株式会社
A9: 水品
D10: 住所:〒101-0021 東京都千代田区外神田1-9-9
D11: TEL:03-5298-6905 FAX:03-32535264
D12: http://www.akibadirect.com
A13: 件名 | B13: 2023年11月発注分 | D13: h-shioda@hamada-dk.co.jp
A14: 小計 | B14: 消費税 | C14: 合計金額
A15: 1,624,200円 | B15: 162,420円 | C15: 1,786,620円
A17: 摘要 | D17: 数量 | E17: 単価 | F17: 明細金額
A18: メーカーSanDisk 型番SDSQXAA-128G-GH3MA | D18: 500個 | E18: 1299 | F18: 649500
A19: メーカーSanDisk 型番SDSDXDK-032G-GHJIN | D19: 250個 | E19: 2499 | F19: 624750
A20: メーカーSanDisk 型番SDSQXCZ-1T00-GN6MA | D20: 50個 | E20: 6999 | F20: 349950
D35: 内訳 10％対象（税抜） | F35: 1,624,200円
D36: 10％消費税 | F36: 162,420円
A38: 備考

Sheet 4_4_請求書
AY2: 伝票内容設定
A3: 請 求 書 | AY3: 発行日 年 | AZ3: 2024
AY4: 発行日 月 | AZ4: 7
AY5: 発行日 日 | AZ5: 29
